Workbook

Sheet Detail5-4214658
A1: current_tier | B1: month | C1: initiated_by_org_id | D1: activation_month | E1: total_payments | F1: ach_payments | G1: tpv | H1: total_revenue | I1: ach_fees | J1: core_gross_profit_wo_loss | K1: core_gp | L1: loss | M1: sub_gp | N1: Total GP | O1: Opp Create Date | P1: Opp Create Month | Q1: Count GP?
A2: Melio Basic | B2: 46023 | C2: 4214658 | D2: 45962 | E2: 67 | F2: 67 | G2: 141628.32 | H2: 0 | J2: -9.8331 | K2: -9.8331 | L2: 0 | N2: -9.8331 | O2: 45973 | P2: 45962 | Q2: Yes

Sheet Detail4-4117067
A1: current_tier | B1: month | C1: initiated_by_org_id | D1: activation_month | E1: total_payments | F1: ach_payments | G1: tpv | H1: total_revenue | I1: ach_fees | J1: core_gross_profit_wo_loss | K1: core_gp | L1: loss | M1: sub_gp | N1: Total GP | O1: Opp Create Date | P1: Opp Create Month | Q1: Count GP?
A2: Melio Unlimited Ach | B2: 46023 | C2: 4117067 | D2: 45992 | E2: 575 | F2: 575 | G2: 2880932.6 | H2: 1057.7422 | I2: 0.5 | J2: 973.2603 | K2: 973.2603 | L2: 0 | M2: 6.4 | N2: 979.6603 | O2: 45831 | P2: 45809 | Q2: Yes

Sheet Current Calendar Quarter Stats
G1: AP Status | H1: AR Status | I1: AP/AR Status | J1: Opportunity Owner | K1: Account Name | L1: Estimated Monthly GP | M1: Expected Ramp Complete Month | N1: Close Date | O1: Total Orgs | P1: =COUNTIF(A2:A1000,">=0") -> 168 | R1: LAST DATA PULL: | S1: 46201 | U1: Ramp Start Date
G2: {=iferror(XLOOKUP(A2,'Download of SFDC Activation Rep'!B:B,'Download of SFDC Activation Rep'!H:H),"")} -> Active | H2: {=iferror(xlookup(A2,'Download of SFDC Activation Rep'!B:B,'Download of SFDC Activation Rep'!L:L),"")} | I2: =IF(or(G2="Active",H2="Active"),"Active","Not Active") -> Active | J2: {=iferror(XLOOKUP(A2,'Download of SFDC Activation Rep'!B:B,'Download of SFDC Activation Rep'!X:X),"")} -> Kate Olivares | K2: {=iferror(XLOOKUP(A2,'Download of SFDC Activation Rep'!B:B,'Download of SFDC Activation Rep'!C:C),"")} -> Net Conversion | L2: {=iferror(XLOOKUP(A2,'Download of SFDC Activation Rep'!B:B,'Download of SFDC Activation Rep'!S:S),"")} -> 400 | M2: {=iferror(XLOOKUP(A2,'Download of SFDC Activation Rep'!B:B,'Download of SFDC Activation Rep'!Z:Z)+150,"")} -> 45981 | N2: {=iferror(XLOOKUP(A2,'Download of SFDC Activation Rep'!B:B,'Download of SFDC Activation Rep'!Y:Y),"")} -> 45992 | O2: Total Active Orgs | P2: =COUNTIF(I:I,"Active") -> 148 | U2: =IF(M2="", "", EOMONTH(M2, -5) + 1) -> 45839
G3: {=iferror(XLOOKUP(A3,'Download of SFDC Activation Rep'!B:B,'Download of SFDC Activation Rep'!H:H),"")} -> Active | H3: {=iferror(xlookup(A3,'Download of SFDC Activation Rep'!B:B,'Download of SFDC Activation Rep'!L:L),"")} | I3: =IF(or(G3="Active",H3="Active"),"Active","Not Active") -> Active | J3: {=iferror(XLOOKUP(A3,'Download of SFDC Activation Rep'!B:B,'Download of SFDC Activation Rep'!X:X),"")} -> Matthew Frost | K3: {=iferror(XLOOKUP(A3,'Download of SFDC Activation Rep'!B:B,'Download of SFDC Activation Rep'!C:C),"")} -> Solutions Group International, Inc. | L3: {=iferror(XLOOKUP(A3,'Download of SFDC Activation Rep'!B:B,'Download of SFDC Activation Rep'!S:S),"")} -> 155.65 | M3: {=iferror(XLOOKUP(A3,'Download of SFDC Activation Rep'!B:B,'Download of SFDC Activation Rep'!Z:Z)+150,"")} -> 46178 | N3: {=iferror(XLOOKUP(A3,'Download of SFDC Activation Rep'!B:B,'Download of SFDC Activation Rep'!Y:Y),"")} -> 46079 | Q3: =(TODAY() - EOMONTH(TODAY(), -MOD(MONTH(TODAY())-1,3)-1)) / (EOMONTH(TODAY(), -MOD(MONTH(TODAY())-1,3)+2)+1 - (EOMONTH(TODAY(), -MOD(MONTH(TODAY())-1,3)-1)+1)) -> 0.98901099 | R3: of way through quarter | U3: =IF(M3="", "", EOMONTH(M3, -5) + 1) -> 46054
G4: {=iferror(XLOOKUP(A4,'Download of SFDC Activation Rep'!B:B,'Download of SFDC Activation Rep'!H:H),"")} -> Active | H4: {=iferror(xlookup(A4,'Download of SFDC Activation Rep'!B:B,'Download of SFDC Activation Rep'!L:L),"")} | I4: =IF(or(G4="Active",H4="Active"),"Active","Not Active") -> Active | J4: {=iferror(XLOOKUP(A4,'Download of SFDC Activation Rep'!B:B,'Download of SFDC Activation Rep'!X:X),"")} -> Matthew Frost | K4: {=iferror(XLOOKUP(A4,'Download of SFDC Activation Rep'!B:B,'Download of SFDC Activation Rep'!C:C),"")} -> National Rural Health Association | L4: {=iferror(XLOOKUP(A4,'Download of SFDC Activation Rep'!B:B,'Download of SFDC Activation Rep'!S:S),"")} -> 128.1 | M4: {=iferror(XLOOKUP(A4,'Download of SFDC Activation Rep'!B:B,'Download of SFDC Activation Rep'!Z:Z)+150,"")} -> 46111 | N4: {=iferror(XLOOKUP(A4,'Download of SFDC Activation Rep'!B:B,'Download of SFDC Activation Rep'!Y:Y),"")} -> 46013 | O4: Avg Monthly TPV for Group | P4: =P15/(3*Q3) -> 18436255 | Q4: =(TODAY() - EOMONTH(TODAY(), -MOD(MONTH(TODAY())-1,3)-1)) / (EOMONTH(TODAY(), -MOD(MONTH(TODAY())-1,3)+2)+1 - (EOMONTH(TODAY(), -MOD(MONTH(TODAY())-1,3)-1)+1)) -> 0.98901099 | U4: =IF(M4="", "", EOMONTH(M4, -5) + 1) -> 45962
G5: {=iferror(XLOOKUP(A5,'Download of SFDC Activation Rep'!B:B,'Download of SFDC Activation Rep'!H:H),"")} -> Active | H5: {=iferror(xlookup(A5,'Download of SFDC Activation Rep'!B:B,'Download of SFDC Activation Rep'!L:L),"")} | I5: =IF(or(G5="Active",H5="Active"),"Active","Not Active") -> Active | J5: {=iferror(XLOOKUP(A5,'Download of SFDC Activation Rep'!B:B,'Download of SFDC Activation Rep'!X:X),"")} -> Arianna Modesti | K5: {=iferror(XLOOKUP(A5,'Download of SFDC Activation Rep'!B:B,'Download of SFDC Activation Rep'!C:C),"")} -> HTT Cardmax Company | L5: {=iferror(XLOOKUP(A5,'Download of SFDC Activation Rep'!B:B,'Download of SFDC Activation Rep'!S:S),"")} -> 671.95 | M5: {=iferror(XLOOKUP(A5,'Download of SFDC Activation Rep'!B:B,'Download of SFDC Activation Rep'!Z:Z)+150,"")} -> 46347 | N5: {=iferror(XLOOKUP(A5,'Download of SFDC Activation Rep'!B:B,'Download of SFDC Activation Rep'!Y:Y),"")} -> 46361 | O5: Avg Monthly GP for Group | P5: =P13/(3*Q3) -> 24284.269 | U5: =IF(M5="", "", EOMONTH(M5, -5) + 1) -> 46204
G6: {=iferror(XLOOKUP(A6,'Download of SFDC Activation Rep'!B:B,'Download of SFDC Activation Rep'!H:H),"")} -> Active | H6: {=iferror(xlookup(A6,'Download of SFDC Activation Rep'!B:B,'Download of SFDC Activation Rep'!L:L),"")} | I6: =IF(or(G6="Active",H6="Active"),"Active","Not Active") -> Active | J6: {=iferror(XLOOKUP(A6,'Download of SFDC Activation Rep'!B:B,'Download of SFDC Activation Rep'!X:X),"")} -> Matthew Frost | K6: {=iferror(XLOOKUP(A6,'Download of SFDC Activation Rep'!B:B,'Download of SFDC Activation Rep'!C:C),"")} -> Toland Construction - MO | L6: {=iferror(XLOOKUP(A6,'Download of SFDC Activation Rep'!B:B,'Download of SFDC Activation Rep'!S:S),"")} -> 287 | M6: {=iferror(XLOOKUP(A6,'Download of SFDC Activation Rep'!B:B,'Download of SFDC Activation Rep'!Z:Z)+150,"")} -> 46031 | N6: {=iferror(XLOOKUP(A6,'Download of SFDC Activation Rep'!B:B,'Download of SFDC Activation Rep'!Y:Y),"")} -> 45889 | U6: =IF(M6="", "", EOMONTH(M6, -5) + 1) -> 45901
G7: {=iferror(XLOOKUP(A7,'Download of SFDC Activation Rep'!B:B,'Download of SFDC Activation Rep'!H:H),"")} -> Active | H7: {=iferror(xlookup(A7,'Download of SFDC Activation Rep'!B:B,'Download of SFDC Activation Rep'!L:L),"")} | I7: =IF(or(G7="Active",H7="Active"),"Active","Not Active") -> Active | J7: {=iferror(XLOOKUP(A7,'Download of SFDC Activation Rep'!B:B,'Download of SFDC Activation Rep'!X:X),"")} -> Arianna Modesti | K7: {=iferror(XLOOKUP(A7,'Download of SFDC Activation Rep'!B:B,'Download of SFDC Activation Rep'!C:C),"")} -> DataLinks LLC | L7: {=iferror(XLOOKUP(A7,'Download of SFDC Activation Rep'!B:B,'Download of SFDC Activation Rep'!S:S),"")} -> 315.9 | M7: {=iferror(XLOOKUP(A7,'Download of SFDC Activation Rep'!B:B,'Download of SFDC Activation Rep'!Z:Z)+150,"")} -> 46320 | N7: {=iferror(XLOOKUP(A7,'Download of SFDC Activation Rep'!B:B,'Download of SFDC Activation Rep'!Y:Y),"")} -> 46258 | O7: Avg Monthly GP per Org | P7: =(P13/P1)/(3*Q3) -> 144.54922 | U7: =IF(M7="", "", EOMONTH(M7, -5) + 1) -> 46174
G8: {=iferror(XLOOKUP(A8,'Download of SFDC Activation Rep'!B:B,'Download of SFDC Activation Rep'!H:H),"")} -> Active | H8: {=iferror(xlookup(A8,'Download of SFDC Activation Rep'!B:B,'Download of SFDC Activation Rep'!L:L),"")} | I8: =IF(or(G8="Active",H8="Active"),"Active","Not Active") -> Active | J8: {=iferror(XLOOKUP(A8,'Download of SFDC Activation Rep'!B:B,'Download of SFDC Activation Rep'!X:X),"")} -> Matthew Frost | K8: {=iferror(XLOOKUP(A8,'Download of SFDC Activation Rep'!B:B,'Download of SFDC Activation Rep'!C:C),"")} -> Hendersonville Community Co-Op | L8: {=iferror(XLOOKUP(A8,'Download of SFDC Activation Rep'!B:B,'Download of SFDC Activation Rep'!S:S),"")} -> 171 | M8: {=iferror(XLOOKUP(A8,'Download of SFDC Activation Rep'!B:B,'Download of SFDC Activation Rep'!Z:Z)+150,"")} -> 46041 | N8: {=iferror(XLOOKUP(A8,'Download of SFDC Activation Rep'!B:B,'Download of SFDC Activation Rep'!Y:Y),"")} -> 46029 | U8: =IF(M8="", "", EOMONTH(M8, -5) + 1) -> 45901
G9: {=iferror(XLOOKUP(A9,'Download of SFDC Activation Rep'!B:B,'Download of SFDC Activation Rep'!H:H),"")} -> Active | H9: {=iferror(xlookup(A9,'Download of SFDC Activation Rep'!B:B,'Download of SFDC Activation Rep'!L:L),"")} | I9: =IF(or(G9="Active",H9="Active"),"Active","Not Active") -> Active | J9: {=iferror(XLOOKUP(A9,'Download of SFDC Activation Rep'!B:B,'Download of SFDC Activation Rep'!X:X),"")} -> Kate Olivares | K9: {=iferror(XLOOKUP(A9,'Download of SFDC Activation Rep'!B:B,'Download of SFDC Activation Rep'!C:C),"")} -> Expert Semiconductor Technology, inc | L9: {=iferror(XLOOKUP(A9,'Download of SFDC Activation Rep'!B:B,'Download of SFDC Activation Rep'!S:S),"")} -> 292.51 | M9: {=iferror(XLOOKUP(A9,'Download of SFDC Activation Rep'!B:B,'Download of SFDC Activation Rep'!Z:Z)+150,"")} -> 45968 | N9: {=iferror(XLOOKUP(A9,'Download of SFDC Activation Rep'!B:B,'Download of SFDC Activation Rep'!Y:Y),"")} -> 45859 | O9: Avg TPV per Org per Month | P9: =P15/P1/(3*Q3) -> 109739.61 | U9: =IF(M9="", "", EOMONTH(M9, -5) + 1) -> 45839
G10: {=iferror(XLOOKUP(A10,'Download of SFDC Activation Rep'!B:B,'Download of SFDC Activation Rep'!H:H),"")} -> Active | H10: {=iferror(xlookup(A10,'Download of SFDC Activation Rep'!B:B,'Download of SFDC Activation Rep'!L:L),"")} | I10: =IF(or(G10="Active",H10="Active"),"Active","Not Active") -> Active | J10: {=iferror(XLOOKUP(A10,'Download of SFDC Activation Rep'!B:B,'Download of SFDC Activation Rep'!X:X),"")} -> Rudy Maestas | K10: {=iferror(XLOOKUP(A10,'Download of SFDC Activation Rep'!B:B,'Download of SFDC Activation Rep'!C:C),"")} -> megg mining llc | L10: {=iferror(XLOOKUP(A10,'Download of SFDC Activation Rep'!B:B,'Download of SFDC Activation Rep'!S:S),"")} -> 665 | M10: {=iferror(XLOOKUP(A10,'Download of SFDC Activation Rep'!B:B,'Download of SFDC Activation Rep'!Z:Z)+150,"")} -> 46074 | N10: {=iferror(XLOOKUP(A10,'Download of SFDC Activation Rep'!B:B,'Download of SFDC Activation Rep'!Y:Y),"")} -> 46055 | U10: =IF(M10="", "", EOMONTH(M10, -5) + 1) -> 45931
G11: {=iferror(XLOOKUP(A11,'Download of SFDC Activation Rep'!B:B,'Download of SFDC Activation Rep'!H:H),"")} -> Active | H11: {=iferror(xlookup(A11,'Download of SFDC Activation Rep'!B:B,'Download of SFDC Activation Rep'!L:L),"")} -> Active | I11: =IF(or(G11="Active",H11="Active"),"Active","Not Active") -> Active | J11: {=iferror(XLOOKUP(A11,'Download of SFDC Activation Rep'!B:B,'Download of SFDC Activation Rep'!X:X),"")} -> Matthew Frost | K11: {=iferror(XLOOKUP(A11,'Download of SFDC Activation Rep'!B:B,'Download of SFDC Activation Rep'!C:C),"")} -> Scale Foundations Inc. | L11: {=iferror(XLOOKUP(A11,'Download of SFDC Activation Rep'!B:B,'Download of SFDC Activation Rep'!S:S),"")} -> 312.17 | M11: {=iferror(XLOOKUP(A11,'Download of SFDC Activation Rep'!B:B,'Download of SFDC Activation Rep'!Z:Z)+150,"")} -> 46178 | N11: {=iferror(XLOOKUP(A11,'Download of SFDC Activation Rep'!B:B,'Download of SFDC Activation Rep'!Y:Y),"")} -> 46086 | U11: =IF(M11="", "", EOMONTH(M11, -5) + 1) -> 46054
G12: {=iferror(XLOOKUP(A12,'Download of SFDC Activation Rep'!B:B,'Download of SFDC Activation Rep'!H:H),"")} -> Active | H12: {=iferror(xlookup(A12,'Download of SFDC Activation Rep'!B:B,'Download of SFDC Activation Rep'!L:L),"")} | I12: =IF(or(G12="Active",H12="Active"),"Active","Not Active") -> Active | J12: {=iferror(XLOOKUP(A12,'Download of SFDC Activation Rep'!B:B,'Download of SFDC Activation Rep'!X:X),"")} -> Arianna Modesti | K12: {=iferror(XLOOKUP(A12,'Download of SFDC Activation Rep'!B:B,'Download of SFDC Activation Rep'!C:C),"")} -> Kloris LLC | L12: {=iferror(XLOOKUP(A12,'Download of SFDC Activation Rep'!B:B,'Download of SFDC Activation Rep'!S:S),"")} -> 385 | M12: {=iferror(XLOOKUP(A12,'Download of SFDC Activation Rep'!B:B,'Download of SFDC Activation Rep'!Z:Z)+150,"")} -> 46286 | N12: {=iferror(XLOOKUP(A12,'Download of SFDC Activation Rep'!B:B,'Download of SFDC Activation Rep'!Y:Y),"")} -> 46244 | U12: =IF(M12="", "", EOMONTH(M12, -5) + 1) -> 46143
G13: {=iferror(XLOOKUP(A13,'Download of SFDC Activation Rep'!B:B,'Download of SFDC Activation Rep'!H:H),"")} -> Active | H13: {=iferror(xlookup(A13,'Download of SFDC Activation Rep'!B:B,'Download of SFDC Activation Rep'!L:L),"")} | I13: =IF(or(G13="Active",H13="Active"),"Active","Not Active") -> Active | J13: {=iferror(XLOOKUP(A13,'Download of SFDC Activation Rep'!B:B,'Download of SFDC Activation Rep'!X:X),"")} -> Kate Olivares | K13: {=iferror(XLOOKUP(A13,'Download of SFDC Activation Rep'!B:B,'Download of SFDC Activation Rep'!C:C),"")} -> Liberty Land Management LLC | L13: {=iferror(XLOOKUP(A13,'Download of SFDC Activation Rep'!B:B,'Download of SFDC Activation Rep'!S:S),"")} -> 0 | M13: {=iferror(XLOOKUP(A13,'Download of SFDC Activation Rep'!B:B,'Download of SFDC Activation Rep'!Z:Z)+150,"")} -> 46124 | N13: {=iferror(XLOOKUP(A13,'Download of SFDC Activation Rep'!B:B,'Download of SFDC Activation Rep'!Y:Y),"")} -> 45933 | O13: Total GP Generated | P13: =SUM(B:B) -> 72052.227 | U13: =IF(M13="", "", EOMONTH(M13, -5) + 1) -> 45992
G14: {=iferror(XLOOKUP(A14,'Download of SFDC Activation Rep'!B:B,'Download of SFDC Activation Rep'!H:H),"")} -> Active | H14: {=iferror(xlookup(A14,'Download of SFDC Activation Rep'!B:B,'Download of SFDC Activation Rep'!L:L),"")} | I14: =IF(or(G14="Active",H14="Active"),"Active","Not Active") -> Active | J14: {=iferror(XLOOKUP(A14,'Download of SFDC Activation Rep'!B:B,'Download of SFDC Activation Rep'!X:X),"")} -> Kate Olivares | K14: {=iferror(XLOOKUP(A14,'Download of SFDC Activation Rep'!B:B,'Download of SFDC Activation Rep'!C:C),"")} -> United Home Care LLC | L14: {=iferror(XLOOKUP(A14,'Download of SFDC Activation Rep'!B:B,'Download of SFDC Activation Rep'!S:S),"")} -> 96.47 | M14: {=iferror(XLOOKUP(A14,'Download of SFDC Activation Rep'!B:B,'Download of SFDC Activation Rep'!Z:Z)+150,"")} -> 45989 | N14: {=iferror(XLOOKUP(A14,'Download of SFDC Activation Rep'!B:B,'Download of SFDC Activation Rep'!Y:Y),"")} -> 45841 | U14: =IF(M14="", "", EOMONTH(M14, -5) + 1) -> 45839
G15: {=iferror(XLOOKUP(A15,'Download of SFDC Activation Rep'!B:B,'Download of SFDC Activation Rep'!H:H),"")} -> Active | H15: {=iferror(xlookup(A15,'Download of SFDC Activation Rep'!B:B,'Download of SFDC Activation Rep'!L:L),"")} | I15: =IF(or(G15="Active",H15="Active"),"Active","Not Active") -> Active | J15: {=iferror(XLOOKUP(A15,'Download of SFDC Activation Rep'!B:B,'Download of SFDC Activation Rep'!X:X),"")} -> Arianna Modesti | K15: {=iferror(XLOOKUP(A15,'Download of SFDC Activation Rep'!B:B,'Download of SFDC Activation Rep'!C:C),"")} -> Naz Apparel | L15: {=iferror(XLOOKUP(A15,'Download of SFDC Activation Rep'!B:B,'Download of SFDC Activation Rep'!S:S),"")} -> 452.7 | M15: {=iferror(XLOOKUP(A15,'Download of SFDC Activation Rep'!B:B,'Download of SFDC Activation Rep'!Z:Z)+150,"")} -> 46347 | N15: {=iferror(XLOOKUP(A15,'Download of SFDC Activation Rep'!B:B,'Download of SFDC Activation Rep'!Y:Y),"")} -> 46361 | O15: Total TPV Generated | P15: =SUM(D:D) -> 54700977 | U15: =IF(M15="", "", EOMONTH(M15, -5) + 1) -> 46204
G16: {=iferror(XLOOKUP(A16,'Download of SFDC Activation Rep'!B:B,'Download of SFDC Activation Rep'!H:H),"")} -> Active | H16: {=iferror(xlookup(A16,'Download of SFDC Activation Rep'!B:B,'Download of SFDC Activation Rep'!L:L),"")} | I16: =IF(or(G16="Active",H16="Active"),"Active","Not Active") -> Active | J16: {=iferror(XLOOKUP(A16,'Download of SFDC Activation Rep'!B:B,'Download of SFDC Activation Rep'!X:X),"")} -> Kate Olivares | K16: {=iferror(XLOOKUP(A16,'Download of SFDC Activation Rep'!B:B,'Download of SFDC Activation Rep'!C:C),"")} -> CDT Construction | L16: {=iferror(XLOOKUP(A16,'Download of SFDC Activation Rep'!B:B,'Download of SFDC Activation Rep'!S:S),"")} -> 338.01 | M16: {=iferror(XLOOKUP(A16,'Download of SFDC Activation Rep'!B:B,'Download of SFDC Activation Rep'!Z:Z)+150,"")} -> 45989 | N16: {=iferror(XLOOKUP(A16,'Download of SFDC Activation Rep'!B:B,'Download of SFDC Activation Rep'!Y:Y),"")} -> 45877 | U16: =IF(M16="", "", EOMONTH(M16, -5) + 1) -> 45839
G17: {=iferror(XLOOKUP(A17,'Download of SFDC Activation Rep'!B:B,'Download of SFDC Activation Rep'!H:H),"")} -> Active | H17: {=iferror(xlookup(A17,'Download of SFDC Activation Rep'!B:B,'Download of SFDC Activation Rep'!L:L),"")} | I17: =IF(or(G17="Active",H17="Active"),"Active","Not Active") -> Active | J17: {=iferror(XLOOKUP(A17,'Download of SFDC Activation Rep'!B:B,'Download of SFDC Activation Rep'!X:X),"")} -> Matthew Frost | K17: {=iferror(XLOOKUP(A17,'Download of SFDC Activation Rep'!B:B,'Download of SFDC Activation Rep'!C:C),"")} -> Kenneth Adam Designs | L17: {=iferror(XLOOKUP(A17,'Download of SFDC Activation Rep'!B:B,'Download of SFDC Activation Rep'!S:S),"")} -> 435 | M17: {=iferror(XLOOKUP(A17,'Download of SFDC Activation Rep'!B:B,'Download of SFDC Activation Rep'!Z:Z)+150,"")} -> 46177 | N17: {=iferror(XLOOKUP(A17,'Download of SFDC Activation Rep'!B:B,'Download of SFDC Activation Rep'!Y:Y),"")} -> 46043 | U17: =IF(M17="", "", EOMONTH(M17, -5) + 1) -> 46054
G18: {=iferror(XLOOKUP(A18,'Download of SFDC Activation Rep'!B:B,'Download of SFDC Activation Rep'!H:H),"")} -> Active | H18: {=iferror(xlookup(A18,'Download of SFDC Activation Rep'!B:B,'Download of SFDC Activation Rep'!L:L),"")} | I18: =IF(or(G18="Active",H18="Active"),"Active","Not Active") -> Active | J18: {=iferror(XLOOKUP(A18,'Download of SFDC Activation Rep'!B:B,'Download of SFDC Activation Rep'!X:X),"")} -> Matthew Frost | K18: {=iferror(XLOOKUP(A18,'Download of SFDC Activation Rep'!B:B,'Download of SFDC Activation Rep'!C:C),"")} -> St George Spirits | L18: {=iferror(XLOOKUP(A18,'Download of SFDC Activation Rep'!B:B,'Download of SFDC Activation Rep'!S:S),"")} -> 280.89 | M18: {=iferror(XLOOKUP(A18,'Download of SFDC Activation Rep'!B:B,'Download of SFDC Activation Rep'!Z:Z)+150,"")} -> 46208 | N18: {=iferror(XLOOKUP(A18,'Download of SFDC Activation Rep'!B:B,'Download of SFDC Activation Rep'!Y:Y),"")} -> 46118 | O18: Median TPV per Org per Month | P18: =MEDIAN(E2:E1000) -> 23535.252 | U18: =IF(M18="", "", EOMONTH(M18, -5) + 1) -> 46082
G19: {=iferror(XLOOKUP(A19,'Download of SFDC Activation Rep'!B:B,'Download of SFDC Activation Rep'!H:H),"")} -> Active | H19: {=iferror(xlookup(A19,'Download of SFDC Activation Rep'!B:B,'Download of SFDC Activation Rep'!L:L),"")} | I19: =IF(or(G19="Active",H19="Active"),"Active","Not Active") -> Active | J19: {=iferror(XLOOKUP(A19,'Download of SFDC Activation Rep'!B:B,'Download of SFDC Activation Rep'!X:X),"")} -> Matthew Frost | K19: {=iferror(XLOOKUP(A19,'Download of SFDC Activation Rep'!B:B,'Download of SFDC Activation Rep'!C:C),"")} -> Abecca Grace, LLC | L19: {=iferror(XLOOKUP(A19,'Download of SFDC Activation Rep'!B:B,'Download of SFDC Activation Rep'!S:S),"")} -> 0 | M19: {=iferror(XLOOKUP(A19,'Download of SFDC Activation Rep'!B:B,'Download of SFDC Activation Rep'!Z:Z)+150,"")} -> 46248 | N19: {=iferror(XLOOKUP(A19,'Download of SFDC Activation Rep'!B:B,'Download of SFDC Activation Rep'!Y:Y),"")} -> 46141 | O19: Median Monthly GP per Org | P19: =MEDIAN(C2:C1000) -> 56.9073 | U19: =IF(M19="", "", EOMONTH(M19, -5) + 1) -> 46113
G20: {=iferror(XLOOKUP(A20,'Download of SFDC Activation Rep'!B:B,'Download of SFDC Activation Rep'!H:H),"")} -> Active | H20: {=iferror(xlookup(A20,'Download of SFDC Activation Rep'!B:B,'Download of SFDC Activation Rep'!L:L),"")} | I20: =IF(or(G20="Active",H20="Active"),"Active","Not Active") -> Active | J20: {=iferror(XLOOKUP(A20,'Download of SFDC Activation Rep'!B:B,'Download of SFDC Activation Rep'!X:X),"")} -> Matthew Frost | K20: {=iferror(XLOOKUP(A20,'Download of SFDC Activation Rep'!B:B,'Download of SFDC Activation Rep'!C:C),"")} -> MJDII Architects, Inc. | L20: {=iferror(XLOOKUP(A20,'Download of SFDC Activation Rep'!B:B,'Download of SFDC Activation Rep'!S:S),"")} -> 72.7 | M20: {=iferror(XLOOKUP(A20,'Download of SFDC Activation Rep'!B:B,'Download of SFDC Activation Rep'!Z:Z)+150,"")} -> 46157 | N20: {=iferror(XLOOKUP(A20,'Download of SFDC Activation Rep'!B:B,'Download of SFDC Activation Rep'!Y:Y),"")} -> 46007 | U20: =IF(M20="", "", EOMONTH(M20, -5) + 1) -> 46023
G21: {=iferror(XLOOKUP(A21,'Download of SFDC Activation Rep'!B:B,'Download of SFDC Activation Rep'!H:H),"")} -> Active | H21: {=iferror(xlookup(A21,'Download of SFDC Activation Rep'!B:B,'Download of SFDC Activation Rep'!L:L),"")} | I21: =IF(or(G21="Active",H21="Active"),"Active","Not Active") -> Active | J21: {=iferror(XLOOKUP(A21,'Download of SFDC Activation Rep'!B:B,'Download of SFDC Activation Rep'!X:X),"")} -> Arianna Modesti | K21: {=iferror(XLOOKUP(A21,'Download of SFDC Activation Rep'!B:B,'Download of SFDC Activation Rep'!C:C),"")} -> Brian Schmidt Builder | L21: {=iferror(XLOOKUP(A21,'Download of SFDC Activation Rep'!B:B,'Download of SFDC Activation Rep'!S:S),"")} -> 316.95 | M21: {=iferror(XLOOKUP(A21,'Download of SFDC Activation Rep'!B:B,'Download of SFDC Activation Rep'!Z:Z)+150,"")} -> 46242 | N21: {=iferror(XLOOKUP(A21,'Download of SFDC Activation Rep'!B:B,'Download of SFDC Activation Rep'!Y:Y),"")} -> 46132 | U21: =IF(M21="", "", EOMONTH(M21, -5) + 1) -> 46113
G22: {=iferror(XLOOKUP(A22,'Download of SFDC Activation Rep'!B:B,'Download of SFDC Activation Rep'!H:H),"")} -> Active | H22: {=iferror(xlookup(A22,'Download of SFDC Activation Rep'!B:B,'Download of SFDC Activation Rep'!L:L),"")} | I22: =IF(or(G22="Active",H22="Active"),"Active","Not Active") -> Active | J22: {=iferror(XLOOKUP(A22,'Download of SFDC Activation Rep'!B:B,'Download of SFDC Activation Rep'!X:X),"")} -> Arianna Modesti | K22: {=iferror(XLOOKUP(A22,'Download of SFDC Activation Rep'!B:B,'Download of SFDC Activation Rep'!C:C),"")} -> Landa Cleary Travel Co. Inc. D.B.A. Mater Dei Tours | L22: {=iferror(XLOOKUP(A22,'Download of SFDC Activation Rep'!B:B,'Download of SFDC Activation Rep'!S:S),"")} -> 281.77 | M22: {=iferror(XLOOKUP(A22,'Download of SFDC Activation Rep'!B:B,'Download of SFDC Activation Rep'!Z:Z)+150,"")} -> 46263 | N22: {=iferror(XLOOKUP(A22,'Download of SFDC Activation Rep'!B:B,'Download of SFDC Activation Rep'!Y:Y),"")} -> 46237 | U22: =IF(M22="", "", EOMONTH(M22, -5) + 1) -> 46113
G23: {=iferror(XLOOKUP(A23,'Download of SFDC Activation Rep'!B:B,'Download of SFDC Activation Rep'!H:H),"")} -> Active | H23: {=iferror(xlookup(A23,'Download of SFDC Activation Rep'!B:B,'Download of SFDC Activation Rep'!L:L),"")} | I23: =IF(or(G23="Active",H23="Active"),"Active","Not Active") -> Active | J23: {=iferror(XLOOKUP(A23,'Download of SFDC Activation Rep'!B:B,'Download of SFDC Activation Rep'!X:X),"")} -> Kate Olivares | K23: {=iferror(XLOOKUP(A23,'Download of SFDC Activation Rep'!B:B,'Download of SFDC Activation Rep'!C:C),"")} -> H&H Auto Parts LLC | L23: {=iferror(XLOOKUP(A23,'Download of SFDC Activation Rep'!B:B,'Download of SFDC Activation Rep'!S:S),"")} -> 423.9 | M23: {=iferror(XLOOKUP(A23,'Download of SFDC Activation Rep'!B:B,'Download of SFDC Activation Rep'!Z:Z)+150,"")} -> 46111 | N23: {=iferror(XLOOKUP(A23,'Download of SFDC Activation Rep'!B:B,'Download of SFDC Activation Rep'!Y:Y),"")} -> 46013 | U23: =IF(M23="", "", EOMONTH(M23, -5) + 1) -> 45962
G24: {=iferror(XLOOKUP(A24,'Download of SFDC Activation Rep'!B:B,'Download of SFDC Activation Rep'!H:H),"")} -> Active | H24: {=iferror(xlookup(A24,'Download of SFDC Activation Rep'!B:B,'Download of SFDC Activation Rep'!L:L),"")} | I24: =IF(or(G24="Active",H24="Active"),"Active","Not Active") -> Active | J24: {=iferror(XLOOKUP(A24,'Download of SFDC Activation Rep'!B:B,'Download of SFDC Activation Rep'!X:X),"")} -> Matthew Frost | K24: {=iferror(XLOOKUP(A24,'Download of SFDC Activation Rep'!B:B,'Download of SFDC Activation Rep'!C:C),"")} -> Shree Satya Sai LLC | L24: {=iferror(XLOOKUP(A24,'Download of SFDC Activation Rep'!B:B,'Download of SFDC Activation Rep'!S:S),"")} -> 35 | M24: {=iferror(XLOOKUP(A24,'Download of SFDC Activation Rep'!B:B,'Download of SFDC Activation Rep'!Z:Z)+150,"")} -> 46270 | N24: {=iferror(XLOOKUP(A24,'Download of SFDC Activation Rep'!B:B,'Download of SFDC Activation Rep'!Y:Y),"")} -> 46147 | U24: =IF(M24="", "", EOMONTH(M24, -5) + 1) -> 46143
G25: {=iferror(XLOOKUP(A25,'Download of SFDC Activation Rep'!B:B,'Download of SFDC Activation Rep'!H:H),"")} -> Active | H25: {=iferror(xlookup(A25,'Download of SFDC Activation Rep'!B:B,'Download of SFDC Activation Rep'!L:L),"")} | I25: =IF(or(G25="Active",H25="Active"),"Active","Not Active") -> Active | J25: {=iferror(XLOOKUP(A25,'Download of SFDC Activation Rep'!B:B,'Download of SFDC Activation Rep'!X:X),"")} -> Kate Olivares | K25: {=iferror(XLOOKUP(A25,'Download of SFDC Activation Rep'!B:B,'Download of SFDC Activation Rep'!C:C),"")} -> GK Truckline | L25: {=iferror(XLOOKUP(A25,'Download of SFDC Activation Rep'!B:B,'Download of SFDC Activation Rep'!S:S),"")} -> 461.94 | M25: {=iferror(XLOOKUP(A25,'Download of SFDC Activation Rep'!B:B,'Download of SFDC Activation Rep'!Z:Z)+150,"")} -> 46305 | N25: {=iferror(XLOOKUP(A25,'Download of SFDC Activation Rep'!B:B,'Download of SFDC Activation Rep'!Y:Y),"")} -> 46286 | U25: =IF(M25="", "", EOMONTH(M25, -5) + 1) -> 46174
G26: {=iferror(XLOOKUP(A26,'Download of SFDC Activation Rep'!B:B,'Download of SFDC Activation Rep'!H:H),"")} -> Active | H26: {=iferror(xlookup(A26,'Download of SFDC Activation Rep'!B:B,'Download of SFDC Activation Rep'!L:L),"")} | I26: =IF(or(G26="Active",H26="Active"),"Active","Not Active") -> Active | J26: {=iferror(XLOOKUP(A26,'Download of SFDC Activation Rep'!B:B,'Download of SFDC Activation Rep'!X:X),"")} -> Matthew Frost | K26: {=iferror(XLOOKUP(A26,'Download of SFDC Activation Rep'!B:B,'Download of SFDC Activation Rep'!C:C),"")} -> Protagenic Therapeutics, Inc. | L26: {=iferror(XLOOKUP(A26,'Download of SFDC Activation Rep'!B:B,'Download of SFDC Activation Rep'!S:S),"")} -> 147.7 | M26: {=iferror(XLOOKUP(A26,'Download of SFDC Activation Rep'!B:B,'Download of SFDC Activation Rep'!Z:Z)+150,"")} -> 46110 | N26: {=iferror(XLOOKUP(A26,'Download of SFDC Activation Rep'!B:B,'Download of SFDC Activation Rep'!Y:Y),"")} -> 46006 | U26: =IF(M26="", "", EOMONTH(M26, -5) + 1) -> 45962
G27: {=iferror(XLOOKUP(A27,'Download of SFDC Activation Rep'!B:B,'Download of SFDC Activation Rep'!H:H),"")} -> Active | H27: {=iferror(xlookup(A27,'Download of SFDC Activation Rep'!B:B,'Download of SFDC Activation Rep'!L:L),"")} -> Active | I27: =IF(or(G27="Active",H27="Active"),"Active","Not Active") -> Active | J27: {=iferror(XLOOKUP(A27,'Download of SFDC Activation Rep'!B:B,'Download of SFDC Activation Rep'!X:X),"")} -> Kate Olivares | K27: {=iferror(XLOOKUP(A27,'Download of SFDC Activation Rep'!B:B,'Download of SFDC Activation Rep'!C:C),"")} -> Rumford Stone, Inc | L27: {=iferror(XLOOKUP(A27,'Download of SFDC Activation Rep'!B:B,'Download of SFDC Activation Rep'!S:S),"")} -> 168.5 | M27: {=iferror(XLOOKUP(A27,'Download of SFDC Activation Rep'!B:B,'Download of SFDC Activation Rep'!Z:Z)+150,"")} -> 45947 | N27: {=iferror(XLOOKUP(A27,'Download of SFDC Activation Rep'!B:B,'Download of SFDC Activation Rep'!Y:Y),"")} -> 45797 | U27: =IF(M27="", "", EOMONTH(M27, -5) + 1) -> 45809
G28: {=iferror(XLOOKUP(A28,'Download of SFDC Activation Rep'!B:B,'Download of SFDC Activation Rep'!H:H),"")} -> Active | H28: {=iferror(xlookup(A28,'Download of SFDC Activation Rep'!B:B,'Download of SFDC Activation Rep'!L:L),"")} -> Active | I28: =IF(or(G28="Active",H28="Active"),"Active","Not Active") -> Active | J28: {=iferror(XLOOKUP(A28,'Download of SFDC Activation Rep'!B:B,'Download of SFDC Activation Rep'!X:X),"")} -> Matthew Frost | K28: {=iferror(XLOOKUP(A28,'Download of SFDC Activation Rep'!B:B,'Download of SFDC Activation Rep'!C:C),"")} -> Friendly Foods Inc | L28: {=iferror(XLOOKUP(A28,'Download of SFDC Activation Rep'!B:B,'Download of SFDC Activation Rep'!S:S),"")} -> 691.55 | M28: {=iferror(XLOOKUP(A28,'Download of SFDC Activation Rep'!B:B,'Download of SFDC Activation Rep'!Z:Z)+150,"")} -> 46157 | N28: {=iferror(XLOOKUP(A28,'Download of SFDC Activation Rep'!B:B,'Download of SFDC Activation Rep'!Y:Y),"")} -> 46021 | U28: =IF(M28="", "", EOMONTH(M28, -5) + 1) -> 46023
G29: {=iferror(XLOOKUP(A29,'Download of SFDC Activation Rep'!B:B,'Download of SFDC Activation Rep'!H:H),"")} -> Active | H29: {=iferror(xlookup(A29,'Download of SFDC Activation Rep'!B:B,'Download of SFDC Activation Rep'!L:L),"")} | I29: =IF(or(G29="Active",H29="Active"),"Active","Not Active") -> Active | J29: {=iferror(XLOOKUP(A29,'Download of SFDC Activation Rep'!B:B,'Download of SFDC Activation Rep'!X:X),"")} -> Matthew Frost | K29: {=iferror(XLOOKUP(A29,'Download of SFDC Activation Rep'!B:B,'Download of SFDC Activation Rep'!C:C),"")} -> Appellate Defenders, Inc. | L29: {=iferror(XLOOKUP(A29,'Download of SFDC Activation Rep'!B:B,'Download of SFDC Activation Rep'!S:S),"")} -> 107 | M29: {=iferror(XLOOKUP(A29,'Download of SFDC Activation Rep'!B:B,'Download of SFDC Activation Rep'!Z:Z)+150,"")} -> 46061 | N29: {=iferror(XLOOKUP(A29,'Download of SFDC Activation Rep'!B:B,'Download of SFDC Activation Rep'!Y:Y),"")} -> 45945 | U29: =IF(M29="", "", EOMONTH(M29, -5) + 1) -> 45931
G30: {=iferror(XLOOKUP(A30,'Download of SFDC Activation Rep'!B:B,'Download of SFDC Activation Rep'!H:H),"")} -> Active | H30: {=iferror(xlookup(A30,'Download of SFDC Activation Rep'!B:B,'Download of SFDC Activation Rep'!L:L),"")} | I30: =IF(or(G30="Active",H30="Active"),"Active","Not Active") -> Active | J30: {=iferror(XLOOKUP(A30,'Download of SFDC Activation Rep'!B:B,'Download of SFDC Activation Rep'!X:X),"")} -> Matthew Frost | K30: {=iferror(XLOOKUP(A30,'Download of SFDC Activation Rep'!B:B,'Download of SFDC Activation Rep'!C:C),"")} -> Herbert Law Group, LLC | L30: {=iferror(XLOOKUP(A30,'Download of SFDC Activation Rep'!B:B,'Download of SFDC Activation Rep'!S:S),"")} -> 375 | M30: {=iferror(XLOOKUP(A30,'Download of SFDC Activation Rep'!B:B,'Download of SFDC Activation Rep'!Z:Z)+150,"")} -> 46187 | N30: {=iferror(XLOOKUP(A30,'Download of SFDC Activation Rep'!B:B,'Download of SFDC Activation Rep'!Y:Y),"")} -> 46057 | U30: =IF(M30="", "", EOMONTH(M30, -5) + 1) -> 46054
G31: {=iferror(XLOOKUP(A31,'Download of SFDC Activation Rep'!B:B,'Download of SFDC Activation Rep'!H:H),"")} -> Active | H31: {=iferror(xlookup(A31,'Download of SFDC Activation Rep'!B:B,'Download of SFDC Activation Rep'!L:L),"")} | I31: =IF(or(G31="Active",H31="Active"),"Active","Not Active") -> Active | J31: {=iferror(XLOOKUP(A31,'Download of SFDC Activation Rep'!B:B,'Download of SFDC Activation Rep'!X:X),"")} -> Matthew Frost | K31: {=iferror(XLOOKUP(A31,'Download of SFDC Activation Rep'!B:B,'Download of SFDC Activation Rep'!C:C),"")} -> Cope Equities | L31: {=iferror(XLOOKUP(A31,'Download of SFDC Activation Rep'!B:B,'Download of SFDC Activation Rep'!S:S),"")} -> 0 | M31: {=iferror(XLOOKUP(A31,'Download of SFDC Activation Rep'!B:B,'Download of SFDC Activation Rep'!Z:Z)+150,"")} -> 46249 | N31: {=iferror(XLOOKUP(A31,'Download of SFDC Activation Rep'!B:B,'Download of SFDC Activation Rep'!Y:Y),"")} -> 46087 | U31: =IF(M31="", "", EOMONTH(M31, -5) + 1) -> 46113
... G172: {=iferror(XLOOKUP(A172,'Download of SFDC Activation Rep'!B:B,'Download of SFDC Activation Rep'!H:H),"")} | H172: {=iferror(xlookup(A172,'Download of SFDC Activation Rep'!B:B,'Download of SFDC Activation Rep'!L:L),"")} | I172: =IF(or(G172="Active",H172="Active"),"Active","Not Active") -> Not Active | J172: {=iferror(XLOOKUP(A172,'Download of SFDC Activation Rep'!B:B,'Download of SFDC Activation Rep'!X:X),"")} | K172: {=iferror(XLOOKUP(A172,'Download of SFDC Activation Rep'!B:B,'Download of SFDC Activation Rep'!C:C),"")} | L172: {=iferror(XLOOKUP(A172,'Download of SFDC Activation Rep'!B:B,'Download of SFDC Activation Rep'!S:S),"")} | M172: {=iferror(XLOOKUP(A172,'Download of SFDC Activation Rep'!B:B,'Download of SFDC Activation Rep'!Z:Z)+150,"")} | N172: {=iferror(XLOOKUP(A172,'Download of SFDC Activation Rep'!B:B,'Download of SFDC Activation Rep'!Y:Y),"")} | U172: =IF(M172="", "", EOMONTH(M172, -5) + 1)
G173: {=iferror(XLOOKUP(A173,'Download of SFDC Activation Rep'!B:B,'Download of SFDC Activation Rep'!H:H),"")} | H173: {=iferror(xlookup(A173,'Download of SFDC Activation Rep'!B:B,'Download of SFDC Activation Rep'!L:L),"")} | I173: =IF(or(G173="Active",H173="Active"),"Active","Not Active") -> Not Active | J173: {=iferror(XLOOKUP(A173,'Download of SFDC Activation Rep'!B:B,'Download of SFDC Activation Rep'!X:X),"")} | K173: {=iferror(XLOOKUP(A173,'Download of SFDC Activation Rep'!B:B,'Download of SFDC Activation Rep'!C:C),"")} | L173: {=iferror(XLOOKUP(A173,'Download of SFDC Activation Rep'!B:B,'Download of SFDC Activation Rep'!S:S),"")} | M173: {=iferror(XLOOKUP(A173,'Download of SFDC Activation Rep'!B:B,'Download of SFDC Activation Rep'!Z:Z)+150,"")} | N173: {=iferror(XLOOKUP(A173,'Download of SFDC Activation Rep'!B:B,'Download of SFDC Activation Rep'!Y:Y),"")}
G174: {=iferror(XLOOKUP(A174,'Download of SFDC Activation Rep'!B:B,'Download of SFDC Activation Rep'!H:H),"")} | H174: {=iferror(xlookup(A174,'Download of SFDC Activation Rep'!B:B,'Download of SFDC Activation Rep'!L:L),"")} | I174: =IF(or(G174="Active",H174="Active"),"Active","Not Active") -> Not Active | J174: {=iferror(XLOOKUP(A174,'Download of SFDC Activation Rep'!B:B,'Download of SFDC Activation Rep'!X:X),"")} | K174: {=iferror(XLOOKUP(A174,'Download of SFDC Activation Rep'!B:B,'Download of SFDC Activation Rep'!C:C),"")} | L174: {=iferror(XLOOKUP(A174,'Download of SFDC Activation Rep'!B:B,'Download of SFDC Activation Rep'!S:S),"")} | M174: {=iferror(XLOOKUP(A174,'Download of SFDC Activation Rep'!B:B,'Download of SFDC Activation Rep'!Z:Z)+150,"")} | N174: {=iferror(XLOOKUP(A174,'Download of SFDC Activation Rep'!B:B,'Download of SFDC Activation Rep'!Y:Y),"")}
G175: {=iferror(XLOOKUP(A175,'Download of SFDC Activation Rep'!B:B,'Download of SFDC Activation Rep'!H:H),"")} | H175: {=iferror(xlookup(A175,'Download of SFDC Activation Rep'!B:B,'Download of SFDC Activation Rep'!L:L),"")} | I175: =IF(or(G175="Active",H175="Active"),"Active","Not Active") -> Not Active | J175: {=iferror(XLOOKUP(A175,'Download of SFDC Activation Rep'!B:B,'Download of SFDC Activation Rep'!X:X),"")} | K175: {=iferror(XLOOKUP(A175,'Download of SFDC Activation Rep'!B:B,'Download of SFDC Activation Rep'!C:C),"")} | L175: {=iferror(XLOOKUP(A175,'Download of SFDC Activation Rep'!B:B,'Download of SFDC Activation Rep'!S:S),"")} | M175: {=iferror(XLOOKUP(A175,'Download of SFDC Activation Rep'!B:B,'Download of SFDC Activation Rep'!Z:Z)+150,"")} | N175: {=iferror(XLOOKUP(A175,'Download of SFDC Activation Rep'!B:B,'Download of SFDC Activation Rep'!Y:Y),"")}
G176: {=iferror(XLOOKUP(A176,'Download of SFDC Activation Rep'!B:B,'Download of SFDC Activation Rep'!H:H),"")} | H176: {=iferror(xlookup(A176,'Download of SFDC Activation Rep'!B:B,'Download of SFDC Activation Rep'!L:L),"")} | I176: =IF(or(G176="Active",H176="Active"),"Active","Not Active") -> Not Active | J176: {=iferror(XLOOKUP(A176,'Download of SFDC Activation Rep'!B:B,'Download of SFDC Activation Rep'!X:X),"")} | K176: {=iferror(XLOOKUP(A176,'Download of SFDC Activation Rep'!B:B,'Download of SFDC Activation Rep'!C:C),"")} | L176: {=iferror(XLOOKUP(A176,'Download of SFDC Activation Rep'!B:B,'Download of SFDC Activation Rep'!S:S),"")} | M176: {=iferror(XLOOKUP(A176,'Download of SFDC Activation Rep'!B:B,'Download of SFDC Activation Rep'!Z:Z)+150,"")} | N176: {=iferror(XLOOKUP(A176,'Download of SFDC Activation Rep'!B:B,'Download of SFDC Activation Rep'!Y:Y),"")}
G177: {=iferror(XLOOKUP(A177,'Download of SFDC Activation Rep'!B:B,'Download of SFDC Activation Rep'!H:H),"")} | H177: {=iferror(xlookup(A177,'Download of SFDC Activation Rep'!B:B,'Download of SFDC Activation Rep'!L:L),"")} | I177: =IF(or(G177="Active",H177="Active"),"Active","Not Active") -> Not Active | J177: {=iferror(XLOOKUP(A177,'Download of SFDC Activation Rep'!B:B,'Download of SFDC Activation Rep'!X:X),"")} | K177: {=iferror(XLOOKUP(A177,'Download of SFDC Activation Rep'!B:B,'Download of SFDC Activation Rep'!C:C),"")} | L177: {=iferror(XLOOKUP(A177,'Download of SFDC Activation Rep'!B:B,'Download of SFDC Activation Rep'!S:S),"")} | M177: {=iferror(XLOOKUP(A177,'Download of SFDC Activation Rep'!B:B,'Download of SFDC Activation Rep'!Z:Z)+150,"")} | N177: {=iferror(XLOOKUP(A177,'Download of SFDC Activation Rep'!B:B,'Download of SFDC Activation Rep'!Y:Y),"")}
G178: {=iferror(XLOOKUP(A178,'Download of SFDC Activation Rep'!B:B,'Download of SFDC Activation Rep'!H:H),"")} | H178: {=iferror(xlookup(A178,'Download of SFDC Activation Rep'!B:B,'Download of SFDC Activation Rep'!L:L),"")} | I178: =IF(or(G178="Active",H178="Active"),"Active","Not Active") -> Not Active | J178: {=iferror(XLOOKUP(A178,'Download of SFDC Activation Rep'!B:B,'Download of SFDC Activation Rep'!X:X),"")} | K178: {=iferror(XLOOKUP(A178,'Download of SFDC Activation Rep'!B:B,'Download of SFDC Activation Rep'!C:C),"")} | L178: {=iferror(XLOOKUP(A178,'Download of SFDC Activation Rep'!B:B,'Download of SFDC Activation Rep'!S:S),"")} | M178: {=iferror(XLOOKUP(A178,'Download of SFDC Activation Rep'!B:B,'Download of SFDC Activation Rep'!Z:Z)+150,"")} | N178: {=iferror(XLOOKUP(A178,'Download of SFDC Activation Rep'!B:B,'Download of SFDC Activation Rep'!Y:Y),"")}
G179: {=iferror(XLOOKUP(A179,'Download of SFDC Activation Rep'!B:B,'Download of SFDC Activation Rep'!H:H),"")} | H179: {=iferror(xlookup(A179,'Download of SFDC Activation Rep'!B:B,'Download of SFDC Activation Rep'!L:L),"")} | I179: =IF(or(G179="Active",H179="Active"),"Active","Not Active") -> Not Active | J179: {=iferror(XLOOKUP(A179,'Download of SFDC Activation Rep'!B:B,'Download of SFDC Activation Rep'!X:X),"")} | K179: {=iferror(XLOOKUP(A179,'Download of SFDC Activation Rep'!B:B,'Download of SFDC Activation Rep'!C:C),"")} | L179: {=iferror(XLOOKUP(A179,'Download of SFDC Activation Rep'!B:B,'Download of SFDC Activation Rep'!S:S),"")} | M179: {=iferror(XLOOKUP(A179,'Download of SFDC Activation Rep'!B:B,'Download of SFDC Activation Rep'!Z:Z)+150,"")} | N179: {=iferror(XLOOKUP(A179,'Download of SFDC Activation Rep'!B:B,'Download of SFDC Activation Rep'!Y:Y),"")}
G180: {=iferror(XLOOKUP(A180,'Download of SFDC Activation Rep'!B:B,'Download of SFDC Activation Rep'!H:H),"")} | H180: {=iferror(xlookup(A180,'Download of SFDC Activation Rep'!B:B,'Download of SFDC Activation Rep'!L:L),"")} | I180: =IF(or(G180="Active",H180="Active"),"Active","Not Active") -> Not Active | J180: {=iferror(XLOOKUP(A180,'Download of SFDC Activation Rep'!B:B,'Download of SFDC Activation Rep'!X:X),"")} | K180: {=iferror(XLOOKUP(A180,'Download of SFDC Activation Rep'!B:B,'Download of SFDC Activation Rep'!C:C),"")} | L180: {=iferror(XLOOKUP(A180,'Download of SFDC Activation Rep'!B:B,'Download of SFDC Activation Rep'!S:S),"")} | M180: {=iferror(XLOOKUP(A180,'Download of SFDC Activation Rep'!B:B,'Download of SFDC Activation Rep'!Z:Z)+150,"")} | N180: {=iferror(XLOOKUP(A180,'Download of SFDC Activation Rep'!B:B,'Download of SFDC Activation Rep'!Y:Y),"")}
G181: {=iferror(XLOOKUP(A181,'Download of SFDC Activation Rep'!B:B,'Download of SFDC Activation Rep'!H:H),"")} | H181: {=iferror(xlookup(A181,'Download of SFDC Activation Rep'!B:B,'Download of SFDC Activation Rep'!L:L),"")} | I181: =IF(or(G181="Active",H181="Active"),"Active","Not Active") -> Not Active | J181: {=iferror(XLOOKUP(A181,'Download of SFDC Activation Rep'!B:B,'Download of SFDC Activation Rep'!X:X),"")} | K181: {=iferror(XLOOKUP(A181,'Download of SFDC Activation Rep'!B:B,'Download of SFDC Activation Rep'!C:C),"")} | L181: {=iferror(XLOOKUP(A181,'Download of SFDC Activation Rep'!B:B,'Download of SFDC Activation Rep'!S:S),"")} | M181: {=iferror(XLOOKUP(A181,'Download of SFDC Activation Rep'!B:B,'Download of SFDC Activation Rep'!Z:Z)+150,"")} | N181: {=iferror(XLOOKUP(A181,'Download of SFDC Activation Rep'!B:B,'Download of SFDC Activation Rep'!Y:Y),"")}
G182: {=iferror(XLOOKUP(A182,'Download of SFDC Activation Rep'!B:B,'Download of SFDC Activation Rep'!H:H),"")} | H182: {=iferror(xlookup(A182,'Download of SFDC Activation Rep'!B:B,'Download of SFDC Activation Rep'!L:L),"")} | I182: =IF(or(G182="Active",H182="Active"),"Active","Not Active") -> Not Active | J182: {=iferror(XLOOKUP(A182,'Download of SFDC Activation Rep'!B:B,'Download of SFDC Activation Rep'!X:X),"")} | K182: {=iferror(XLOOKUP(A182,'Download of SFDC Activation Rep'!B:B,'Download of SFDC Activation Rep'!C:C),"")} | L182: {=iferror(XLOOKUP(A182,'Download of SFDC Activation Rep'!B:B,'Download of SFDC Activation Rep'!S:S),"")} | M182: {=iferror(XLOOKUP(A182,'Download of SFDC Activation Rep'!B:B,'Download of SFDC Activation Rep'!Z:Z)+150,"")} | N182: {=iferror(XLOOKUP(A182,'Download of SFDC Activation Rep'!B:B,'Download of SFDC Activation Rep'!Y:Y),"")}
G183: {=iferror(XLOOKUP(A183,'Download of SFDC Activation Rep'!B:B,'Download of SFDC Activation Rep'!H:H),"")} | H183: {=iferror(xlookup(A183,'Download of SFDC Activation Rep'!B:B,'Download of SFDC Activation Rep'!L:L),"")} | I183: =IF(or(G183="Active",H183="Active"),"Active","Not Active") -> Not Active | J183: {=iferror(XLOOKUP(A183,'Download of SFDC Activation Rep'!B:B,'Download of SFDC Activation Rep'!X:X),"")} | K183: {=iferror(XLOOKUP(A183,'Download of SFDC Activation Rep'!B:B,'Download of SFDC Activation Rep'!C:C),"")} | L183: {=iferror(XLOOKUP(A183,'Download of SFDC Activation Rep'!B:B,'Download of SFDC Activation Rep'!S:S),"")} | M183: {=iferror(XLOOKUP(A183,'Download of SFDC Activation Rep'!B:B,'Download of SFDC Activation Rep'!Z:Z)+150,"")} | N183: {=iferror(XLOOKUP(A183,'Download of SFDC Activation Rep'!B:B,'Download of SFDC Activation Rep'!Y:Y),"")}
G184: {=iferror(XLOOKUP(A184,'Download of SFDC Activation Rep'!B:B,'Download of SFDC Activation Rep'!H:H),"")} | H184: {=iferror(xlookup(A184,'Download of SFDC Activation Rep'!B:B,'Download of SFDC Activation Rep'!L:L),"")} | I184: =IF(or(G184="Active",H184="Active"),"Active","Not Active") -> Not Active | J184: {=iferror(XLOOKUP(A184,'Download of SFDC Activation Rep'!B:B,'Download of SFDC Activation Rep'!X:X),"")} | K184: {=iferror(XLOOKUP(A184,'Download of SFDC Activation Rep'!B:B,'Download of SFDC Activation Rep'!C:C),"")} | L184: {=iferror(XLOOKUP(A184,'Download of SFDC Activation Rep'!B:B,'Download of SFDC Activation Rep'!S:S),"")} | M184: {=iferror(XLOOKUP(A184,'Download of SFDC Activation Rep'!B:B,'Download of SFDC Activation Rep'!Z:Z)+150,"")} | N184: {=iferror(XLOOKUP(A184,'Download of SFDC Activation Rep'!B:B,'Download of SFDC Activation Rep'!Y:Y),"")}
... G1000: {=iferror(XLOOKUP(A1000,'Download of SFDC Activation Rep'!B:B,'Download of SFDC Activation Rep'!H:H),"")} | H1000: {=iferror(xlookup(A1000,'Download of SFDC Activation Rep'!B:B,'Download of SFDC Activation Rep'!L:L),"")} | I1000: =IF(or(G1000="Active",H1000="Active"),"Active","Not Active") -> Not Active | J1000: {=iferror(XLOOKUP(A1000,'Download of SFDC Activation Rep'!B:B,'Download of SFDC Activation Rep'!X:X),"")} | K1000: {=iferror(XLOOKUP(A1000,'Download of SFDC Activation Rep'!B:B,'Download of SFDC Activation Rep'!C:C),"")} | L1000: {=iferror(XLOOKUP(A1000,'Download of SFDC Activation Rep'!B:B,'Download of SFDC Activation Rep'!S:S),"")} | M1000: {=iferror(XLOOKUP(A1000,'Download of SFDC Activation Rep'!B:B,'Download of SFDC Activation Rep'!Z:Z)+150,"")} | N1000: {=iferror(XLOOKUP(A1000,'Download of SFDC Activation Rep'!B:B,'Download of SFDC Activation Rep'!Y:Y),"")}

Sheet Current Calendar Month Stats
F1: AP Status | G1: AR Status | H1: AP/AR Status | I1: Account Owner | J1: Account Name | K1: Opp Owner | L1: Create Date | M1: Total Orgs | N1: =COUNTIF(A2:A1000,">=0") -> 121 | P1: LAST DATA PULL: | Q1: 46201
F2: {=iferror(XLOOKUP(A2,'Download of SFDC Activation Rep'!B:B,'Download of SFDC Activation Rep'!H:H),"")} -> Active | G2: {=iferror(xlookup(A2,'Download of SFDC Activation Rep'!B:B,'Download of SFDC Activation Rep'!L:L),"")} | H2: =IF(or(F2="Active",G2="Active"),"Active","Not Active") -> Active | I2: {=XLOOKUP(A2,'Download of SFDC Activation Rep'!B:B,'Download of SFDC Activation Rep'!T:T)} -> 006VT00000sgdkK | J2: {=iferror(XLOOKUP(A2,'Download of SFDC Activation Rep'!B:B,'Download of SFDC Activation Rep'!C:C),"")} -> HTT Cardmax Company | K2: {=XLOOKUP(A2,'Download of SFDC Activation Rep'!B:B,'Download of SFDC Activation Rep'!X:X)} -> Arianna Modesti | L2: {=xlookup(A2,'Download of SFDC Activation Rep'!B:B,'Download of SFDC Activation Rep'!Z:Z)} -> 46197 | M2: Total Active Orgs | N2: =COUNTIF(H:H,"Active") -> 121 | O2: =SUMIFS('Redash Pull of Activated Org GP'!J:J,'Redash Pull of Activated Org GP'!B:B,"2025-10-01",'Redash Pull of Activated Org GP'!C:C,"<>4054136") -> 42
F3: {=iferror(XLOOKUP(A3,'Download of SFDC Activation Rep'!B:B,'Download of SFDC Activation Rep'!H:H),"")} -> Active | G3: {=iferror(xlookup(A3,'Download of SFDC Activation Rep'!B:B,'Download of SFDC Activation Rep'!L:L),"")} | H3: =IF(or(F3="Active",G3="Active"),"Active","Not Active") -> Active | I3: {=XLOOKUP(A3,'Download of SFDC Activation Rep'!B:B,'Download of SFDC Activation Rep'!T:T)} -> 006VT00000rNywD | J3: {=iferror(XLOOKUP(A3,'Download of SFDC Activation Rep'!B:B,'Download of SFDC Activation Rep'!C:C),"")} -> DataLinks LLC | K3: {=XLOOKUP(A3,'Download of SFDC Activation Rep'!B:B,'Download of SFDC Activation Rep'!X:X)} -> Arianna Modesti | L3: {=xlookup(A3,'Download of SFDC Activation Rep'!B:B,'Download of SFDC Activation Rep'!Z:Z)} -> 46170
F4: {=iferror(XLOOKUP(A4,'Download of SFDC Activation Rep'!B:B,'Download of SFDC Activation Rep'!H:H),"")} -> Active | G4: {=iferror(xlookup(A4,'Download of SFDC Activation Rep'!B:B,'Download of SFDC Activation Rep'!L:L),"")} | H4: =IF(or(F4="Active",G4="Active"),"Active","Not Active") -> Active | I4: {=XLOOKUP(A4,'Download of SFDC Activation Rep'!B:B,'Download of SFDC Activation Rep'!T:T)} -> 006UU00000Og7FN | J4: {=iferror(XLOOKUP(A4,'Download of SFDC Activation Rep'!B:B,'Download of SFDC Activation Rep'!C:C),"")} -> Solutions Group International, Inc. | K4: {=XLOOKUP(A4,'Download of SFDC Activation Rep'!B:B,'Download of SFDC Activation Rep'!X:X)} -> Matthew Frost | L4: {=xlookup(A4,'Download of SFDC Activation Rep'!B:B,'Download of SFDC Activation Rep'!Z:Z)} -> 46028 | M4: Avg TPV per Org | N4: =N15/N2 -> 130241.22
F5: {=iferror(XLOOKUP(A5,'Download of SFDC Activation Rep'!B:B,'Download of SFDC Activation Rep'!H:H),"")} -> Active | G5: {=iferror(xlookup(A5,'Download of SFDC Activation Rep'!B:B,'Download of SFDC Activation Rep'!L:L),"")} | H5: =IF(or(F5="Active",G5="Active"),"Active","Not Active") -> Active | I5: {=XLOOKUP(A5,'Download of SFDC Activation Rep'!B:B,'Download of SFDC Activation Rep'!T:T)} -> 006UU00000LzrZs | J5: {=iferror(XLOOKUP(A5,'Download of SFDC Activation Rep'!B:B,'Download of SFDC Activation Rep'!C:C),"")} -> Net Conversion | K5: {=XLOOKUP(A5,'Download of SFDC Activation Rep'!B:B,'Download of SFDC Activation Rep'!X:X)} -> Kate Olivares | L5: {=xlookup(A5,'Download of SFDC Activation Rep'!B:B,'Download of SFDC Activation Rep'!Z:Z)} -> 45831
F6: {=iferror(XLOOKUP(A6,'Download of SFDC Activation Rep'!B:B,'Download of SFDC Activation Rep'!H:H),"")} -> Active | G6: {=iferror(xlookup(A6,'Download of SFDC Activation Rep'!B:B,'Download of SFDC Activation Rep'!L:L),"")} | H6: =IF(or(F6="Active",G6="Active"),"Active","Not Active") -> Active | I6: {=XLOOKUP(A6,'Download of SFDC Activation Rep'!B:B,'Download of SFDC Activation Rep'!T:T)} -> 006VT00000pom8v | J6: {=iferror(XLOOKUP(A6,'Download of SFDC Activation Rep'!B:B,'Download of SFDC Activation Rep'!C:C),"")} -> Kloris LLC | K6: {=XLOOKUP(A6,'Download of SFDC Activation Rep'!B:B,'Download of SFDC Activation Rep'!X:X)} -> Arianna Modesti | L6: {=xlookup(A6,'Download of SFDC Activation Rep'!B:B,'Download of SFDC Activation Rep'!Z:Z)} -> 46136 | M6: Avg GP per Org | N6: =N13/N2 -> 227.2066
F7: {=iferror(XLOOKUP(A7,'Download of SFDC Activation Rep'!B:B,'Download of SFDC Activation Rep'!H:H),"")} -> Active | G7: {=iferror(xlookup(A7,'Download of SFDC Activation Rep'!B:B,'Download of SFDC Activation Rep'!L:L),"")} | H7: =IF(or(F7="Active",G7="Active"),"Active","Not Active") -> Active | I7: {=XLOOKUP(A7,'Download of SFDC Activation Rep'!B:B,'Download of SFDC Activation Rep'!T:T)} -> 006VT00000sgdkF | J7: {=iferror(XLOOKUP(A7,'Download of SFDC Activation Rep'!B:B,'Download of SFDC Activation Rep'!C:C),"")} -> Naz Apparel | K7: {=XLOOKUP(A7,'Download of SFDC Activation Rep'!B:B,'Download of SFDC Activation Rep'!X:X)} -> Arianna Modesti | L7: {=xlookup(A7,'Download of SFDC Activation Rep'!B:B,'Download of SFDC Activation Rep'!Z:Z)} -> 46197
F8: {=iferror(XLOOKUP(A8,'Download of SFDC Activation Rep'!B:B,'Download of SFDC Activation Rep'!H:H),"")} -> Active | G8: {=iferror(xlookup(A8,'Download of SFDC Activation Rep'!B:B,'Download of SFDC Activation Rep'!L:L),"")} | H8: =IF(or(F8="Active",G8="Active"),"Active","Not Active") -> Active | I8: {=XLOOKUP(A8,'Download of SFDC Activation Rep'!B:B,'Download of SFDC Activation Rep'!T:T)} -> 006UU00000Lzmjj | J8: {=iferror(XLOOKUP(A8,'Download of SFDC Activation Rep'!B:B,'Download of SFDC Activation Rep'!C:C),"")} -> Hendersonville Community Co-Op | K8: {=XLOOKUP(A8,'Download of SFDC Activation Rep'!B:B,'Download of SFDC Activation Rep'!X:X)} -> Matthew Frost | L8: {=xlookup(A8,'Download of SFDC Activation Rep'!B:B,'Download of SFDC Activation Rep'!Z:Z)} -> 45891
F9: {=iferror(XLOOKUP(A9,'Download of SFDC Activation Rep'!B:B,'Download of SFDC Activation Rep'!H:H),"")} -> Active | G9: {=iferror(xlookup(A9,'Download of SFDC Activation Rep'!B:B,'Download of SFDC Activation Rep'!L:L),"")} -> Active | H9: =IF(or(F9="Active",G9="Active"),"Active","Not Active") -> Active | I9: {=XLOOKUP(A9,'Download of SFDC Activation Rep'!B:B,'Download of SFDC Activation Rep'!T:T)} -> 006UU00000OgQGQ | J9: {=iferror(XLOOKUP(A9,'Download of SFDC Activation Rep'!B:B,'Download of SFDC Activation Rep'!C:C),"")} -> Scale Foundations Inc. | K9: {=XLOOKUP(A9,'Download of SFDC Activation Rep'!B:B,'Download of SFDC Activation Rep'!X:X)} -> Matthew Frost | L9: {=xlookup(A9,'Download of SFDC Activation Rep'!B:B,'Download of SFDC Activation Rep'!Z:Z)} -> 46028
F10: {=iferror(XLOOKUP(A10,'Download of SFDC Activation Rep'!B:B,'Download of SFDC Activation Rep'!H:H),"")} -> Active | G10: {=iferror(xlookup(A10,'Download of SFDC Activation Rep'!B:B,'Download of SFDC Activation Rep'!L:L),"")} | H10: =IF(or(F10="Active",G10="Active"),"Active","Not Active") -> Active | I10: {=XLOOKUP(A10,'Download of SFDC Activation Rep'!B:B,'Download of SFDC Activation Rep'!T:T)} -> 006VT00000niYeT | J10: {=iferror(XLOOKUP(A10,'Download of SFDC Activation Rep'!B:B,'Download of SFDC Activation Rep'!C:C),"")} -> Brian Schmidt Builder | K10: {=XLOOKUP(A10,'Download of SFDC Activation Rep'!B:B,'Download of SFDC Activation Rep'!X:X)} -> Arianna Modesti | L10: {=xlookup(A10,'Download of SFDC Activation Rep'!B:B,'Download of SFDC Activation Rep'!Z:Z)} -> 46092
F11: {=iferror(XLOOKUP(A11,'Download of SFDC Activation Rep'!B:B,'Download of SFDC Activation Rep'!H:H),"")} -> Active | G11: {=iferror(xlookup(A11,'Download of SFDC Activation Rep'!B:B,'Download of SFDC Activation Rep'!L:L),"")} | H11: =IF(or(F11="Active",G11="Active"),"Active","Not Active") -> Active | I11: {=XLOOKUP(A11,'Download of SFDC Activation Rep'!B:B,'Download of SFDC Activation Rep'!T:T)} -> 006UU00000LzrZl | J11: {=iferror(XLOOKUP(A11,'Download of SFDC Activation Rep'!B:B,'Download of SFDC Activation Rep'!C:C),"")} -> Toland Construction - MO
F12: {=iferror(XLOOKUP(A12,'Download of SFDC Activation Rep'!B:B,'Download of SFDC Activation Rep'!H:H),"")} -> Active | G12: {=iferror(xlookup(A12,'Download of SFDC Activation Rep'!B:B,'Download of SFDC Activation Rep'!L:L),"")} | H12: =IF(or(F12="Active",G12="Active"),"Active","Not Active") -> Active | I12: {=XLOOKUP(A12,'Download of SFDC Activation Rep'!B:B,'Download of SFDC Activation Rep'!T:T)} -> 006VT00000qfNVl | J12: {=iferror(XLOOKUP(A12,'Download of SFDC Activation Rep'!B:B,'Download of SFDC Activation Rep'!C:C),"")} -> GK Truckline | K12: {=XLOOKUP(A12,'Download of SFDC Activation Rep'!B:B,'Download of SFDC Activation Rep'!X:X)} -> Kate Olivares | L12: {=xlookup(A12,'Download of SFDC Activation Rep'!B:B,'Download of SFDC Activation Rep'!Z:Z)} -> 46155
F13: {=iferror(XLOOKUP(A13,'Download of SFDC Activation Rep'!B:B,'Download of SFDC Activation Rep'!H:H),"")} -> Active | G13: {=iferror(xlookup(A13,'Download of SFDC Activation Rep'!B:B,'Download of SFDC Activation Rep'!L:L),"")} | H13: =IF(or(F13="Active",G13="Active"),"Active","Not Active") -> Active | I13: {=XLOOKUP(A13,'Download of SFDC Activation Rep'!B:B,'Download of SFDC Activation Rep'!T:T)} -> 006UU00000O1KbZ | J13: {=iferror(XLOOKUP(A13,'Download of SFDC Activation Rep'!B:B,'Download of SFDC Activation Rep'!C:C),"")} -> MJDII Architects, Inc. | K13: {=XLOOKUP(A13,'Download of SFDC Activation Rep'!B:B,'Download of SFDC Activation Rep'!X:X)} -> Matthew Frost | L13: {=xlookup(A13,'Download of SFDC Activation Rep'!B:B,'Download of SFDC Activation Rep'!Z:Z)} -> 46007 | M13: Total GP Generated | N13: =SUM(B:B) -> 27491.998
F14: {=iferror(XLOOKUP(A14,'Download of SFDC Activation Rep'!B:B,'Download of SFDC Activation Rep'!H:H),"")} -> Active | G14: {=iferror(xlookup(A14,'Download of SFDC Activation Rep'!B:B,'Download of SFDC Activation Rep'!L:L),"")} | H14: =IF(or(F14="Active",G14="Active"),"Active","Not Active") -> Active | I14: {=XLOOKUP(A14,'Download of SFDC Activation Rep'!B:B,'Download of SFDC Activation Rep'!T:T)} -> 006UU00000MQpnD | J14: {=iferror(XLOOKUP(A14,'Download of SFDC Activation Rep'!B:B,'Download of SFDC Activation Rep'!C:C),"")} -> Expert Semiconductor Technology, inc | K14: {=XLOOKUP(A14,'Download of SFDC Activation Rep'!B:B,'Download of SFDC Activation Rep'!X:X)} -> Kate Olivares | L14: {=xlookup(A14,'Download of SFDC Activation Rep'!B:B,'Download of SFDC Activation Rep'!Z:Z)} -> 45818
F15: {=iferror(XLOOKUP(A15,'Download of SFDC Activation Rep'!B:B,'Download of SFDC Activation Rep'!H:H),"")} -> Active | G15: {=iferror(xlookup(A15,'Download of SFDC Activation Rep'!B:B,'Download of SFDC Activation Rep'!L:L),"")} | H15: =IF(or(F15="Active",G15="Active"),"Active","Not Active") -> Active | I15: {=XLOOKUP(A15,'Download of SFDC Activation Rep'!B:B,'Download of SFDC Activation Rep'!T:T)} -> 006VT00000oiGKQ | J15: {=iferror(XLOOKUP(A15,'Download of SFDC Activation Rep'!B:B,'Download of SFDC Activation Rep'!C:C),"")} -> Landa Cleary Travel Co. Inc. D.B.A. Mater Dei Tours | K15: {=XLOOKUP(A15,'Download of SFDC Activation Rep'!B:B,'Download of SFDC Activation Rep'!X:X)} -> Arianna Modesti | L15: {=xlookup(A15,'Download of SFDC Activation Rep'!B:B,'Download of SFDC Activation Rep'!Z:Z)} -> 46113 | M15: Total TPV Generated | N15: =SUM(D:D) -> 15759187
F16: {=iferror(XLOOKUP(A16,'Download of SFDC Activation Rep'!B:B,'Download of SFDC Activation Rep'!H:H),"")} -> Active | G16: {=iferror(xlookup(A16,'Download of SFDC Activation Rep'!B:B,'Download of SFDC Activation Rep'!L:L),"")} | H16: =IF(or(F16="Active",G16="Active"),"Active","Not Active") -> Active | I16: {=XLOOKUP(A16,'Download of SFDC Activation Rep'!B:B,'Download of SFDC Activation Rep'!T:T)} -> 006UU00000MU72b | J16: {=iferror(XLOOKUP(A16,'Download of SFDC Activation Rep'!B:B,'Download of SFDC Activation Rep'!C:C),"")} -> Buescher Ranch | K16: {=XLOOKUP(A16,'Download of SFDC Activation Rep'!B:B,'Download of SFDC Activation Rep'!X:X)} -> Kate Olivares | L16: {=xlookup(A16,'Download of SFDC Activation Rep'!B:B,'Download of SFDC Activation Rep'!Z:Z)} -> 45966
F17: {=iferror(XLOOKUP(A17,'Download of SFDC Activation Rep'!B:B,'Download of SFDC Activation Rep'!H:H),"")} -> Active | G17: {=iferror(xlookup(A17,'Download of SFDC Activation Rep'!B:B,'Download of SFDC Activation Rep'!L:L),"")} | H17: =IF(or(F17="Active",G17="Active"),"Active","Not Active") -> Active | I17: {=XLOOKUP(A17,'Download of SFDC Activation Rep'!B:B,'Download of SFDC Activation Rep'!T:T)} -> 006UU00000OcWHB | J17: {=iferror(XLOOKUP(A17,'Download of SFDC Activation Rep'!B:B,'Download of SFDC Activation Rep'!C:C),"")} -> Kenneth Adam Designs | K17: {=XLOOKUP(A17,'Download of SFDC Activation Rep'!B:B,'Download of SFDC Activation Rep'!X:X)} -> Matthew Frost | L17: {=xlookup(A17,'Download of SFDC Activation Rep'!B:B,'Download of SFDC Activation Rep'!Z:Z)} -> 46027
F18: {=iferror(XLOOKUP(A18,'Download of SFDC Activation Rep'!B:B,'Download of SFDC Activation Rep'!H:H),"")} -> Active | G18: {=iferror(xlookup(A18,'Download of SFDC Activation Rep'!B:B,'Download of SFDC Activation Rep'!L:L),"")} | H18: =IF(or(F18="Active",G18="Active"),"Active","Not Active") -> Active | I18: {=XLOOKUP(A18,'Download of SFDC Activation Rep'!B:B,'Download of SFDC Activation Rep'!T:T)} -> 006UU00000KruBr | J18: {=iferror(XLOOKUP(A18,'Download of SFDC Activation Rep'!B:B,'Download of SFDC Activation Rep'!C:C),"")} -> megg mining llc | K18: {=XLOOKUP(A18,'Download of SFDC Activation Rep'!B:B,'Download of SFDC Activation Rep'!X:X)} -> Rudy Maestas | L18: {=xlookup(A18,'Download of SFDC Activation Rep'!B:B,'Download of SFDC Activation Rep'!Z:Z)} -> 45924 | M18: Median TPV per Org per Month | N18: =MEDIAN(D:D) -> 27018.47
F19: {=iferror(XLOOKUP(A19,'Download of SFDC Activation Rep'!B:B,'Download of SFDC Activation Rep'!H:H),"")} -> Active | G19: {=iferror(xlookup(A19,'Download of SFDC Activation Rep'!B:B,'Download of SFDC Activation Rep'!L:L),"")} | H19: =IF(or(F19="Active",G19="Active"),"Active","Not Active") -> Active | I19: {=XLOOKUP(A19,'Download of SFDC Activation Rep'!B:B,'Download of SFDC Activation Rep'!T:T)} -> 006UU00000MQpnP | J19: {=iferror(XLOOKUP(A19,'Download of SFDC Activation Rep'!B:B,'Download of SFDC Activation Rep'!C:C),"")} -> United Home Care LLC | K19: {=XLOOKUP(A19,'Download of SFDC Activation Rep'!B:B,'Download of SFDC Activation Rep'!X:X)} -> Kate Olivares | L19: {=xlookup(A19,'Download of SFDC Activation Rep'!B:B,'Download of SFDC Activation Rep'!Z:Z)} -> 45839 | M19: Median Monthly GP per Org | N19: =MEDIAN(B:B) -> 60.1
F20: {=iferror(XLOOKUP(A20,'Download of SFDC Activation Rep'!B:B,'Download of SFDC Activation Rep'!H:H),"")} -> Active | G20: {=iferror(xlookup(A20,'Download of SFDC Activation Rep'!B:B,'Download of SFDC Activation Rep'!L:L),"")} | H20: =IF(or(F20="Active",G20="Active"),"Active","Not Active") -> Active | I20: {=XLOOKUP(A20,'Download of SFDC Activation Rep'!B:B,'Download of SFDC Activation Rep'!T:T)} -> 006VT00000qes29 | J20: {=iferror(XLOOKUP(A20,'Download of SFDC Activation Rep'!B:B,'Download of SFDC Activation Rep'!C:C),"")} -> Temporary Assistance Guru, Inc | K20: {=XLOOKUP(A20,'Download of SFDC Activation Rep'!B:B,'Download of SFDC Activation Rep'!X:X)} -> Arianna Modesti | L20: {=xlookup(A20,'Download of SFDC Activation Rep'!B:B,'Download of SFDC Activation Rep'!Z:Z)} -> 46155
F21: {=iferror(XLOOKUP(A21,'Download of SFDC Activation Rep'!B:B,'Download of SFDC Activation Rep'!H:H),"")} -> Active | G21: {=iferror(xlookup(A21,'Download of SFDC Activation Rep'!B:B,'Download of SFDC Activation Rep'!L:L),"")} | H21: =IF(or(F21="Active",G21="Active"),"Active","Not Active") -> Active | I21: {=XLOOKUP(A21,'Download of SFDC Activation Rep'!B:B,'Download of SFDC Activation Rep'!T:T)} -> 006UU00000MGsar | J21: {=iferror(XLOOKUP(A21,'Download of SFDC Activation Rep'!B:B,'Download of SFDC Activation Rep'!C:C),"")} -> Protagenic Therapeutics, Inc. | K21: {=XLOOKUP(A21,'Download of SFDC Activation Rep'!B:B,'Download of SFDC Activation Rep'!X:X)} -> Matthew Frost | L21: {=xlookup(A21,'Download of SFDC Activation Rep'!B:B,'Download of SFDC Activation Rep'!Z:Z)} -> 45960
F22: {=iferror(XLOOKUP(A22,'Download of SFDC Activation Rep'!B:B,'Download of SFDC Activation Rep'!H:H),"")} -> Inactive | G22: {=iferror(xlookup(A22,'Download of SFDC Activation Rep'!B:B,'Download of SFDC Activation Rep'!L:L),"")} -> Active | H22: =IF(or(F22="Active",G22="Active"),"Active","Not Active") -> Active | I22: {=XLOOKUP(A22,'Download of SFDC Activation Rep'!B:B,'Download of SFDC Activation Rep'!T:T)} -> 006VT00000sgdkD | J22: {=iferror(XLOOKUP(A22,'Download of SFDC Activation Rep'!B:B,'Download of SFDC Activation Rep'!C:C),"")} -> lanier welding products | K22: {=XLOOKUP(A22,'Download of SFDC Activation Rep'!B:B,'Download of SFDC Activation Rep'!X:X)} -> Arianna Modesti | L22: {=xlookup(A22,'Download of SFDC Activation Rep'!B:B,'Download of SFDC Activation Rep'!Z:Z)} -> 46197
F23: {=iferror(XLOOKUP(A23,'Download of SFDC Activation Rep'!B:B,'Download of SFDC Activation Rep'!H:H),"")} -> Active | G23: {=iferror(xlookup(A23,'Download of SFDC Activation Rep'!B:B,'Download of SFDC Activation Rep'!L:L),"")} -> Active | H23: =IF(or(F23="Active",G23="Active"),"Active","Not Active") -> Active | I23: {=XLOOKUP(A23,'Download of SFDC Activation Rep'!B:B,'Download of SFDC Activation Rep'!T:T)} -> 006UU00000LzrZk | J23: {=iferror(XLOOKUP(A23,'Download of SFDC Activation Rep'!B:B,'Download of SFDC Activation Rep'!C:C),"")} -> Rumford Stone, Inc | K23: {=XLOOKUP(A23,'Download of SFDC Activation Rep'!B:B,'Download of SFDC Activation Rep'!X:X)} -> Kate Olivares | L23: {=xlookup(A23,'Download of SFDC Activation Rep'!B:B,'Download of SFDC Activation Rep'!Z:Z)} -> 45797
F24: {=iferror(XLOOKUP(A24,'Download of SFDC Activation Rep'!B:B,'Download of SFDC Activation Rep'!H:H),"")} -> Active | G24: {=iferror(xlookup(A24,'Download of SFDC Activation Rep'!B:B,'Download of SFDC Activation Rep'!L:L),"")} | H24: =IF(or(F24="Active",G24="Active"),"Active","Not Active") -> Active | I24: {=XLOOKUP(A24,'Download of SFDC Activation Rep'!B:B,'Download of SFDC Activation Rep'!T:T)} -> 006UU00000LzrZp | J24: {=iferror(XLOOKUP(A24,'Download of SFDC Activation Rep'!B:B,'Download of SFDC Activation Rep'!C:C),"")} -> Liberty Orchards LLC | K24: {=XLOOKUP(A24,'Download of SFDC Activation Rep'!B:B,'Download of SFDC Activation Rep'!X:X)} -> Kate Olivares | L24: {=xlookup(A24,'Download of SFDC Activation Rep'!B:B,'Download of SFDC Activation Rep'!Z:Z)} -> 45856
F25: {=iferror(XLOOKUP(A25,'Download of SFDC Activation Rep'!B:B,'Download of SFDC Activation Rep'!H:H),"")} -> Active | G25: {=iferror(xlookup(A25,'Download of SFDC Activation Rep'!B:B,'Download of SFDC Activation Rep'!L:L),"")} | H25: =IF(or(F25="Active",G25="Active"),"Active","Not Active") -> Active | I25: {=XLOOKUP(A25,'Download of SFDC Activation Rep'!B:B,'Download of SFDC Activation Rep'!T:T)} -> 006UU00000LzrZn | J25: {=iferror(XLOOKUP(A25,'Download of SFDC Activation Rep'!B:B,'Download of SFDC Activation Rep'!C:C),"")} -> CRUSHS | K25: {=XLOOKUP(A25,'Download of SFDC Activation Rep'!B:B,'Download of SFDC Activation Rep'!X:X)} -> Matthew Frost | L25: {=xlookup(A25,'Download of SFDC Activation Rep'!B:B,'Download of SFDC Activation Rep'!Z:Z)} -> 45890
F26: {=iferror(XLOOKUP(A26,'Download of SFDC Activation Rep'!B:B,'Download of SFDC Activation Rep'!H:H),"")} -> Active | G26: {=iferror(xlookup(A26,'Download of SFDC Activation Rep'!B:B,'Download of SFDC Activation Rep'!L:L),"")} -> Active | H26: =IF(or(F26="Active",G26="Active"),"Active","Not Active") -> Active | I26: {=XLOOKUP(A26,'Download of SFDC Activation Rep'!B:B,'Download of SFDC Activation Rep'!T:T)} -> 006UU00000O1zBi | J26: {=iferror(XLOOKUP(A26,'Download of SFDC Activation Rep'!B:B,'Download of SFDC Activation Rep'!C:C),"")} -> Friendly Foods Inc
F27: {=iferror(XLOOKUP(A27,'Download of SFDC Activation Rep'!B:B,'Download of SFDC Activation Rep'!H:H),"")} -> Active | G27: {=iferror(xlookup(A27,'Download of SFDC Activation Rep'!B:B,'Download of SFDC Activation Rep'!L:L),"")} | H27: =IF(or(F27="Active",G27="Active"),"Active","Not Active") -> Active | I27: {=XLOOKUP(A27,'Download of SFDC Activation Rep'!B:B,'Download of SFDC Activation Rep'!T:T)} -> 006VT00000qMODp | J27: {=iferror(XLOOKUP(A27,'Download of SFDC Activation Rep'!B:B,'Download of SFDC Activation Rep'!C:C),"")} -> Willard Manufacturing | K27: {=XLOOKUP(A27,'Download of SFDC Activation Rep'!B:B,'Download of SFDC Activation Rep'!X:X)} -> Arianna Modesti | L27: {=xlookup(A27,'Download of SFDC Activation Rep'!B:B,'Download of SFDC Activation Rep'!Z:Z)} -> 46148
F28: {=iferror(XLOOKUP(A28,'Download of SFDC Activation Rep'!B:B,'Download of SFDC Activation Rep'!H:H),"")} -> Active | G28: {=iferror(xlookup(A28,'Download of SFDC Activation Rep'!B:B,'Download of SFDC Activation Rep'!L:L),"")} | H28: =IF(or(F28="Active",G28="Active"),"Active","Not Active") -> Active | I28: {=XLOOKUP(A28,'Download of SFDC Activation Rep'!B:B,'Download of SFDC Activation Rep'!T:T)} -> 006UU00000MpN7Z | J28: {=iferror(XLOOKUP(A28,'Download of SFDC Activation Rep'!B:B,'Download of SFDC Activation Rep'!C:C),"")} -> Liberty Land Management LLC | K28: {=XLOOKUP(A28,'Download of SFDC Activation Rep'!B:B,'Download of SFDC Activation Rep'!X:X)} -> Kate Olivares | L28: {=xlookup(A28,'Download of SFDC Activation Rep'!B:B,'Download of SFDC Activation Rep'!Z:Z)} -> 45974
F29: {=iferror(XLOOKUP(A29,'Download of SFDC Activation Rep'!B:B,'Download of SFDC Activation Rep'!H:H),"")} -> Active | G29: {=iferror(xlookup(A29,'Download of SFDC Activation Rep'!B:B,'Download of SFDC Activation Rep'!L:L),"")} -> Inactive | H29: =IF(or(F29="Active",G29="Active"),"Active","Not Active") -> Active | I29: {=XLOOKUP(A29,'Download of SFDC Activation Rep'!B:B,'Download of SFDC Activation Rep'!T:T)} -> 006UU00000Lzmjh | J29: {=iferror(XLOOKUP(A29,'Download of SFDC Activation Rep'!B:B,'Download of SFDC Activation Rep'!C:C),"")} -> ClearBlu Environmental | K29: {=XLOOKUP(A29,'Download of SFDC Activation Rep'!B:B,'Download of SFDC Activation Rep'!X:X)} -> Kate Olivares | L29: {=xlookup(A29,'Download of SFDC Activation Rep'!B:B,'Download of SFDC Activation Rep'!Z:Z)} -> 45896
F30: {=iferror(XLOOKUP(A30,'Download of SFDC Activation Rep'!B:B,'Download of SFDC Activation Rep'!H:H),"")} -> Active | G30: {=iferror(xlookup(A30,'Download of SFDC Activation Rep'!B:B,'Download of SFDC Activation Rep'!L:L),"")} | H30: =IF(or(F30="Active",G30="Active"),"Active","Not Active") -> Active | I30: {=XLOOKUP(A30,'Download of SFDC Activation Rep'!B:B,'Download of SFDC Activation Rep'!T:T)} -> 006VT00000qLJJR | J30: {=iferror(XLOOKUP(A30,'Download of SFDC Activation Rep'!B:B,'Download of SFDC Activation Rep'!C:C),"")} -> Lyophilization Systems Inc. | K30: {=XLOOKUP(A30,'Download of SFDC Activation Rep'!B:B,'Download of SFDC Activation Rep'!X:X)} -> Arianna Modesti | L30: {=xlookup(A30,'Download of SFDC Activation Rep'!B:B,'Download of SFDC Activation Rep'!Z:Z)} -> 46148
F31: {=iferror(XLOOKUP(A31,'Download of SFDC Activation Rep'!B:B,'Download of SFDC Activation Rep'!H:H),"")} -> Active | G31: {=iferror(xlookup(A31,'Download of SFDC Activation Rep'!B:B,'Download of SFDC Activation Rep'!L:L),"")} | H31: =IF(or(F31="Active",G31="Active"),"Active","Not Active") -> Active | I31: {=XLOOKUP(A31,'Download of SFDC Activation Rep'!B:B,'Download of SFDC Activation Rep'!T:T)} -> 006VT00000mhbv7 | J31: {=iferror(XLOOKUP(A31,'Download of SFDC Activation Rep'!B:B,'Download of SFDC Activation Rep'!C:C),"")} -> YRS LLC | K31: {=XLOOKUP(A31,'Download of SFDC Activation Rep'!B:B,'Download of SFDC Activation Rep'!X:X)} -> Matthew Frost | L31: {=xlookup(A31,'Download of SFDC Activation Rep'!B:B,'Download of SFDC Activation Rep'!Z:Z)} -> 46071
F32: {=iferror(XLOOKUP(A32,'Download of SFDC Activation Rep'!B:B,'Download of SFDC Activation Rep'!H:H),"")} | G32: {=iferror(xlookup(A32,'Download of SFDC Activation Rep'!B:B,'Download of SFDC Activation Rep'!L:L),"")} -> Active | H32: =IF(or(F32="Active",G32="Active"),"Active","Not Active") -> Active | I32: {=XLOOKUP(A32,'Download of SFDC Activation Rep'!B:B,'Download of SFDC Activation Rep'!T:T)} -> 006UU00000LSvAX | J32: {=iferror(XLOOKUP(A32,'Download of SFDC Activation Rep'!B:B,'Download of SFDC Activation Rep'!C:C),"")} -> Rippa USA Sales LLC. | K32: {=XLOOKUP(A32,'Download of SFDC Activation Rep'!B:B,'Download of SFDC Activation Rep'!X:X)} -> Matthew Frost | L32: {=xlookup(A32,'Download of SFDC Activation Rep'!B:B,'Download of SFDC Activation Rep'!Z:Z)} -> 45940
F33: {=iferror(XLOOKUP(A33,'Download of SFDC Activation Rep'!B:B,'Download of SFDC Activation Rep'!H:H),"")} -> Active | G33: {=iferror(xlookup(A33,'Download of SFDC Activation Rep'!B:B,'Download of SFDC Activation Rep'!L:L),"")} | H33: =IF(or(F33="Active",G33="Active"),"Active","Not Active") -> Active | I33: {=XLOOKUP(A33,'Download of SFDC Activation Rep'!B:B,'Download of SFDC Activation Rep'!T:T)} -> 006VT00000q0rzF | J33: {=iferror(XLOOKUP(A33,'Download of SFDC Activation Rep'!B:B,'Download of SFDC Activation Rep'!C:C),"")} -> Boston Granite Exchange | K33: {=XLOOKUP(A33,'Download of SFDC Activation Rep'!B:B,'Download of SFDC Activation Rep'!X:X)} -> Arianna Modesti | L33: {=xlookup(A33,'Download of SFDC Activation Rep'!B:B,'Download of SFDC Activation Rep'!Z:Z)} -> 46141
F34: {=iferror(XLOOKUP(A34,'Download of SFDC Activation Rep'!B:B,'Download of SFDC Activation Rep'!H:H),"")} | G34: {=iferror(xlookup(A34,'Download of SFDC Activation Rep'!B:B,'Download of SFDC Activation Rep'!L:L),"")} -> Active | H34: =IF(or(F34="Active",G34="Active"),"Active","Not Active") -> Active | I34: {=XLOOKUP(A34,'Download of SFDC Activation Rep'!B:B,'Download of SFDC Activation Rep'!T:T)} -> 006UU00000Lzkqw | J34: {=iferror(XLOOKUP(A34,'Download of SFDC Activation Rep'!B:B,'Download of SFDC Activation Rep'!C:C),"")} -> Rminvestmentsmiami LLC | K34: {=XLOOKUP(A34,'Download of SFDC Activation Rep'!B:B,'Download of SFDC Activation Rep'!X:X)} -> Matthew Frost | L34: {=xlookup(A34,'Download of SFDC Activation Rep'!B:B,'Download of SFDC Activation Rep'!Z:Z)} -> 45903
F35: {=iferror(XLOOKUP(A35,'Download of SFDC Activation Rep'!B:B,'Download of SFDC Activation Rep'!H:H),"")} -> Active | G35: {=iferror(xlookup(A35,'Download of SFDC Activation Rep'!B:B,'Download of SFDC Activation Rep'!L:L),"")} | H35: =IF(or(F35="Active",G35="Active"),"Active","Not Active") -> Active | I35: {=XLOOKUP(A35,'Download of SFDC Activation Rep'!B:B,'Download of SFDC Activation Rep'!T:T)} -> 006VT00000o0IBR | J35: {=iferror(XLOOKUP(A35,'Download of SFDC Activation Rep'!B:B,'Download of SFDC Activation Rep'!C:C),"")} -> Cope Equities | K35: {=XLOOKUP(A35,'Download of SFDC Activation Rep'!B:B,'Download of SFDC Activation Rep'!X:X)} -> Matthew Frost | L35: {=xlookup(A35,'Download of SFDC Activation Rep'!B:B,'Download of SFDC Activation Rep'!Z:Z)} -> 46099
F36: {=iferror(XLOOKUP(A36,'Download of SFDC Activation Rep'!B:B,'Download of SFDC Activation Rep'!H:H),"")} -> Active | G36: {=iferror(xlookup(A36,'Download of SFDC Activation Rep'!B:B,'Download of SFDC Activation Rep'!L:L),"")} | H36: =IF(or(F36="Active",G36="Active"),"Active","Not Active") -> Active | I36: {=XLOOKUP(A36,'Download of SFDC Activation Rep'!B:B,'Download of SFDC Activation Rep'!T:T)} -> 006VT00000mBkrt | J36: {=iferror(XLOOKUP(A36,'Download of SFDC Activation Rep'!B:B,'Download of SFDC Activation Rep'!C:C),"")} -> Beyond Pickleball LLC | K36: {=XLOOKUP(A36,'Download of SFDC Activation Rep'!B:B,'Download of SFDC Activation Rep'!X:X)} -> Matthew Frost | L36: {=xlookup(A36,'Download of SFDC Activation Rep'!B:B,'Download of SFDC Activation Rep'!Z:Z)} -> 46059
F37: {=iferror(XLOOKUP(A37,'Download of SFDC Activation Rep'!B:B,'Download of SFDC Activation Rep'!H:H),"")} -> Active | G37: {=iferror(xlookup(A37,'Download of SFDC Activation Rep'!B:B,'Download of SFDC Activation Rep'!L:L),"")} | H37: =IF(or(F37="Active",G37="Active"),"Active","Not Active") -> Active | I37: {=XLOOKUP(A37,'Download of SFDC Activation Rep'!B:B,'Download of SFDC Activation Rep'!T:T)} -> 006VT00000owkyd | J37: {=iferror(XLOOKUP(A37,'Download of SFDC Activation Rep'!B:B,'Download of SFDC Activation Rep'!C:C),"")} -> Shri Krishna Inc | K37: {=XLOOKUP(A37,'Download of SFDC Activation Rep'!B:B,'Download of SFDC Activation Rep'!X:X)} -> Matthew Frost | L37: {=xlookup(A37,'Download of SFDC Activation Rep'!B:B,'Download of SFDC Activation Rep'!Z:Z)} -> 46119
F38: {=iferror(XLOOKUP(A38,'Download of SFDC Activation Rep'!B:B,'Download of SFDC Activation Rep'!H:H),"")} -> Active | G38: {=iferror(xlookup(A38,'Download of SFDC Activation Rep'!B:B,'Download of SFDC Activation Rep'!L:L),"")} | H38: =IF(or(F38="Active",G38="Active"),"Active","Not Active") -> Active | I38: {=XLOOKUP(A38,'Download of SFDC Activation Rep'!B:B,'Download of SFDC Activation Rep'!T:T)} -> 006VT00000nyDe5 | J38: {=iferror(XLOOKUP(A38,'Download of SFDC Activation Rep'!B:B,'Download of SFDC Activation Rep'!C:C),"")} -> Abecca Grace, LLC | K38: {=XLOOKUP(A38,'Download of SFDC Activation Rep'!B:B,'Download of SFDC Activation Rep'!X:X)} -> Matthew Frost | L38: {=xlookup(A38,'Download of SFDC Activation Rep'!B:B,'Download of SFDC Activation Rep'!Z:Z)} -> 46098
... F53: {=iferror(XLOOKUP(A53,'Download of SFDC Activation Rep'!B:B,'Download of SFDC Activation Rep'!H:H),"")} -> Active | G53: {=iferror(xlookup(A53,'Download of SFDC Activation Rep'!B:B,'Download of SFDC Activation Rep'!L:L),"")} | H53: =IF(or(F53="Active",G53="Active"),"Active","Not Active") -> Active | I53: {=XLOOKUP(A53,'Download of SFDC Activation Rep'!B:B,'Download of SFDC Activation Rep'!T:T)} -> 006UU00000N8qc7 | J53: {=iferror(XLOOKUP(A53,'Download of SFDC Activation Rep'!B:B,'Download of SFDC Activation Rep'!C:C),"")} -> Acme Fine Wines | K53: {=XLOOKUP(A53,'Download of SFDC Activation Rep'!B:B,'Download of SFDC Activation Rep'!X:X)} -> Kate Olivares | L53: {=xlookup(A53,'Download of SFDC Activation Rep'!B:B,'Download of SFDC Activation Rep'!Z:Z)} -> 45981
F54: {=iferror(XLOOKUP(A54,'Download of SFDC Activation Rep'!B:B,'Download of SFDC Activation Rep'!H:H),"")} -> Active | G54: {=iferror(xlookup(A54,'Download of SFDC Activation Rep'!B:B,'Download of SFDC Activation Rep'!L:L),"")} | H54: =IF(or(F54="Active",G54="Active"),"Active","Not Active") -> Active | I54: {=XLOOKUP(A54,'Download of SFDC Activation Rep'!B:B,'Download of SFDC Activation Rep'!T:T)} -> 006UU00000P2jh1 | J54: {=iferror(XLOOKUP(A54,'Download of SFDC Activation Rep'!B:B,'Download of SFDC Activation Rep'!C:C),"")} -> Herbert Law Group, LLC | L54: {=xlookup(A54,'Download of SFDC Activation Rep'!B:B,'Download of SFDC Activation Rep'!Z:Z)} -> 46037
F55: {=iferror(XLOOKUP(A55,'Download of SFDC Activation Rep'!B:B,'Download of SFDC Activation Rep'!H:H),"")} -> Active | G55: {=iferror(xlookup(A55,'Download of SFDC Activation Rep'!B:B,'Download of SFDC Activation Rep'!L:L),"")} -> Churned | H55: =IF(or(F55="Active",G55="Active"),"Active","Not Active") -> Active | I55: {=XLOOKUP(A55,'Download of SFDC Activation Rep'!B:B,'Download of SFDC Activation Rep'!T:T)} -> 006UU00000LzkrL | J55: {=iferror(XLOOKUP(A55,'Download of SFDC Activation Rep'!B:B,'Download of SFDC Activation Rep'!C:C),"")} -> The Arts Club of Chicago | K55: {=XLOOKUP(A55,'Download of SFDC Activation Rep'!B:B,'Download of SFDC Activation Rep'!X:X)} -> Matthew Frost | L55: {=xlookup(A55,'Download of SFDC Activation Rep'!B:B,'Download of SFDC Activation Rep'!Z:Z)} -> 45904
F56: {=iferror(XLOOKUP(A56,'Download of SFDC Activation Rep'!B:B,'Download of SFDC Activation Rep'!H:H),"")} -> Active | G56: {=iferror(xlookup(A56,'Download of SFDC Activation Rep'!B:B,'Download of SFDC Activation Rep'!L:L),"")} | H56: =IF(or(F56="Active",G56="Active"),"Active","Not Active") -> Active | I56: {=XLOOKUP(A56,'Download of SFDC Activation Rep'!B:B,'Download of SFDC Activation Rep'!T:T)} -> 006UU00000MQpnS | J56: {=iferror(XLOOKUP(A56,'Download of SFDC Activation Rep'!B:B,'Download of SFDC Activation Rep'!C:C),"")} -> Meralex Farm, Inc. | K56: {=XLOOKUP(A56,'Download of SFDC Activation Rep'!B:B,'Download of SFDC Activation Rep'!X:X)} -> Kate Olivares | L56: {=xlookup(A56,'Download of SFDC Activation Rep'!B:B,'Download of SFDC Activation Rep'!Z:Z)} -> 45809
F57: {=iferror(XLOOKUP(A57,'Download of SFDC Activation Rep'!B:B,'Download of SFDC Activation Rep'!H:H),"")} -> Active | G57: {=iferror(xlookup(A57,'Download of SFDC Activation Rep'!B:B,'Download of SFDC Activation Rep'!L:L),"")} | H57: =IF(or(F57="Active",G57="Active"),"Active","Not Active") -> Active | I57: {=XLOOKUP(A57,'Download of SFDC Activation Rep'!B:B,'Download of SFDC Activation Rep'!T:T)} -> 006UU00000MIrPN | J57: {=iferror(XLOOKUP(A57,'Download of SFDC Activation Rep'!B:B,'Download of SFDC Activation Rep'!C:C),"")} -> National Rural Health Association | K57: {=XLOOKUP(A57,'Download of SFDC Activation Rep'!B:B,'Download of SFDC Activation Rep'!X:X)} -> Matthew Frost | L57: {=xlookup(A57,'Download of SFDC Activation Rep'!B:B,'Download of SFDC Activation Rep'!Z:Z)} -> 45961
F58: {=iferror(XLOOKUP(A58,'Download of SFDC Activation Rep'!B:B,'Download of SFDC Activation Rep'!H:H),"")} -> Active | G58: {=iferror(xlookup(A58,'Download of SFDC Activation Rep'!B:B,'Download of SFDC Activation Rep'!L:L),"")} | H58: =IF(or(F58="Active",G58="Active"),"Active","Not Active") -> Active | I58: {=XLOOKUP(A58,'Download of SFDC Activation Rep'!B:B,'Download of SFDC Activation Rep'!T:T)} -> 006UU00000Lzkqn | J58: {=iferror(XLOOKUP(A58,'Download of SFDC Activation Rep'!B:B,'Download of SFDC Activation Rep'!C:C),"")} -> Stupendous Events LLC | K58: {=XLOOKUP(A58,'Download of SFDC Activation Rep'!B:B,'Download of SFDC Activation Rep'!X:X)} -> Kate Olivares | L58: {=xlookup(A58,'Download of SFDC Activation Rep'!B:B,'Download of SFDC Activation Rep'!Z:Z)} -> 45817
F59: {=iferror(XLOOKUP(A59,'Download of SFDC Activation Rep'!B:B,'Download of SFDC Activation Rep'!H:H),"")} -> Active | G59: {=iferror(xlookup(A59,'Download of SFDC Activation Rep'!B:B,'Download of SFDC Activation Rep'!L:L),"")} | H59: =IF(or(F59="Active",G59="Active"),"Active","Not Active") -> Active | I59: {=XLOOKUP(A59,'Download of SFDC Activation Rep'!B:B,'Download of SFDC Activation Rep'!T:T)} -> 006VT00000m8uPZ | J59: {=iferror(XLOOKUP(A59,'Download of SFDC Activation Rep'!B:B,'Download of SFDC Activation Rep'!C:C),"")} -> St George Spirits | K59: {=XLOOKUP(A59,'Download of SFDC Activation Rep'!B:B,'Download of SFDC Activation Rep'!X:X)} -> Matthew Frost | L59: {=xlookup(A59,'Download of SFDC Activation Rep'!B:B,'Download of SFDC Activation Rep'!Z:Z)} -> 46058
F60: {=iferror(XLOOKUP(A60,'Download of SFDC Activation Rep'!B:B,'Download of SFDC Activation Rep'!H:H),"")} -> Active | G60: {=iferror(xlookup(A60,'Download of SFDC Activation Rep'!B:B,'Download of SFDC Activation Rep'!L:L),"")} | H60: =IF(or(F60="Active",G60="Active"),"Active","Not Active") -> Active | I60: {=XLOOKUP(A60,'Download of SFDC Activation Rep'!B:B,'Download of SFDC Activation Rep'!T:T)} -> 006VT00000m4kgX | J60: {=iferror(XLOOKUP(A60,'Download of SFDC Activation Rep'!B:B,'Download of SFDC Activation Rep'!C:C),"")} -> GF Equine LLC | K60: {=XLOOKUP(A60,'Download of SFDC Activation Rep'!B:B,'Download of SFDC Activation Rep'!X:X)} -> Matthew Frost | L60: {=xlookup(A60,'Download of SFDC Activation Rep'!B:B,'Download of SFDC Activation Rep'!Z:Z)} -> 46057
F61: {=iferror(XLOOKUP(A61,'Download of SFDC Activation Rep'!B:B,'Download of SFDC Activation Rep'!H:H),"")} -> Active | G61: {=iferror(xlookup(A61,'Download of SFDC Activation Rep'!B:B,'Download of SFDC Activation Rep'!L:L),"")} | H61: =IF(or(F61="Active",G61="Active"),"Active","Not Active") -> Active | I61: {=XLOOKUP(A61,'Download of SFDC Activation Rep'!B:B,'Download of SFDC Activation Rep'!T:T)} -> 006UU00000MQpnN | J61: {=iferror(XLOOKUP(A61,'Download of SFDC Activation Rep'!B:B,'Download of SFDC Activation Rep'!C:C),"")} -> CLS Brands LLC | K61: {=XLOOKUP(A61,'Download of SFDC Activation Rep'!B:B,'Download of SFDC Activation Rep'!X:X)} -> Kate Olivares | L61: {=xlookup(A61,'Download of SFDC Activation Rep'!B:B,'Download of SFDC Activation Rep'!Z:Z)} -> 45809
F62: {=iferror(XLOOKUP(A62,'Download of SFDC Activation Rep'!B:B,'Download of SFDC Activation Rep'!H:H),"")} -> Active | G62: {=iferror(xlookup(A62,'Download of SFDC Activation Rep'!B:B,'Download of SFDC Activation Rep'!L:L),"")} | H62: =IF(or(F62="Active",G62="Active"),"Active","Not Active") -> Active | I62: {=XLOOKUP(A62,'Download of SFDC Activation Rep'!B:B,'Download of SFDC Activation Rep'!T:T)} -> 006UU00000LlvrZ | J62: {=iferror(XLOOKUP(A62,'Download of SFDC Activation Rep'!B:B,'Download of SFDC Activation Rep'!C:C),"")} -> Texas Winds Musical Outreach | K62: {=XLOOKUP(A62,'Download of SFDC Activation Rep'!B:B,'Download of SFDC Activation Rep'!X:X)} -> Matthew Frost | L62: {=xlookup(A62,'Download of SFDC Activation Rep'!B:B,'Download of SFDC Activation Rep'!Z:Z)} -> 45947
F63: {=iferror(XLOOKUP(A63,'Download of SFDC Activation Rep'!B:B,'Download of SFDC Activation Rep'!H:H),"")} -> Active | G63: {=iferror(xlookup(A63,'Download of SFDC Activation Rep'!B:B,'Download of SFDC Activation Rep'!L:L),"")} | H63: =IF(or(F63="Active",G63="Active"),"Active","Not Active") -> Active | I63: {=XLOOKUP(A63,'Download of SFDC Activation Rep'!B:B,'Download of SFDC Activation Rep'!T:T)} -> 006UU00000MNO9q | J63: {=iferror(XLOOKUP(A63,'Download of SFDC Activation Rep'!B:B,'Download of SFDC Activation Rep'!C:C),"")} -> Johnston LLC | K63: {=XLOOKUP(A63,'Download of SFDC Activation Rep'!B:B,'Download of SFDC Activation Rep'!X:X)} -> Matthew Frost | L63: {=xlookup(A63,'Download of SFDC Activation Rep'!B:B,'Download of SFDC Activation Rep'!Z:Z)} -> 45964
F64: {=iferror(XLOOKUP(A64,'Download of SFDC Activation Rep'!B:B,'Download of SFDC Activation Rep'!H:H),"")} -> Active | G64: {=iferror(xlookup(A64,'Download of SFDC Activation Rep'!B:B,'Download of SFDC Activation Rep'!L:L),"")} | H64: =IF(or(F64="Active",G64="Active"),"Active","Not Active") -> Active | I64: {=XLOOKUP(A64,'Download of SFDC Activation Rep'!B:B,'Download of SFDC Activation Rep'!T:T)} -> 006UU00000L4wu9 | J64: {=iferror(XLOOKUP(A64,'Download of SFDC Activation Rep'!B:B,'Download of SFDC Activation Rep'!C:C),"")} -> Places to Age | K64: {=XLOOKUP(A64,'Download of SFDC Activation Rep'!B:B,'Download of SFDC Activation Rep'!X:X)} -> Matthew Frost | L64: {=xlookup(A64,'Download of SFDC Activation Rep'!B:B,'Download of SFDC Activation Rep'!Z:Z)} -> 45930
F65: {=iferror(XLOOKUP(A65,'Download of SFDC Activation Rep'!B:B,'Download of SFDC Activation Rep'!H:H),"")} -> Active | G65: {=iferror(xlookup(A65,'Download of SFDC Activation Rep'!B:B,'Download of SFDC Activation Rep'!L:L),"")} | H65: =IF(or(F65="Active",G65="Active"),"Active","Not Active") -> Active | I65: {=XLOOKUP(A65,'Download of SFDC Activation Rep'!B:B,'Download of SFDC Activation Rep'!T:T)} -> 006UU00000MQpnH | J65: {=iferror(XLOOKUP(A65,'Download of SFDC Activation Rep'!B:B,'Download of SFDC Activation Rep'!C:C),"")} -> Coastal Speech Pathology, LLC. | K65: {=XLOOKUP(A65,'Download of SFDC Activation Rep'!B:B,'Download of SFDC Activation Rep'!X:X)} -> Kate Olivares | L65: {=xlookup(A65,'Download of SFDC Activation Rep'!B:B,'Download of SFDC Activation Rep'!Z:Z)} -> 45870
F66: {=iferror(XLOOKUP(A66,'Download of SFDC Activation Rep'!B:B,'Download of SFDC Activation Rep'!H:H),"")} | G66: {=iferror(xlookup(A66,'Download of SFDC Activation Rep'!B:B,'Download of SFDC Activation Rep'!L:L),"")} -> Active | H66: =IF(or(F66="Active",G66="Active"),"Active","Not Active") -> Active | I66: {=XLOOKUP(A66,'Download of SFDC Activation Rep'!B:B,'Download of SFDC Activation Rep'!T:T)} -> 006UU00000KfrEY | J66: {=iferror(XLOOKUP(A66,'Download of SFDC Activation Rep'!B:B,'Download of SFDC Activation Rep'!C:C),"")} -> Paydirt Earthworks Support Services LLC | K66: {=XLOOKUP(A66,'Download of SFDC Activation Rep'!B:B,'Download of SFDC Activation Rep'!X:X)} -> Matthew Frost | L66: {=xlookup(A66,'Download of SFDC Activation Rep'!B:B,'Download of SFDC Activation Rep'!Z:Z)} -> 45918
... F82: {=iferror(XLOOKUP(A82,'Download of SFDC Activation Rep'!B:B,'Download of SFDC Activation Rep'!H:H),"")} -> Active | G82: {=iferror(xlookup(A82,'Download of SFDC Activation Rep'!B:B,'Download of SFDC Activation Rep'!L:L),"")} | H82: =IF(or(F82="Active",G82="Active"),"Active","Not Active") -> Active | I82: {=XLOOKUP(A82,'Download of SFDC Activation Rep'!B:B,'Download of SFDC Activation Rep'!T:T)} -> 006UU00000NnJkI | J82: {=iferror(XLOOKUP(A82,'Download of SFDC Activation Rep'!B:B,'Download of SFDC Activation Rep'!C:C),"")} -> Bottle Barn | K82: {=XLOOKUP(A82,'Download of SFDC Activation Rep'!B:B,'Download of SFDC Activation Rep'!X:X)} -> Matthew Frost | L82: {=xlookup(A82,'Download of SFDC Activation Rep'!B:B,'Download of SFDC Activation Rep'!Z:Z)} -> 46001
F83: {=iferror(XLOOKUP(A83,'Download of SFDC Activation Rep'!B:B,'Download of SFDC Activation Rep'!H:H),"")} -> Active | G83: {=iferror(xlookup(A83,'Download of SFDC Activation Rep'!B:B,'Download of SFDC Activation Rep'!L:L),"")} -> Churned | H83: =IF(or(F83="Active",G83="Active"),"Active","Not Active") -> Active | I83: {=XLOOKUP(A83,'Download of SFDC Activation Rep'!B:B,'Download of SFDC Activation Rep'!T:T)} -> 006UU00000Lzm6t | J83: {=iferror(XLOOKUP(A83,'Download of SFDC Activation Rep'!B:B,'Download of SFDC Activation Rep'!C:C),"")} -> South Earth Property Management
F84: {=iferror(XLOOKUP(A84,'Download of SFDC Activation Rep'!B:B,'Download of SFDC Activation Rep'!H:H),"")} | G84: {=iferror(xlookup(A84,'Download of SFDC Activation Rep'!B:B,'Download of SFDC Activation Rep'!L:L),"")} -> Active | H84: =IF(or(F84="Active",G84="Active"),"Active","Not Active") -> Active | I84: {=XLOOKUP(A84,'Download of SFDC Activation Rep'!B:B,'Download of SFDC Activation Rep'!T:T)} -> 006UU00000OHzkP | J84: {=iferror(XLOOKUP(A84,'Download of SFDC Activation Rep'!B:B,'Download of SFDC Activation Rep'!C:C),"")} -> Smart Launch LLC | K84: {=XLOOKUP(A84,'Download of SFDC Activation Rep'!B:B,'Download of SFDC Activation Rep'!X:X)} -> Kate Olivares | L84: {=xlookup(A84,'Download of SFDC Activation Rep'!B:B,'Download of SFDC Activation Rep'!Z:Z)} -> 46014
F85: {=iferror(XLOOKUP(A85,'Download of SFDC Activation Rep'!B:B,'Download of SFDC Activation Rep'!H:H),"")} -> Active | G85: {=iferror(xlookup(A85,'Download of SFDC Activation Rep'!B:B,'Download of SFDC Activation Rep'!L:L),"")} | H85: =IF(or(F85="Active",G85="Active"),"Active","Not Active") -> Active | I85: {=XLOOKUP(A85,'Download of SFDC Activation Rep'!B:B,'Download of SFDC Activation Rep'!T:T)} -> 006UU00000MxXJR | J85: {=iferror(XLOOKUP(A85,'Download of SFDC Activation Rep'!B:B,'Download of SFDC Activation Rep'!C:C),"")} -> gh Package Product Testing and Consulting, Inc. | K85: {=XLOOKUP(A85,'Download of SFDC Activation Rep'!B:B,'Download of SFDC Activation Rep'!X:X)} -> Matthew Frost | L85: {=xlookup(A85,'Download of SFDC Activation Rep'!B:B,'Download of SFDC Activation Rep'!Z:Z)} -> 45978
F86: {=iferror(XLOOKUP(A86,'Download of SFDC Activation Rep'!B:B,'Download of SFDC Activation Rep'!H:H),"")} | G86: {=iferror(xlookup(A86,'Download of SFDC Activation Rep'!B:B,'Download of SFDC Activation Rep'!L:L),"")} -> Active | H86: =IF(or(F86="Active",G86="Active"),"Active","Not Active") -> Active | I86: {=XLOOKUP(A86,'Download of SFDC Activation Rep'!B:B,'Download of SFDC Activation Rep'!T:T)} -> 006UU00000NKUMT | J86: {=iferror(XLOOKUP(A86,'Download of SFDC Activation Rep'!B:B,'Download of SFDC Activation Rep'!C:C),"")} -> 365 Archery LLC | K86: {=XLOOKUP(A86,'Download of SFDC Activation Rep'!B:B,'Download of SFDC Activation Rep'!X:X)} -> Kate Olivares | L86: {=xlookup(A86,'Download of SFDC Activation Rep'!B:B,'Download of SFDC Activation Rep'!Z:Z)} -> 45987
F87: {=iferror(XLOOKUP(A87,'Download of SFDC Activation Rep'!B:B,'Download of SFDC Activation Rep'!H:H),"")} -> Active | G87: {=iferror(xlookup(A87,'Download of SFDC Activation Rep'!B:B,'Download of SFDC Activation Rep'!L:L),"")} -> Active | H87: =IF(or(F87="Active",G87="Active"),"Active","Not Active") -> Active | I87: {=XLOOKUP(A87,'Download of SFDC Activation Rep'!B:B,'Download of SFDC Activation Rep'!T:T)} -> 006UU00000NKOvN | J87: {=iferror(XLOOKUP(A87,'Download of SFDC Activation Rep'!B:B,'Download of SFDC Activation Rep'!C:C),"")} -> Performance Supply LLC | K87: {=XLOOKUP(A87,'Download of SFDC Activation Rep'!B:B,'Download of SFDC Activation Rep'!X:X)} -> Kate Olivares | L87: {=xlookup(A87,'Download of SFDC Activation Rep'!B:B,'Download of SFDC Activation Rep'!Z:Z)} -> 45987
F88: {=iferror(XLOOKUP(A88,'Download of SFDC Activation Rep'!B:B,'Download of SFDC Activation Rep'!H:H),"")} | G88: {=iferror(xlookup(A88,'Download of SFDC Activation Rep'!B:B,'Download of SFDC Activation Rep'!L:L),"")} -> Active | H88: =IF(or(F88="Active",G88="Active"),"Active","Not Active") -> Active | I88: {=XLOOKUP(A88,'Download of SFDC Activation Rep'!B:B,'Download of SFDC Activation Rep'!T:T)} -> 006VT00000moks5 | J88: {=iferror(XLOOKUP(A88,'Download of SFDC Activation Rep'!B:B,'Download of SFDC Activation Rep'!C:C),"")} -> Cross Engineering LLC | K88: {=XLOOKUP(A88,'Download of SFDC Activation Rep'!B:B,'Download of SFDC Activation Rep'!X:X)} -> Matthew Frost | L88: {=xlookup(A88,'Download of SFDC Activation Rep'!B:B,'Download of SFDC Activation Rep'!Z:Z)} -> 46073
F89: {=iferror(XLOOKUP(A89,'Download of SFDC Activation Rep'!B:B,'Download of SFDC Activation Rep'!H:H),"")} | G89: {=iferror(xlookup(A89,'Download of SFDC Activation Rep'!B:B,'Download of SFDC Activation Rep'!L:L),"")} -> Active | H89: =IF(or(F89="Active",G89="Active"),"Active","Not Active") -> Active | I89: {=XLOOKUP(A89,'Download of SFDC Activation Rep'!B:B,'Download of SFDC Activation Rep'!T:T)} -> 006UU00000MQpnQ | J89: {=iferror(XLOOKUP(A89,'Download of SFDC Activation Rep'!B:B,'Download of SFDC Activation Rep'!C:C),"")} -> Commercial Fire & Security | K89: {=XLOOKUP(A89,'Download of SFDC Activation Rep'!B:B,'Download of SFDC Activation Rep'!X:X)} -> Kate Olivares | L89: {=xlookup(A89,'Download of SFDC Activation Rep'!B:B,'Download of SFDC Activation Rep'!Z:Z)} -> 45839
F90: {=iferror(XLOOKUP(A90,'Download of SFDC Activation Rep'!B:B,'Download of SFDC Activation Rep'!H:H),"")} -> Active | G90: {=iferror(xlookup(A90,'Download of SFDC Activation Rep'!B:B,'Download of SFDC Activation Rep'!L:L),"")} | H90: =IF(or(F90="Active",G90="Active"),"Active","Not Active") -> Active | I90: {=XLOOKUP(A90,'Download of SFDC Activation Rep'!B:B,'Download of SFDC Activation Rep'!T:T)} -> 006UU00000MQpn9 | J90: {=iferror(XLOOKUP(A90,'Download of SFDC Activation Rep'!B:B,'Download of SFDC Activation Rep'!C:C),"")} -> Star Blue Interpreting Service, LLC | K90: {=XLOOKUP(A90,'Download of SFDC Activation Rep'!B:B,'Download of SFDC Activation Rep'!X:X)} -> Kate Olivares | L90: {=xlookup(A90,'Download of SFDC Activation Rep'!B:B,'Download of SFDC Activation Rep'!Z:Z)} -> 45863
F91: {=iferror(XLOOKUP(A91,'Download of SFDC Activation Rep'!B:B,'Download of SFDC Activation Rep'!H:H),"")} | G91: {=iferror(xlookup(A91,'Download of SFDC Activation Rep'!B:B,'Download of SFDC Activation Rep'!L:L),"")} -> Active | H91: =IF(or(F91="Active",G91="Active"),"Active","Not Active") -> Active | I91: {=XLOOKUP(A91,'Download of SFDC Activation Rep'!B:B,'Download of SFDC Activation Rep'!T:T)} -> 006VT00000oHAFu | J91: {=iferror(XLOOKUP(A91,'Download of SFDC Activation Rep'!B:B,'Download of SFDC Activation Rep'!C:C),"")} -> NOFD Firewatch Detail | K91: {=XLOOKUP(A91,'Download of SFDC Activation Rep'!B:B,'Download of SFDC Activation Rep'!X:X)} -> Arianna Modesti | L91: {=xlookup(A91,'Download of SFDC Activation Rep'!B:B,'Download of SFDC Activation Rep'!Z:Z)} -> 46104
F92: {=iferror(XLOOKUP(A92,'Download of SFDC Activation Rep'!B:B,'Download of SFDC Activation Rep'!H:H),"")} -> Active | G92: {=iferror(xlookup(A92,'Download of SFDC Activation Rep'!B:B,'Download of SFDC Activation Rep'!L:L),"")} | H92: =IF(or(F92="Active",G92="Active"),"Active","Not Active") -> Active | I92: {=XLOOKUP(A92,'Download of SFDC Activation Rep'!B:B,'Download of SFDC Activation Rep'!T:T)} -> 006UU00000N120w | J92: {=iferror(XLOOKUP(A92,'Download of SFDC Activation Rep'!B:B,'Download of SFDC Activation Rep'!C:C),"")} -> Amlife Global LLC
F93: {=iferror(XLOOKUP(A93,'Download of SFDC Activation Rep'!B:B,'Download of SFDC Activation Rep'!H:H),"")} -> Active | G93: {=iferror(xlookup(A93,'Download of SFDC Activation Rep'!B:B,'Download of SFDC Activation Rep'!L:L),"")} | H93: =IF(or(F93="Active",G93="Active"),"Active","Not Active") -> Active | I93: {=XLOOKUP(A93,'Download of SFDC Activation Rep'!B:B,'Download of SFDC Activation Rep'!T:T)} -> 006UU00000N14tx | J93: {=iferror(XLOOKUP(A93,'Download of SFDC Activation Rep'!B:B,'Download of SFDC Activation Rep'!C:C),"")} -> Hemm Ventures LLC | K93: {=XLOOKUP(A93,'Download of SFDC Activation Rep'!B:B,'Download of SFDC Activation Rep'!X:X)} -> Kate Olivares | L93: {=xlookup(A93,'Download of SFDC Activation Rep'!B:B,'Download of SFDC Activation Rep'!Z:Z)} -> 45979
F94: {=iferror(XLOOKUP(A94,'Download of SFDC Activation Rep'!B:B,'Download of SFDC Activation Rep'!H:H),"")} -> Active | G94: {=iferror(xlookup(A94,'Download of SFDC Activation Rep'!B:B,'Download of SFDC Activation Rep'!L:L),"")} | H94: =IF(or(F94="Active",G94="Active"),"Active","Not Active") -> Active | I94: {=XLOOKUP(A94,'Download of SFDC Activation Rep'!B:B,'Download of SFDC Activation Rep'!T:T)} -> 006UU00000N14E1 | J94: {=iferror(XLOOKUP(A94,'Download of SFDC Activation Rep'!B:B,'Download of SFDC Activation Rep'!C:C),"")} -> Trustwell Brands LLC | K94: {=XLOOKUP(A94,'Download of SFDC Activation Rep'!B:B,'Download of SFDC Activation Rep'!X:X)} -> Kate Olivares | L94: {=xlookup(A94,'Download of SFDC Activation Rep'!B:B,'Download of SFDC Activation Rep'!Z:Z)} -> 45979
F95: {=iferror(XLOOKUP(A95,'Download of SFDC Activation Rep'!B:B,'Download of SFDC Activation Rep'!H:H),"")} -> Active | G95: {=iferror(xlookup(A95,'Download of SFDC Activation Rep'!B:B,'Download of SFDC Activation Rep'!L:L),"")} | H95: =IF(or(F95="Active",G95="Active"),"Active","Not Active") -> Active | I95: {=XLOOKUP(A95,'Download of SFDC Activation Rep'!B:B,'Download of SFDC Activation Rep'!T:T)} -> 006UU00000NTWs6 | J95: {=iferror(XLOOKUP(A95,'Download of SFDC Activation Rep'!B:B,'Download of SFDC Activation Rep'!C:C),"")} -> Meraki Ventures LLC | K95: {=XLOOKUP(A95,'Download of SFDC Activation Rep'!B:B,'Download of SFDC Activation Rep'!X:X)} -> Kate Olivares | L95: {=xlookup(A95,'Download of SFDC Activation Rep'!B:B,'Download of SFDC Activation Rep'!Z:Z)} -> 45992
F96: {=iferror(XLOOKUP(A96,'Download of SFDC Activation Rep'!B:B,'Download of SFDC Activation Rep'!H:H),"")} -> Active | G96: {=iferror(xlookup(A96,'Download of SFDC Activation Rep'!B:B,'Download of SFDC Activation Rep'!L:L),"")} | H96: =IF(or(F96="Active",G96="Active"),"Active","Not Active") -> Active | I96: {=XLOOKUP(A96,'Download of SFDC Activation Rep'!B:B,'Download of SFDC Activation Rep'!T:T)} -> 006UU00000NTdIT | J96: {=iferror(XLOOKUP(A96,'Download of SFDC Activation Rep'!B:B,'Download of SFDC Activation Rep'!C:C),"")} -> Bespoke Creations LLC | K96: {=XLOOKUP(A96,'Download of SFDC Activation Rep'!B:B,'Download of SFDC Activation Rep'!X:X)} -> Kate Olivares | L96: {=xlookup(A96,'Download of SFDC Activation Rep'!B:B,'Download of SFDC Activation Rep'!Z:Z)} -> 45992
F97: {=iferror(XLOOKUP(A97,'Download of SFDC Activation Rep'!B:B,'Download of SFDC Activation Rep'!H:H),"")} -> Active | G97: {=iferror(xlookup(A97,'Download of SFDC Activation Rep'!B:B,'Download of SFDC Activation Rep'!L:L),"")} | H97: =IF(or(F97="Active",G97="Active"),"Active","Not Active") -> Active | I97: {=XLOOKUP(A97,'Download of SFDC Activation Rep'!B:B,'Download of SFDC Activation Rep'!T:T)} -> 006UU00000L2cpv | J97: {=iferror(XLOOKUP(A97,'Download of SFDC Activation Rep'!B:B,'Download of SFDC Activation Rep'!C:C),"")} -> Austin Elementary PTO | K97: {=XLOOKUP(A97,'Download of SFDC Activation Rep'!B:B,'Download of SFDC Activation Rep'!X:X)} -> Matthew Frost | L97: {=xlookup(A97,'Download of SFDC Activation Rep'!B:B,'Download of SFDC Activation Rep'!Z:Z)} -> 45929
F98: {=iferror(XLOOKUP(A98,'Download of SFDC Activation Rep'!B:B,'Download of SFDC Activation Rep'!H:H),"")} | G98: {=iferror(xlookup(A98,'Download of SFDC Activation Rep'!B:B,'Download of SFDC Activation Rep'!L:L),"")} -> Active | H98: =IF(or(F98="Active",G98="Active"),"Active","Not Active") -> Active | I98: {=XLOOKUP(A98,'Download of SFDC Activation Rep'!B:B,'Download of SFDC Activation Rep'!T:T)} -> 006UU00000LzkrK | J98: {=iferror(XLOOKUP(A98,'Download of SFDC Activation Rep'!B:B,'Download of SFDC Activation Rep'!C:C),"")} -> Mighty of Arizona | K98: {=XLOOKUP(A98,'Download of SFDC Activation Rep'!B:B,'Download of SFDC Activation Rep'!X:X)} -> Matthew Frost | L98: {=xlookup(A98,'Download of SFDC Activation Rep'!B:B,'Download of SFDC Activation Rep'!Z:Z)} -> 45895
F99: {=iferror(XLOOKUP(A99,'Download of SFDC Activation Rep'!B:B,'Download of SFDC Activation Rep'!H:H),"")} -> Active | G99: {=iferror(xlookup(A99,'Download of SFDC Activation Rep'!B:B,'Download of SFDC Activation Rep'!L:L),"")} | H99: =IF(or(F99="Active",G99="Active"),"Active","Not Active") -> Active | I99: {=XLOOKUP(A99,'Download of SFDC Activation Rep'!B:B,'Download of SFDC Activation Rep'!T:T)} -> 006UU00000LTAki | J99: {=iferror(XLOOKUP(A99,'Download of SFDC Activation Rep'!B:B,'Download of SFDC Activation Rep'!C:C),"")} -> TecTeam LLC | K99: {=XLOOKUP(A99,'Download of SFDC Activation Rep'!B:B,'Download of SFDC Activation Rep'!X:X)} -> Mass Niang | L99: {=xlookup(A99,'Download of SFDC Activation Rep'!B:B,'Download of SFDC Activation Rep'!Z:Z)} -> 45940
F100: {=iferror(XLOOKUP(A100,'Download of SFDC Activation Rep'!B:B,'Download of SFDC Activation Rep'!H:H),"")} -> Active | G100: {=iferror(xlookup(A100,'Download of SFDC Activation Rep'!B:B,'Download of SFDC Activation Rep'!L:L),"")} | H100: =IF(or(F100="Active",G100="Active"),"Active","Not Active") -> Active | I100: {=XLOOKUP(A100,'Download of SFDC Activation Rep'!B:B,'Download of SFDC Activation Rep'!T:T)} -> 006VT00000niEUT | J100: {=iferror(XLOOKUP(A100,'Download of SFDC Activation Rep'!B:B,'Download of SFDC Activation Rep'!C:C),"")} -> K2 Parts Inc | K100: {=XLOOKUP(A100,'Download of SFDC Activation Rep'!B:B,'Download of SFDC Activation Rep'!X:X)} -> Arianna Modesti | L100: {=xlookup(A100,'Download of SFDC Activation Rep'!B:B,'Download of SFDC Activation Rep'!Z:Z)} -> 46092
F101: {=iferror(XLOOKUP(A101,'Download of SFDC Activation Rep'!B:B,'Download of SFDC Activation Rep'!H:H),"")} | G101: {=iferror(xlookup(A101,'Download of SFDC Activation Rep'!B:B,'Download of SFDC Activation Rep'!L:L),"")} -> Active | H101: =IF(or(F101="Active",G101="Active"),"Active","Not Active") -> Active | I101: {=XLOOKUP(A101,'Download of SFDC Activation Rep'!B:B,'Download of SFDC Activation Rep'!T:T)} -> 006UU00000Mq5Oj | J101: {=iferror(XLOOKUP(A101,'Download of SFDC Activation Rep'!B:B,'Download of SFDC Activation Rep'!C:C),"")} -> Jenny and Francois Selections | K101: {=XLOOKUP(A101,'Download of SFDC Activation Rep'!B:B,'Download of SFDC Activation Rep'!X:X)} -> Kate Olivares | L101: {=xlookup(A101,'Download of SFDC Activation Rep'!B:B,'Download of SFDC Activation Rep'!Z:Z)} -> 45974
F102: {=iferror(XLOOKUP(A102,'Download of SFDC Activation Rep'!B:B,'Download of SFDC Activation Rep'!H:H),"")} -> Active | G102: {=iferror(xlookup(A102,'Download of SFDC Activation Rep'!B:B,'Download of SFDC Activation Rep'!L:L),"")} | H102: =IF(or(F102="Active",G102="Active"),"Active","Not Active") -> Active | I102: {=XLOOKUP(A102,'Download of SFDC Activation Rep'!B:B,'Download of SFDC Activation Rep'!T:T)} -> 006UU00000N12ov | J102: {=iferror(XLOOKUP(A102,'Download of SFDC Activation Rep'!B:B,'Download of SFDC Activation Rep'!C:C),"")} -> Vitamin Science LLC | K102: {=XLOOKUP(A102,'Download of SFDC Activation Rep'!B:B,'Download of SFDC Activation Rep'!X:X)} -> Kate Olivares | L102: {=xlookup(A102,'Download of SFDC Activation Rep'!B:B,'Download of SFDC Activation Rep'!Z:Z)} -> 45979
F103: {=iferror(XLOOKUP(A103,'Download of SFDC Activation Rep'!B:B,'Download of SFDC Activation Rep'!H:H),"")} -> Active | G103: {=iferror(xlookup(A103,'Download of SFDC Activation Rep'!B:B,'Download of SFDC Activation Rep'!L:L),"")} | H103: =IF(or(F103="Active",G103="Active"),"Active","Not Active") -> Active | I103: {=XLOOKUP(A103,'Download of SFDC Activation Rep'!B:B,'Download of SFDC Activation Rep'!T:T)} -> 006UU00000LzrZm | J103: {=iferror(XLOOKUP(A103,'Download of SFDC Activation Rep'!B:B,'Download of SFDC Activation Rep'!C:C),"")} -> Habitat for Humanity-Anchorage | K103: {=XLOOKUP(A103,'Download of SFDC Activation Rep'!B:B,'Download of SFDC Activation Rep'!X:X)} -> Matthew Frost | L103: {=xlookup(A103,'Download of SFDC Activation Rep'!B:B,'Download of SFDC Activation Rep'!Z:Z)} -> 45897
F104: {=iferror(XLOOKUP(A104,'Download of SFDC Activation Rep'!B:B,'Download of SFDC Activation Rep'!H:H),"")} | G104: {=iferror(xlookup(A104,'Download of SFDC Activation Rep'!B:B,'Download of SFDC Activation Rep'!L:L),"")} -> Active | H104: =IF(or(F104="Active",G104="Active"),"Active","Not Active") -> Active | I104: {=XLOOKUP(A104,'Download of SFDC Activation Rep'!B:B,'Download of SFDC Activation Rep'!T:T)} -> 006VT00000o0NO1 | J104: {=iferror(XLOOKUP(A104,'Download of SFDC Activation Rep'!B:B,'Download of SFDC Activation Rep'!C:C),"")} -> Guber Sports Llc | K104: {=XLOOKUP(A104,'Download of SFDC Activation Rep'!B:B,'Download of SFDC Activation Rep'!X:X)} -> Matthew Frost | L104: {=xlookup(A104,'Download of SFDC Activation Rep'!B:B,'Download of SFDC Activation Rep'!Z:Z)} -> 46099
... F109: {=iferror(XLOOKUP(A109,'Download of SFDC Activation Rep'!B:B,'Download of SFDC Activation Rep'!H:H),"")} -> Active | G109: {=iferror(xlookup(A109,'Download of SFDC Activation Rep'!B:B,'Download of SFDC Activation Rep'!L:L),"")} | H109: =IF(or(F109="Active",G109="Active"),"Active","Not Active") -> Active | I109: {=XLOOKUP(A109,'Download of SFDC Activation Rep'!B:B,'Download of SFDC Activation Rep'!T:T)} -> 006VT00000owujN | J109: {=iferror(XLOOKUP(A109,'Download of SFDC Activation Rep'!B:B,'Download of SFDC Activation Rep'!C:C),"")} -> GATEWAY LIGHTING AND DESIGN INC | K109: {=XLOOKUP(A109,'Download of SFDC Activation Rep'!B:B,'Download of SFDC Activation Rep'!X:X)} -> Arianna Modesti | L109: {=xlookup(A109,'Download of SFDC Activation Rep'!B:B,'Download of SFDC Activation Rep'!Z:Z)} -> 46119
F110: {=iferror(XLOOKUP(A110,'Download of SFDC Activation Rep'!B:B,'Download of SFDC Activation Rep'!H:H),"")} | G110: {=iferror(xlookup(A110,'Download of SFDC Activation Rep'!B:B,'Download of SFDC Activation Rep'!L:L),"")} -> Active | H110: =IF(or(F110="Active",G110="Active"),"Active","Not Active") -> Active | I110: {=XLOOKUP(A110,'Download of SFDC Activation Rep'!B:B,'Download of SFDC Activation Rep'!T:T)} -> 006UU00000O1Il6 | J110: {=iferror(XLOOKUP(A110,'Download of SFDC Activation Rep'!B:B,'Download of SFDC Activation Rep'!C:C),"")} -> Jenny and Francois Selections
F111: {=iferror(XLOOKUP(A111,'Download of SFDC Activation Rep'!B:B,'Download of SFDC Activation Rep'!H:H),"")} -> Active | G111: {=iferror(xlookup(A111,'Download of SFDC Activation Rep'!B:B,'Download of SFDC Activation Rep'!L:L),"")} | H111: =IF(or(F111="Active",G111="Active"),"Active","Not Active") -> Active | I111: {=XLOOKUP(A111,'Download of SFDC Activation Rep'!B:B,'Download of SFDC Activation Rep'!T:T)} -> 006VT00000puqcr | J111: {=iferror(XLOOKUP(A111,'Download of SFDC Activation Rep'!B:B,'Download of SFDC Activation Rep'!C:C),"")} -> Victory Bicycle Studio | K111: {=XLOOKUP(A111,'Download of SFDC Activation Rep'!B:B,'Download of SFDC Activation Rep'!X:X)} -> Arianna Modesti | L111: {=xlookup(A111,'Download of SFDC Activation Rep'!B:B,'Download of SFDC Activation Rep'!Z:Z)} -> 46139
F112: {=iferror(XLOOKUP(A112,'Download of SFDC Activation Rep'!B:B,'Download of SFDC Activation Rep'!H:H),"")} -> Active | G112: {=iferror(xlookup(A112,'Download of SFDC Activation Rep'!B:B,'Download of SFDC Activation Rep'!L:L),"")} -> Churned | H112: =IF(or(F112="Active",G112="Active"),"Active","Not Active") -> Active | I112: {=XLOOKUP(A112,'Download of SFDC Activation Rep'!B:B,'Download of SFDC Activation Rep'!T:T)} -> 006UU00000LzkrF | J112: {=iferror(XLOOKUP(A112,'Download of SFDC Activation Rep'!B:B,'Download of SFDC Activation Rep'!C:C),"")} -> Millbrook Distillery LLC dba Tenmile Distillery | K112: {=XLOOKUP(A112,'Download of SFDC Activation Rep'!B:B,'Download of SFDC Activation Rep'!X:X)} -> Mass Niang | L112: {=xlookup(A112,'Download of SFDC Activation Rep'!B:B,'Download of SFDC Activation Rep'!Z:Z)} -> 45890
F113: {=iferror(XLOOKUP(A113,'Download of SFDC Activation Rep'!B:B,'Download of SFDC Activation Rep'!H:H),"")} -> Active | G113: {=iferror(xlookup(A113,'Download of SFDC Activation Rep'!B:B,'Download of SFDC Activation Rep'!L:L),"")} | H113: =IF(or(F113="Active",G113="Active"),"Active","Not Active") -> Active | I113: {=XLOOKUP(A113,'Download of SFDC Activation Rep'!B:B,'Download of SFDC Activation Rep'!T:T)} -> 006VT00000rcekJ | J113: {=iferror(XLOOKUP(A113,'Download of SFDC Activation Rep'!B:B,'Download of SFDC Activation Rep'!C:C),"")} -> Bella Notte Linens | K113: {=XLOOKUP(A113,'Download of SFDC Activation Rep'!B:B,'Download of SFDC Activation Rep'!X:X)} -> Arianna Modesti | L113: {=xlookup(A113,'Download of SFDC Activation Rep'!B:B,'Download of SFDC Activation Rep'!Z:Z)} -> 46175
F114: {=iferror(XLOOKUP(A114,'Download of SFDC Activation Rep'!B:B,'Download of SFDC Activation Rep'!H:H),"")} -> Active | G114: {=iferror(xlookup(A114,'Download of SFDC Activation Rep'!B:B,'Download of SFDC Activation Rep'!L:L),"")} | H114: =IF(or(F114="Active",G114="Active"),"Active","Not Active") -> Active | I114: {=XLOOKUP(A114,'Download of SFDC Activation Rep'!B:B,'Download of SFDC Activation Rep'!T:T)} -> 006UU00000LKXgU | J114: {=iferror(XLOOKUP(A114,'Download of SFDC Activation Rep'!B:B,'Download of SFDC Activation Rep'!C:C),"")} -> MJM Construction | K114: {=XLOOKUP(A114,'Download of SFDC Activation Rep'!B:B,'Download of SFDC Activation Rep'!X:X)} -> Mass Niang | L114: {=xlookup(A114,'Download of SFDC Activation Rep'!B:B,'Download of SFDC Activation Rep'!Z:Z)} -> 45937
F115: {=iferror(XLOOKUP(A115,'Download of SFDC Activation Rep'!B:B,'Download of SFDC Activation Rep'!H:H),"")} -> Active | G115: {=iferror(xlookup(A115,'Download of SFDC Activation Rep'!B:B,'Download of SFDC Activation Rep'!L:L),"")} -> Churned | H115: =IF(or(F115="Active",G115="Active"),"Active","Not Active") -> Active | I115: {=XLOOKUP(A115,'Download of SFDC Activation Rep'!B:B,'Download of SFDC Activation Rep'!T:T)} -> 006UU00000OcYZ7 | J115: {=iferror(XLOOKUP(A115,'Download of SFDC Activation Rep'!B:B,'Download of SFDC Activation Rep'!C:C),"")} -> Big House Group LLC | K115: {=XLOOKUP(A115,'Download of SFDC Activation Rep'!B:B,'Download of SFDC Activation Rep'!X:X)} -> Matthew Frost | L115: {=xlookup(A115,'Download of SFDC Activation Rep'!B:B,'Download of SFDC Activation Rep'!Z:Z)} -> 46027
F116: {=iferror(XLOOKUP(A116,'Download of SFDC Activation Rep'!B:B,'Download of SFDC Activation Rep'!H:H),"")} -> Active | G116: {=iferror(xlookup(A116,'Download of SFDC Activation Rep'!B:B,'Download of SFDC Activation Rep'!L:L),"")} -> Active | H116: =IF(or(F116="Active",G116="Active"),"Active","Not Active") -> Active | I116: {=XLOOKUP(A116,'Download of SFDC Activation Rep'!B:B,'Download of SFDC Activation Rep'!T:T)} -> 006UU00000MQpn6 | J116: {=iferror(XLOOKUP(A116,'Download of SFDC Activation Rep'!B:B,'Download of SFDC Activation Rep'!C:C),"")} -> L&M Mail & Courier | K116: {=XLOOKUP(A116,'Download of SFDC Activation Rep'!B:B,'Download of SFDC Activation Rep'!X:X)} -> Kate Olivares | L116: {=xlookup(A116,'Download of SFDC Activation Rep'!B:B,'Download of SFDC Activation Rep'!Z:Z)} -> 45880
F117: {=iferror(XLOOKUP(A117,'Download of SFDC Activation Rep'!B:B,'Download of SFDC Activation Rep'!H:H),"")} | G117: {=iferror(xlookup(A117,'Download of SFDC Activation Rep'!B:B,'Download of SFDC Activation Rep'!L:L),"")} -> Active | H117: =IF(or(F117="Active",G117="Active"),"Active","Not Active") -> Active | I117: {=XLOOKUP(A117,'Download of SFDC Activation Rep'!B:B,'Download of SFDC Activation Rep'!T:T)} -> 006UU00000Lzkqz | J117: {=iferror(XLOOKUP(A117,'Download of SFDC Activation Rep'!B:B,'Download of SFDC Activation Rep'!C:C),"")} -> Advanced Medical Software Solutions, Inc. | K117: {=XLOOKUP(A117,'Download of SFDC Activation Rep'!B:B,'Download of SFDC Activation Rep'!X:X)} -> Matthew Frost | L117: {=xlookup(A117,'Download of SFDC Activation Rep'!B:B,'Download of SFDC Activation Rep'!Z:Z)} -> 45895
F118: {=iferror(XLOOKUP(A118,'Download of SFDC Activation Rep'!B:B,'Download of SFDC Activation Rep'!H:H),"")} -> Active | G118: {=iferror(xlookup(A118,'Download of SFDC Activation Rep'!B:B,'Download of SFDC Activation Rep'!L:L),"")} | H118: =IF(or(F118="Active",G118="Active"),"Active","Not Active") -> Active | I118: {=XLOOKUP(A118,'Download of SFDC Activation Rep'!B:B,'Download of SFDC Activation Rep'!T:T)} -> 006VT00000qRtP3 | J118: {=iferror(XLOOKUP(A118,'Download of SFDC Activation Rep'!B:B,'Download of SFDC Activation Rep'!C:C),"")} -> Nationwide Valuation Solutions, LLC | K118: {=XLOOKUP(A118,'Download of SFDC Activation Rep'!B:B,'Download of SFDC Activation Rep'!X:X)} -> Arianna Modesti | L118: {=xlookup(A118,'Download of SFDC Activation Rep'!B:B,'Download of SFDC Activation Rep'!Z:Z)} -> 46150
F119: {=iferror(XLOOKUP(A119,'Download of SFDC Activation Rep'!B:B,'Download of SFDC Activation Rep'!H:H),"")} | G119: {=iferror(xlookup(A119,'Download of SFDC Activation Rep'!B:B,'Download of SFDC Activation Rep'!L:L),"")} -> Active | H119: =IF(or(F119="Active",G119="Active"),"Active","Not Active") -> Active | I119: {=XLOOKUP(A119,'Download of SFDC Activation Rep'!B:B,'Download of SFDC Activation Rep'!T:T)} -> 006UU00000LzkrI | J119: {=iferror(XLOOKUP(A119,'Download of SFDC Activation Rep'!B:B,'Download of SFDC Activation Rep'!C:C),"")} -> Southside Mighty of Chicago | K119: {=XLOOKUP(A119,'Download of SFDC Activation Rep'!B:B,'Download of SFDC Activation Rep'!X:X)} -> Matthew Frost | L119: {=xlookup(A119,'Download of SFDC Activation Rep'!B:B,'Download of SFDC Activation Rep'!Z:Z)} -> 45895
F120: {=iferror(XLOOKUP(A120,'Download of SFDC Activation Rep'!B:B,'Download of SFDC Activation Rep'!H:H),"")} -> Churned | G120: {=iferror(xlookup(A120,'Download of SFDC Activation Rep'!B:B,'Download of SFDC Activation Rep'!L:L),"")} -> Active | H120: =IF(or(F120="Active",G120="Active"),"Active","Not Active") -> Active | I120: {=XLOOKUP(A120,'Download of SFDC Activation Rep'!B:B,'Download of SFDC Activation Rep'!T:T)} -> 006UU00000MmdC5 | J120: {=iferror(XLOOKUP(A120,'Download of SFDC Activation Rep'!B:B,'Download of SFDC Activation Rep'!C:C),"")} -> International Marine Products | K120: {=XLOOKUP(A120,'Download of SFDC Activation Rep'!B:B,'Download of SFDC Activation Rep'!X:X)} -> Matthew Frost | L120: {=xlookup(A120,'Download of SFDC Activation Rep'!B:B,'Download of SFDC Activation Rep'!Z:Z)} -> 45973
F121: {=iferror(XLOOKUP(A121,'Download of SFDC Activation Rep'!B:B,'Download of SFDC Activation Rep'!H:H),"")} | G121: {=iferror(xlookup(A121,'Download of SFDC Activation Rep'!B:B,'Download of SFDC Activation Rep'!L:L),"")} -> Active | H121: =IF(or(F121="Active",G121="Active"),"Active","Not Active") -> Active | I121: {=XLOOKUP(A121,'Download of SFDC Activation Rep'!B:B,'Download of SFDC Activation Rep'!T:T)} -> 006UU00000LzkrH | J121: {=iferror(XLOOKUP(A121,'Download of SFDC Activation Rep'!B:B,'Download of SFDC Activation Rep'!C:C),"")} -> PC Enterprises | K121: {=XLOOKUP(A121,'Download of SFDC Activation Rep'!B:B,'Download of SFDC Activation Rep'!X:X)} -> Matthew Frost | L121: {=xlookup(A121,'Download of SFDC Activation Rep'!B:B,'Download of SFDC Activation Rep'!Z:Z)} -> 45895
F122: {=iferror(XLOOKUP(A122,'Download of SFDC Activation Rep'!B:B,'Download of SFDC Activation Rep'!H:H),"")} -> Active | G122: {=iferror(xlookup(A122,'Download of SFDC Activation Rep'!B:B,'Download of SFDC Activation Rep'!L:L),"")} | H122: =IF(or(F122="Active",G122="Active"),"Active","Not Active") -> Active | I122: {=XLOOKUP(A122,'Download of SFDC Activation Rep'!B:B,'Download of SFDC Activation Rep'!T:T)} -> 006UU00000NVQyi | J122: {=iferror(XLOOKUP(A122,'Download of SFDC Activation Rep'!B:B,'Download of SFDC Activation Rep'!C:C),"")} -> The Makenzie House | K122: {=XLOOKUP(A122,'Download of SFDC Activation Rep'!B:B,'Download of SFDC Activation Rep'!X:X)} -> Matthew Frost | L122: {=xlookup(A122,'Download of SFDC Activation Rep'!B:B,'Download of SFDC Activation Rep'!Z:Z)} -> 45993
... F1000: {=iferror(XLOOKUP(A1000,'Download of SFDC Activation Rep'!B:B,'Download of SFDC Activation Rep'!H:H),"")} | G1000: {=iferror(xlookup(A1000,'Download of SFDC Activation Rep'!B:B,'Download of SFDC Activation Rep'!L:L),"")} | H1000: =IF(or(F1000="Active",G1000="Active"),"Active","Not Active") -> Not Active | I1000: {=XLOOKUP(A1000,'Download of SFDC Activation Rep'!B:B,'Download of SFDC Activation Rep'!T:T)} -> #N/A | J1000: {=iferror(XLOOKUP(A1000,'Download of SFDC Activation Rep'!B:B,'Download of SFDC Activation Rep'!C:C),"")} | K1000: {=XLOOKUP(A1000,'Download of SFDC Activation Rep'!B:B,'Download of SFDC Activation Rep'!X:X)} -> #N/A | L1000: {=xlookup(A1000,'Download of SFDC Activation Rep'!B:B,'Download of SFDC Activation Rep'!Z:Z)} -> #N/A

Sheet Lifetime Summary Stats
F1: Take Rate (TPV to GP) | G1: AP Status | H1: AR Status | I1: AP/AR Status | J1: Account Owner | K1: Account Name | L1: Total Orgs | M1: =COUNTIF(A2:A1000,">=0") -> 210 | O1: LAST DATA PULL: | P1: 46201
F2: =B2/D2 -> -9.1465479e-06 | G2: {=iferror(XLOOKUP(A2,'Download of SFDC Activation Rep'!B:B,'Download of SFDC Activation Rep'!H:H),"")} -> Active | H2: {=iferror(xlookup(A2,'Download of SFDC Activation Rep'!B:B,'Download of SFDC Activation Rep'!L:L),"")} | I2: =IF(or(G2="Active",H2="Active"),"Active","Not Active") -> Active | J2: {=XLOOKUP(A2,'Download of SFDC Activation Rep'!B:B,'Download of SFDC Activation Rep'!T:T)} -> 006VT00000rcekJ | K2: {=iferror(XLOOKUP(A2,'Download of SFDC Activation Rep'!B:B,'Download of SFDC Activation Rep'!C:C),"")} -> Bella Notte Linens | L2: Total Active Orgs | M2: =COUNTIF(I:I,"Active") -> 146
F3: =B3/D3 -> 0.0019045224 | G3: {=iferror(XLOOKUP(A3,'Download of SFDC Activation Rep'!B:B,'Download of SFDC Activation Rep'!H:H),"")} -> Active | H3: {=iferror(xlookup(A3,'Download of SFDC Activation Rep'!B:B,'Download of SFDC Activation Rep'!L:L),"")} | I3: =IF(or(G3="Active",H3="Active"),"Active","Not Active") -> Active | J3: {=XLOOKUP(A3,'Download of SFDC Activation Rep'!B:B,'Download of SFDC Activation Rep'!T:T)} -> 006VT00000rLcgU | K3: {=iferror(XLOOKUP(A3,'Download of SFDC Activation Rep'!B:B,'Download of SFDC Activation Rep'!C:C),"")} -> Talcan Systems, LLC
F4: =B4/D4 -> -0.006084 | G4: {=iferror(XLOOKUP(A4,'Download of SFDC Activation Rep'!B:B,'Download of SFDC Activation Rep'!H:H),"")} -> Active | H4: {=iferror(xlookup(A4,'Download of SFDC Activation Rep'!B:B,'Download of SFDC Activation Rep'!L:L),"")} | I4: =IF(or(G4="Active",H4="Active"),"Active","Not Active") -> Active | J4: {=XLOOKUP(A4,'Download of SFDC Activation Rep'!B:B,'Download of SFDC Activation Rep'!T:T)} -> 006VT00000qS44N | K4: {=iferror(XLOOKUP(A4,'Download of SFDC Activation Rep'!B:B,'Download of SFDC Activation Rep'!C:C),"")} -> Matte Collection | L4: Avg of Each Org Monthly TPV | M4: =AVERAGE(E:E) -> 99061.242
F5: =B5/D5 -> 0.0050201127 | G5: {=iferror(XLOOKUP(A5,'Download of SFDC Activation Rep'!B:B,'Download of SFDC Activation Rep'!H:H),"")} -> Active | H5: {=iferror(xlookup(A5,'Download of SFDC Activation Rep'!B:B,'Download of SFDC Activation Rep'!L:L),"")} | I5: =IF(or(G5="Active",H5="Active"),"Active","Not Active") -> Active | J5: {=XLOOKUP(A5,'Download of SFDC Activation Rep'!B:B,'Download of SFDC Activation Rep'!T:T)} -> 006VT00000qfNVl | K5: {=iferror(XLOOKUP(A5,'Download of SFDC Activation Rep'!B:B,'Download of SFDC Activation Rep'!C:C),"")} -> GK Truckline | L5: Avg of Each Org Monthly GP | M5: =AVERAGE(C:C) -> 162.57962
G6: {=iferror(XLOOKUP(A6,'Download of SFDC Activation Rep'!B:B,'Download of SFDC Activation Rep'!H:H),"")} -> Active | H6: {=iferror(xlookup(A6,'Download of SFDC Activation Rep'!B:B,'Download of SFDC Activation Rep'!L:L),"")} | I6: =IF(or(G6="Active",H6="Active"),"Active","Not Active") -> Active | J6: {=XLOOKUP(A6,'Download of SFDC Activation Rep'!B:B,'Download of SFDC Activation Rep'!T:T)} -> 006VT00000qRtP3 | K6: {=iferror(XLOOKUP(A6,'Download of SFDC Activation Rep'!B:B,'Download of SFDC Activation Rep'!C:C),"")} -> Nationwide Valuation Solutions, LLC
G7: {=iferror(XLOOKUP(A7,'Download of SFDC Activation Rep'!B:B,'Download of SFDC Activation Rep'!H:H),"")} -> Active | H7: {=iferror(xlookup(A7,'Download of SFDC Activation Rep'!B:B,'Download of SFDC Activation Rep'!L:L),"")} | I7: =IF(or(G7="Active",H7="Active"),"Active","Not Active") -> Active | J7: {=XLOOKUP(A7,'Download of SFDC Activation Rep'!B:B,'Download of SFDC Activation Rep'!T:T)} -> 006VT00000o1YIz | K7: {=iferror(XLOOKUP(A7,'Download of SFDC Activation Rep'!B:B,'Download of SFDC Activation Rep'!C:C),"")} -> CRNA Locum Jobs | L7: Avg GP per Org (Total GP/Total Orgs) | M7: =M9/M1 -> 660.67152
F8: =B8/D8 -> 0.013476821 | G8: {=iferror(XLOOKUP(A8,'Download of SFDC Activation Rep'!B:B,'Download of SFDC Activation Rep'!H:H),"")} -> Active | H8: {=iferror(xlookup(A8,'Download of SFDC Activation Rep'!B:B,'Download of SFDC Activation Rep'!L:L),"")} | I8: =IF(or(G8="Active",H8="Active"),"Active","Not Active") -> Active | J8: {=XLOOKUP(A8,'Download of SFDC Activation Rep'!B:B,'Download of SFDC Activation Rep'!T:T)} -> 006VT00000qes29 | K8: {=iferror(XLOOKUP(A8,'Download of SFDC Activation Rep'!B:B,'Download of SFDC Activation Rep'!C:C),"")} -> Temporary Assistance Guru, Inc
G9: {=iferror(XLOOKUP(A9,'Download of SFDC Activation Rep'!B:B,'Download of SFDC Activation Rep'!H:H),"")} -> Active | H9: {=iferror(xlookup(A9,'Download of SFDC Activation Rep'!B:B,'Download of SFDC Activation Rep'!L:L),"")} | I9: =IF(or(G9="Active",H9="Active"),"Active","Not Active") -> Active | J9: {=XLOOKUP(A9,'Download of SFDC Activation Rep'!B:B,'Download of SFDC Activation Rep'!T:T)} -> 006VT00000qc2Np | K9: {=iferror(XLOOKUP(A9,'Download of SFDC Activation Rep'!B:B,'Download of SFDC Activation Rep'!C:C),"")} -> Carismo | L9: Total GP Generated | M9: =SUM(B:B) -> 138741.02
F10: =B10/D10 -> 0.004187638 | G10: {=iferror(XLOOKUP(A10,'Download of SFDC Activation Rep'!B:B,'Download of SFDC Activation Rep'!H:H),"")} -> Active | H10: {=iferror(xlookup(A10,'Download of SFDC Activation Rep'!B:B,'Download of SFDC Activation Rep'!L:L),"")} | I10: =IF(or(G10="Active",H10="Active"),"Active","Not Active") -> Active | J10: {=XLOOKUP(A10,'Download of SFDC Activation Rep'!B:B,'Download of SFDC Activation Rep'!T:T)} -> 006VT00000qLJJR | K10: {=iferror(XLOOKUP(A10,'Download of SFDC Activation Rep'!B:B,'Download of SFDC Activation Rep'!C:C),"")} -> Lyophilization Systems Inc.
G11: {=iferror(XLOOKUP(A11,'Download of SFDC Activation Rep'!B:B,'Download of SFDC Activation Rep'!H:H),"")} -> Active | H11: {=iferror(xlookup(A11,'Download of SFDC Activation Rep'!B:B,'Download of SFDC Activation Rep'!L:L),"")} | I11: =IF(or(G11="Active",H11="Active"),"Active","Not Active") -> Active | J11: {=XLOOKUP(A11,'Download of SFDC Activation Rep'!B:B,'Download of SFDC Activation Rep'!T:T)} -> 006VT00000puqcr | K11: {=iferror(XLOOKUP(A11,'Download of SFDC Activation Rep'!B:B,'Download of SFDC Activation Rep'!C:C),"")} -> Victory Bicycle Studio | L11: Total TPV Generated | M11: =SUM(D:D) -> 1.0781201e+08
G12: {=iferror(XLOOKUP(A12,'Download of SFDC Activation Rep'!B:B,'Download of SFDC Activation Rep'!H:H),"")} -> Active | H12: {=iferror(xlookup(A12,'Download of SFDC Activation Rep'!B:B,'Download of SFDC Activation Rep'!L:L),"")} | I12: =IF(or(G12="Active",H12="Active"),"Active","Not Active") -> Active | J12: {=XLOOKUP(A12,'Download of SFDC Activation Rep'!B:B,'Download of SFDC Activation Rep'!T:T)} -> 006VT00000pom8v | K12: {=iferror(XLOOKUP(A12,'Download of SFDC Activation Rep'!B:B,'Download of SFDC Activation Rep'!C:C),"")} -> Kloris LLC
G13: {=iferror(XLOOKUP(A13,'Download of SFDC Activation Rep'!B:B,'Download of SFDC Activation Rep'!H:H),"")} -> Active | H13: {=iferror(xlookup(A13,'Download of SFDC Activation Rep'!B:B,'Download of SFDC Activation Rep'!L:L),"")} | I13: =IF(or(G13="Active",H13="Active"),"Active","Not Active") -> Active | J13: {=XLOOKUP(A13,'Download of SFDC Activation Rep'!B:B,'Download of SFDC Activation Rep'!T:T)} -> 006VT00000phFw6 | K13: {=iferror(XLOOKUP(A13,'Download of SFDC Activation Rep'!B:B,'Download of SFDC Activation Rep'!C:C),"")} -> Covenant Construction Group Inc
G14: {=iferror(XLOOKUP(A14,'Download of SFDC Activation Rep'!B:B,'Download of SFDC Activation Rep'!H:H),"")} -> Active | H14: {=iferror(xlookup(A14,'Download of SFDC Activation Rep'!B:B,'Download of SFDC Activation Rep'!L:L),"")} -> Active | I14: =IF(or(G14="Active",H14="Active"),"Active","Not Active") -> Active | J14: {=XLOOKUP(A14,'Download of SFDC Activation Rep'!B:B,'Download of SFDC Activation Rep'!T:T)} -> 006VT00000pude2 | K14: {=iferror(XLOOKUP(A14,'Download of SFDC Activation Rep'!B:B,'Download of SFDC Activation Rep'!C:C),"")} -> WHITE COLLAR MEDIA | L14: Median TPV per Org per Month | M14: =MEDIAN(E:E) -> 20082.14
G15: {=iferror(XLOOKUP(A15,'Download of SFDC Activation Rep'!B:B,'Download of SFDC Activation Rep'!H:H),"")} -> Active | H15: {=iferror(xlookup(A15,'Download of SFDC Activation Rep'!B:B,'Download of SFDC Activation Rep'!L:L),"")} | I15: =IF(or(G15="Active",H15="Active"),"Active","Not Active") -> Active | J15: {=XLOOKUP(A15,'Download of SFDC Activation Rep'!B:B,'Download of SFDC Activation Rep'!T:T)} -> 006VT00000qMODp | K15: {=iferror(XLOOKUP(A15,'Download of SFDC Activation Rep'!B:B,'Download of SFDC Activation Rep'!C:C),"")} -> Willard Manufacturing | L15: Median Monthly GP per Org | M15: =MEDIAN(C:C) -> 49.83475
F16: =B16/D16 -> 0.0051612878 | G16: {=iferror(XLOOKUP(A16,'Download of SFDC Activation Rep'!B:B,'Download of SFDC Activation Rep'!H:H),"")} -> Churned | H16: {=iferror(xlookup(A16,'Download of SFDC Activation Rep'!B:B,'Download of SFDC Activation Rep'!L:L),"")} | I16: =IF(or(G16="Active",H16="Active"),"Active","Not Active") -> Not Active | J16: {=XLOOKUP(A16,'Download of SFDC Activation Rep'!B:B,'Download of SFDC Activation Rep'!T:T)} -> 006VT00000ozbfN | K16: {=iferror(XLOOKUP(A16,'Download of SFDC Activation Rep'!B:B,'Download of SFDC Activation Rep'!C:C),"")} -> Wellness Warrior
G17: {=iferror(XLOOKUP(A17,'Download of SFDC Activation Rep'!B:B,'Download of SFDC Activation Rep'!H:H),"")} -> Active | H17: {=iferror(xlookup(A17,'Download of SFDC Activation Rep'!B:B,'Download of SFDC Activation Rep'!L:L),"")} | I17: =IF(or(G17="Active",H17="Active"),"Active","Not Active") -> Active | J17: {=XLOOKUP(A17,'Download of SFDC Activation Rep'!B:B,'Download of SFDC Activation Rep'!T:T)} -> 006VT00000owVZi | K17: {=iferror(XLOOKUP(A17,'Download of SFDC Activation Rep'!B:B,'Download of SFDC Activation Rep'!C:C),"")} -> Verde Recruitment LLC
F18: =B18/D18 -> 0.0093750189 | G18: {=iferror(XLOOKUP(A18,'Download of SFDC Activation Rep'!B:B,'Download of SFDC Activation Rep'!H:H),"")} -> Churned | H18: {=iferror(xlookup(A18,'Download of SFDC Activation Rep'!B:B,'Download of SFDC Activation Rep'!L:L),"")} | I18: =IF(or(G18="Active",H18="Active"),"Active","Not Active") -> Not Active | J18: {=XLOOKUP(A18,'Download of SFDC Activation Rep'!B:B,'Download of SFDC Activation Rep'!T:T)} -> 006VT00000p3zpZ | K18: {=iferror(XLOOKUP(A18,'Download of SFDC Activation Rep'!B:B,'Download of SFDC Activation Rep'!C:C),"")} -> ALM Ortho, Inc
F19: =B19/D19 -> 0.00039119861 | G19: {=iferror(XLOOKUP(A19,'Download of SFDC Activation Rep'!B:B,'Download of SFDC Activation Rep'!H:H),"")} -> Active | H19: {=iferror(xlookup(A19,'Download of SFDC Activation Rep'!B:B,'Download of SFDC Activation Rep'!L:L),"")} | I19: =IF(or(G19="Active",H19="Active"),"Active","Not Active") -> Active | J19: {=XLOOKUP(A19,'Download of SFDC Activation Rep'!B:B,'Download of SFDC Activation Rep'!T:T)} -> 006VT00000owujN | K19: {=iferror(XLOOKUP(A19,'Download of SFDC Activation Rep'!B:B,'Download of SFDC Activation Rep'!C:C),"")} -> GATEWAY LIGHTING AND DESIGN INC
G20: {=iferror(XLOOKUP(A20,'Download of SFDC Activation Rep'!B:B,'Download of SFDC Activation Rep'!H:H),"")} -> Active | H20: {=iferror(xlookup(A20,'Download of SFDC Activation Rep'!B:B,'Download of SFDC Activation Rep'!L:L),"")} | I20: =IF(or(G20="Active",H20="Active"),"Active","Not Active") -> Active | J20: {=XLOOKUP(A20,'Download of SFDC Activation Rep'!B:B,'Download of SFDC Activation Rep'!T:T)} -> 006VT00000oiGKQ | K20: {=iferror(XLOOKUP(A20,'Download of SFDC Activation Rep'!B:B,'Download of SFDC Activation Rep'!C:C),"")} -> Landa Cleary Travel Co. Inc. D.B.A. Mater Dei Tours
F21: =B21/D21 -> 0.00091798239 | G21: {=iferror(XLOOKUP(A21,'Download of SFDC Activation Rep'!B:B,'Download of SFDC Activation Rep'!H:H),"")} -> Inactive | H21: {=iferror(xlookup(A21,'Download of SFDC Activation Rep'!B:B,'Download of SFDC Activation Rep'!L:L),"")} | I21: =IF(or(G21="Active",H21="Active"),"Active","Not Active") -> Not Active | J21: {=XLOOKUP(A21,'Download of SFDC Activation Rep'!B:B,'Download of SFDC Activation Rep'!T:T)} -> 006VT00000oxFRG | K21: {=iferror(XLOOKUP(A21,'Download of SFDC Activation Rep'!B:B,'Download of SFDC Activation Rep'!C:C),"")} -> Paragon Oilfield Products
F22: =B22/D22 -> 0.0052537656 | G22: {=iferror(XLOOKUP(A22,'Download of SFDC Activation Rep'!B:B,'Download of SFDC Activation Rep'!H:H),"")} -> Churned | H22: {=iferror(xlookup(A22,'Download of SFDC Activation Rep'!B:B,'Download of SFDC Activation Rep'!L:L),"")} | I22: =IF(or(G22="Active",H22="Active"),"Active","Not Active") -> Not Active | J22: {=XLOOKUP(A22,'Download of SFDC Activation Rep'!B:B,'Download of SFDC Activation Rep'!T:T)} -> 006VT00000omtTe | K22: {=iferror(XLOOKUP(A22,'Download of SFDC Activation Rep'!B:B,'Download of SFDC Activation Rep'!C:C),"")} -> Plat4orm
G23: {=iferror(XLOOKUP(A23,'Download of SFDC Activation Rep'!B:B,'Download of SFDC Activation Rep'!H:H),"")} -> Active | H23: {=iferror(xlookup(A23,'Download of SFDC Activation Rep'!B:B,'Download of SFDC Activation Rep'!L:L),"")} -> Active | I23: =IF(or(G23="Active",H23="Active"),"Active","Not Active") -> Active | J23: {=XLOOKUP(A23,'Download of SFDC Activation Rep'!B:B,'Download of SFDC Activation Rep'!T:T)} -> 006VT00000oaqEc | K23: {=iferror(XLOOKUP(A23,'Download of SFDC Activation Rep'!B:B,'Download of SFDC Activation Rep'!C:C),"")} -> Bauer Home Furnishings
F24: =B24/D24 -> 0.0078407393 | G24: {=iferror(XLOOKUP(A24,'Download of SFDC Activation Rep'!B:B,'Download of SFDC Activation Rep'!H:H),"")} -> Churned | H24: {=iferror(xlookup(A24,'Download of SFDC Activation Rep'!B:B,'Download of SFDC Activation Rep'!L:L),"")} | I24: =IF(or(G24="Active",H24="Active"),"Active","Not Active") -> Not Active | J24: {=XLOOKUP(A24,'Download of SFDC Activation Rep'!B:B,'Download of SFDC Activation Rep'!T:T)} -> 006VT00000o3k37 | K24: {=iferror(XLOOKUP(A24,'Download of SFDC Activation Rep'!B:B,'Download of SFDC Activation Rep'!C:C),"")} -> Robert Davies Home Improvement LLC
F25: =B25/D25 -> 0.00012818388 | G25: {=iferror(XLOOKUP(A25,'Download of SFDC Activation Rep'!B:B,'Download of SFDC Activation Rep'!H:H),"")} -> Active | H25: {=iferror(xlookup(A25,'Download of SFDC Activation Rep'!B:B,'Download of SFDC Activation Rep'!L:L),"")} | I25: =IF(or(G25="Active",H25="Active"),"Active","Not Active") -> Active | J25: {=XLOOKUP(A25,'Download of SFDC Activation Rep'!B:B,'Download of SFDC Activation Rep'!T:T)} -> 006VT00000nRBzG | K25: {=iferror(XLOOKUP(A25,'Download of SFDC Activation Rep'!B:B,'Download of SFDC Activation Rep'!C:C),"")} -> TAVco Holdings I LLC
F26: =B26/D26 -> 0.0090953532 | G26: {=iferror(XLOOKUP(A26,'Download of SFDC Activation Rep'!B:B,'Download of SFDC Activation Rep'!H:H),"")} -> Active | H26: {=iferror(xlookup(A26,'Download of SFDC Activation Rep'!B:B,'Download of SFDC Activation Rep'!L:L),"")} | I26: =IF(or(G26="Active",H26="Active"),"Active","Not Active") -> Active | J26: {=XLOOKUP(A26,'Download of SFDC Activation Rep'!B:B,'Download of SFDC Activation Rep'!T:T)} -> 006VT00000ozlGX | K26: {=iferror(XLOOKUP(A26,'Download of SFDC Activation Rep'!B:B,'Download of SFDC Activation Rep'!C:C),"")} -> Shree Satya Sai LLC
F27: =B27/D27 -> 0.0033511173 | G27: {=iferror(XLOOKUP(A27,'Download of SFDC Activation Rep'!B:B,'Download of SFDC Activation Rep'!H:H),"")} -> Active | H27: {=iferror(xlookup(A27,'Download of SFDC Activation Rep'!B:B,'Download of SFDC Activation Rep'!L:L),"")} | I27: =IF(or(G27="Active",H27="Active"),"Active","Not Active") -> Active | J27: {=XLOOKUP(A27,'Download of SFDC Activation Rep'!B:B,'Download of SFDC Activation Rep'!T:T)} -> 006VT00000owkyd | K27: {=iferror(XLOOKUP(A27,'Download of SFDC Activation Rep'!B:B,'Download of SFDC Activation Rep'!C:C),"")} -> Shri Krishna Inc
G28: {=iferror(XLOOKUP(A28,'Download of SFDC Activation Rep'!B:B,'Download of SFDC Activation Rep'!H:H),"")} -> Active | H28: {=iferror(xlookup(A28,'Download of SFDC Activation Rep'!B:B,'Download of SFDC Activation Rep'!L:L),"")} | I28: =IF(or(G28="Active",H28="Active"),"Active","Not Active") -> Active | J28: {=XLOOKUP(A28,'Download of SFDC Activation Rep'!B:B,'Download of SFDC Activation Rep'!T:T)} -> 006VT00000nyDe5 | K28: {=iferror(XLOOKUP(A28,'Download of SFDC Activation Rep'!B:B,'Download of SFDC Activation Rep'!C:C),"")} -> Abecca Grace, LLC
F29: =B29/D29 -> 0.0013985165 | G29: {=iferror(XLOOKUP(A29,'Download of SFDC Activation Rep'!B:B,'Download of SFDC Activation Rep'!H:H),"")} -> Inactive | H29: {=iferror(xlookup(A29,'Download of SFDC Activation Rep'!B:B,'Download of SFDC Activation Rep'!L:L),"")} | I29: =IF(or(G29="Active",H29="Active"),"Active","Not Active") -> Not Active | J29: {=XLOOKUP(A29,'Download of SFDC Activation Rep'!B:B,'Download of SFDC Activation Rep'!T:T)} -> 006VT00000oHBVJ | K29: {=iferror(XLOOKUP(A29,'Download of SFDC Activation Rep'!B:B,'Download of SFDC Activation Rep'!C:C),"")} -> Navi Transport Services LLC
F30: =B30/D30 -> -5.5555556e-05 | G30: {=iferror(XLOOKUP(A30,'Download of SFDC Activation Rep'!B:B,'Download of SFDC Activation Rep'!H:H),"")} -> Churned | H30: {=iferror(xlookup(A30,'Download of SFDC Activation Rep'!B:B,'Download of SFDC Activation Rep'!L:L),"")} | I30: =IF(or(G30="Active",H30="Active"),"Active","Not Active") -> Not Active | J30: {=XLOOKUP(A30,'Download of SFDC Activation Rep'!B:B,'Download of SFDC Activation Rep'!T:T)} -> 006VT00000oarfO | K30: {=iferror(XLOOKUP(A30,'Download of SFDC Activation Rep'!B:B,'Download of SFDC Activation Rep'!C:C),"")} -> DRD Builders Inc
G31: {=iferror(XLOOKUP(A31,'Download of SFDC Activation Rep'!B:B,'Download of SFDC Activation Rep'!H:H),"")} -> Active | H31: {=iferror(xlookup(A31,'Download of SFDC Activation Rep'!B:B,'Download of SFDC Activation Rep'!L:L),"")} | I31: =IF(or(G31="Active",H31="Active"),"Active","Not Active") -> Active | J31: {=XLOOKUP(A31,'Download of SFDC Activation Rep'!B:B,'Download of SFDC Activation Rep'!T:T)} -> 006VT00000n1G3L | K31: {=iferror(XLOOKUP(A31,'Download of SFDC Activation Rep'!B:B,'Download of SFDC Activation Rep'!C:C),"")} -> Shree Group
F32: =B32/D32 -> 0.0053271532 | G32: {=iferror(XLOOKUP(A32,'Download of SFDC Activation Rep'!B:B,'Download of SFDC Activation Rep'!H:H),"")} -> Active | H32: {=iferror(xlookup(A32,'Download of SFDC Activation Rep'!B:B,'Download of SFDC Activation Rep'!L:L),"")} | I32: =IF(or(G32="Active",H32="Active"),"Active","Not Active") -> Active | J32: {=XLOOKUP(A32,'Download of SFDC Activation Rep'!B:B,'Download of SFDC Activation Rep'!T:T)} -> 006VT00000o0w8t | K32: {=iferror(XLOOKUP(A32,'Download of SFDC Activation Rep'!B:B,'Download of SFDC Activation Rep'!C:C),"")} -> JR Prime Pro Construction, LLC
G33: {=iferror(XLOOKUP(A33,'Download of SFDC Activation Rep'!B:B,'Download of SFDC Activation Rep'!H:H),"")} -> Active | H33: {=iferror(xlookup(A33,'Download of SFDC Activation Rep'!B:B,'Download of SFDC Activation Rep'!L:L),"")} | I33: =IF(or(G33="Active",H33="Active"),"Active","Not Active") -> Active | J33: {=XLOOKUP(A33,'Download of SFDC Activation Rep'!B:B,'Download of SFDC Activation Rep'!T:T)} -> 006VT00000niYeT | K33: {=iferror(XLOOKUP(A33,'Download of SFDC Activation Rep'!B:B,'Download of SFDC Activation Rep'!C:C),"")} -> Brian Schmidt Builder
F34: =B34/D34 -> 0.0029888955 | G34: {=iferror(XLOOKUP(A34,'Download of SFDC Activation Rep'!B:B,'Download of SFDC Activation Rep'!H:H),"")} | H34: {=iferror(xlookup(A34,'Download of SFDC Activation Rep'!B:B,'Download of SFDC Activation Rep'!L:L),"")} -> Active | I34: =IF(or(G34="Active",H34="Active"),"Active","Not Active") -> Active | J34: {=XLOOKUP(A34,'Download of SFDC Activation Rep'!B:B,'Download of SFDC Activation Rep'!T:T)} -> 006VT00000oHAFu | K34: {=iferror(XLOOKUP(A34,'Download of SFDC Activation Rep'!B:B,'Download of SFDC Activation Rep'!C:C),"")} -> NOFD Firewatch Detail
G35: {=iferror(XLOOKUP(A35,'Download of SFDC Activation Rep'!B:B,'Download of SFDC Activation Rep'!H:H),"")} -> Active | H35: {=iferror(xlookup(A35,'Download of SFDC Activation Rep'!B:B,'Download of SFDC Activation Rep'!L:L),"")} | I35: =IF(or(G35="Active",H35="Active"),"Active","Not Active") -> Active | J35: {=XLOOKUP(A35,'Download of SFDC Activation Rep'!B:B,'Download of SFDC Activation Rep'!T:T)} -> 006VT00000niEUT | K35: {=iferror(XLOOKUP(A35,'Download of SFDC Activation Rep'!B:B,'Download of SFDC Activation Rep'!C:C),"")} -> K2 Parts Inc
G36: {=iferror(XLOOKUP(A36,'Download of SFDC Activation Rep'!B:B,'Download of SFDC Activation Rep'!H:H),"")} -> Active | H36: {=iferror(xlookup(A36,'Download of SFDC Activation Rep'!B:B,'Download of SFDC Activation Rep'!L:L),"")} | I36: =IF(or(G36="Active",H36="Active"),"Active","Not Active") -> Active | J36: {=XLOOKUP(A36,'Download of SFDC Activation Rep'!B:B,'Download of SFDC Activation Rep'!T:T)} -> 006VT00000mhbv7 | K36: {=iferror(XLOOKUP(A36,'Download of SFDC Activation Rep'!B:B,'Download of SFDC Activation Rep'!C:C),"")} -> YRS LLC
G37: {=iferror(XLOOKUP(A37,'Download of SFDC Activation Rep'!B:B,'Download of SFDC Activation Rep'!H:H),"")} | H37: {=iferror(xlookup(A37,'Download of SFDC Activation Rep'!B:B,'Download of SFDC Activation Rep'!L:L),"")} -> Active | I37: =IF(or(G37="Active",H37="Active"),"Active","Not Active") -> Active | J37: {=XLOOKUP(A37,'Download of SFDC Activation Rep'!B:B,'Download of SFDC Activation Rep'!T:T)} -> 006VT00000n1i61 | K37: {=iferror(XLOOKUP(A37,'Download of SFDC Activation Rep'!B:B,'Download of SFDC Activation Rep'!C:C),"")} -> Placewise LLC
G38: {=iferror(XLOOKUP(A38,'Download of SFDC Activation Rep'!B:B,'Download of SFDC Activation Rep'!H:H),"")} | H38: {=iferror(xlookup(A38,'Download of SFDC Activation Rep'!B:B,'Download of SFDC Activation Rep'!L:L),"")} -> Churned | I38: =IF(or(G38="Active",H38="Active"),"Active","Not Active") -> Not Active | J38: {=XLOOKUP(A38,'Download of SFDC Activation Rep'!B:B,'Download of SFDC Activation Rep'!T:T)} -> 006UU00000NTaFm | K38: {=iferror(XLOOKUP(A38,'Download of SFDC Activation Rep'!B:B,'Download of SFDC Activation Rep'!C:C),"")} -> GUBER LLC
F39: =B39/D39 -> 0.0048553101 | G39: {=iferror(XLOOKUP(A39,'Download of SFDC Activation Rep'!B:B,'Download of SFDC Activation Rep'!H:H),"")} | H39: {=iferror(xlookup(A39,'Download of SFDC Activation Rep'!B:B,'Download of SFDC Activation Rep'!L:L),"")} -> Active | I39: =IF(or(G39="Active",H39="Active"),"Active","Not Active") -> Active | J39: {=XLOOKUP(A39,'Download of SFDC Activation Rep'!B:B,'Download of SFDC Activation Rep'!T:T)} -> 006VT00000o0NO1 | K39: {=iferror(XLOOKUP(A39,'Download of SFDC Activation Rep'!B:B,'Download of SFDC Activation Rep'!C:C),"")} -> Guber Sports Llc | L39: Total TPV Generated | M39: {=XLOOKUP("Grand Total",A:A,D:D)} -> #N/A
F40: =B40/D40 -> 0.0014188838 | G40: {=iferror(XLOOKUP(A40,'Download of SFDC Activation Rep'!B:B,'Download of SFDC Activation Rep'!H:H),"")} -> Active | H40: {=iferror(xlookup(A40,'Download of SFDC Activation Rep'!B:B,'Download of SFDC Activation Rep'!L:L),"")} | I40: =IF(or(G40="Active",H40="Active"),"Active","Not Active") -> Active | J40: {=XLOOKUP(A40,'Download of SFDC Activation Rep'!B:B,'Download of SFDC Activation Rep'!T:T)} -> 006VT00000nhlvV | K40: {=iferror(XLOOKUP(A40,'Download of SFDC Activation Rep'!B:B,'Download of SFDC Activation Rep'!C:C),"")} -> Island Containers
G41: {=iferror(XLOOKUP(A41,'Download of SFDC Activation Rep'!B:B,'Download of SFDC Activation Rep'!H:H),"")} -> Active | H41: {=iferror(xlookup(A41,'Download of SFDC Activation Rep'!B:B,'Download of SFDC Activation Rep'!L:L),"")} | I41: =IF(or(G41="Active",H41="Active"),"Active","Not Active") -> Active | J41: {=XLOOKUP(A41,'Download of SFDC Activation Rep'!B:B,'Download of SFDC Activation Rep'!T:T)} -> 006VT00000m8uPZ | K41: {=iferror(XLOOKUP(A41,'Download of SFDC Activation Rep'!B:B,'Download of SFDC Activation Rep'!C:C),"")} -> St George Spirits
F42: =B42/D42 -> 0.00507017 | G42: {=iferror(XLOOKUP(A42,'Download of SFDC Activation Rep'!B:B,'Download of SFDC Activation Rep'!H:H),"")} -> Active | H42: {=iferror(xlookup(A42,'Download of SFDC Activation Rep'!B:B,'Download of SFDC Activation Rep'!L:L),"")} | I42: =IF(or(G42="Active",H42="Active"),"Active","Not Active") -> Active | J42: {=XLOOKUP(A42,'Download of SFDC Activation Rep'!B:B,'Download of SFDC Activation Rep'!T:T)} -> 006VT00000sgdkJ | K42: {=iferror(XLOOKUP(A42,'Download of SFDC Activation Rep'!B:B,'Download of SFDC Activation Rep'!C:C),"")} -> Buyers Choice USA
G43: {=iferror(XLOOKUP(A43,'Download of SFDC Activation Rep'!B:B,'Download of SFDC Activation Rep'!H:H),"")} | H43: {=iferror(xlookup(A43,'Download of SFDC Activation Rep'!B:B,'Download of SFDC Activation Rep'!L:L),"")} -> Active | I43: =IF(or(G43="Active",H43="Active"),"Active","Not Active") -> Active | J43: {=XLOOKUP(A43,'Download of SFDC Activation Rep'!B:B,'Download of SFDC Activation Rep'!T:T)} -> 006VT00000moks5 | K43: {=iferror(XLOOKUP(A43,'Download of SFDC Activation Rep'!B:B,'Download of SFDC Activation Rep'!C:C),"")} -> Cross Engineering LLC
G44: {=iferror(XLOOKUP(A44,'Download of SFDC Activation Rep'!B:B,'Download of SFDC Activation Rep'!H:H),"")} | H44: {=iferror(xlookup(A44,'Download of SFDC Activation Rep'!B:B,'Download of SFDC Activation Rep'!L:L),"")} -> Active | I44: =IF(or(G44="Active",H44="Active"),"Active","Not Active") -> Active | J44: {=XLOOKUP(A44,'Download of SFDC Activation Rep'!B:B,'Download of SFDC Activation Rep'!T:T)} -> 006VT00000mMU2D | K44: {=iferror(XLOOKUP(A44,'Download of SFDC Activation Rep'!B:B,'Download of SFDC Activation Rep'!C:C),"")} -> Advance Displays, Inc.
F45: =B45/D45 -> 0.0036860056 | G45: {=iferror(XLOOKUP(A45,'Download of SFDC Activation Rep'!B:B,'Download of SFDC Activation Rep'!H:H),"")} -> Active | H45: {=iferror(xlookup(A45,'Download of SFDC Activation Rep'!B:B,'Download of SFDC Activation Rep'!L:L),"")} | I45: =IF(or(G45="Active",H45="Active"),"Active","Not Active") -> Active | J45: {=XLOOKUP(A45,'Download of SFDC Activation Rep'!B:B,'Download of SFDC Activation Rep'!T:T)} -> 006VT00000sgdkK | K45: {=iferror(XLOOKUP(A45,'Download of SFDC Activation Rep'!B:B,'Download of SFDC Activation Rep'!C:C),"")} -> HTT Cardmax Company
G46: {=iferror(XLOOKUP(A46,'Download of SFDC Activation Rep'!B:B,'Download of SFDC Activation Rep'!H:H),"")} -> Active | H46: {=iferror(xlookup(A46,'Download of SFDC Activation Rep'!B:B,'Download of SFDC Activation Rep'!L:L),"")} -> Active | I46: =IF(or(G46="Active",H46="Active"),"Active","Not Active") -> Active | J46: {=XLOOKUP(A46,'Download of SFDC Activation Rep'!B:B,'Download of SFDC Activation Rep'!T:T)} -> 006UU00000NKOvN | K46: {=iferror(XLOOKUP(A46,'Download of SFDC Activation Rep'!B:B,'Download of SFDC Activation Rep'!C:C),"")} -> Performance Supply LLC
G47: {=iferror(XLOOKUP(A47,'Download of SFDC Activation Rep'!B:B,'Download of SFDC Activation Rep'!H:H),"")} -> Active | H47: {=iferror(xlookup(A47,'Download of SFDC Activation Rep'!B:B,'Download of SFDC Activation Rep'!L:L),"")} | I47: =IF(or(G47="Active",H47="Active"),"Active","Not Active") -> Active | J47: {=XLOOKUP(A47,'Download of SFDC Activation Rep'!B:B,'Download of SFDC Activation Rep'!T:T)} -> 006VT00000lSjgf | K47: {=iferror(XLOOKUP(A47,'Download of SFDC Activation Rep'!B:B,'Download of SFDC Activation Rep'!C:C),"")} -> Vertex Holdings
F48: =B48/D48 -> 0.012816524 | G48: {=iferror(XLOOKUP(A48,'Download of SFDC Activation Rep'!B:B,'Download of SFDC Activation Rep'!H:H),"")} -> Active | H48: {=iferror(xlookup(A48,'Download of SFDC Activation Rep'!B:B,'Download of SFDC Activation Rep'!L:L),"")} | I48: =IF(or(G48="Active",H48="Active"),"Active","Not Active") -> Active | J48: {=XLOOKUP(A48,'Download of SFDC Activation Rep'!B:B,'Download of SFDC Activation Rep'!T:T)} -> 006VT00000o0Lin | K48: {=iferror(XLOOKUP(A48,'Download of SFDC Activation Rep'!B:B,'Download of SFDC Activation Rep'!C:C),"")} -> Paine Group, Inc
F49: =B49/D49 -> 0.0022789667 | G49: {=iferror(XLOOKUP(A49,'Download of SFDC Activation Rep'!B:B,'Download of SFDC Activation Rep'!H:H),"")} -> Active | H49: {=iferror(xlookup(A49,'Download of SFDC Activation Rep'!B:B,'Download of SFDC Activation Rep'!L:L),"")} | I49: =IF(or(G49="Active",H49="Active"),"Active","Not Active") -> Active | J49: {=XLOOKUP(A49,'Download of SFDC Activation Rep'!B:B,'Download of SFDC Activation Rep'!T:T)} -> 006VT00000mBkrt | K49: {=iferror(XLOOKUP(A49,'Download of SFDC Activation Rep'!B:B,'Download of SFDC Activation Rep'!C:C),"")} -> Beyond Pickleball LLC
G50: {=iferror(XLOOKUP(A50,'Download of SFDC Activation Rep'!B:B,'Download of SFDC Activation Rep'!H:H),"")} -> Inactive | H50: {=iferror(xlookup(A50,'Download of SFDC Activation Rep'!B:B,'Download of SFDC Activation Rep'!L:L),"")} | I50: =IF(or(G50="Active",H50="Active"),"Active","Not Active") -> Not Active | J50: {=XLOOKUP(A50,'Download of SFDC Activation Rep'!B:B,'Download of SFDC Activation Rep'!T:T)} -> 006VT00000mBcSy | K50: {=iferror(XLOOKUP(A50,'Download of SFDC Activation Rep'!B:B,'Download of SFDC Activation Rep'!C:C),"")} -> Stigall Sales Inc.
F51: =B51/D51 -> 0.0020187338 | G51: {=iferror(XLOOKUP(A51,'Download of SFDC Activation Rep'!B:B,'Download of SFDC Activation Rep'!H:H),"")} -> Active | H51: {=iferror(xlookup(A51,'Download of SFDC Activation Rep'!B:B,'Download of SFDC Activation Rep'!L:L),"")} | I51: =IF(or(G51="Active",H51="Active"),"Active","Not Active") -> Active | J51: {=XLOOKUP(A51,'Download of SFDC Activation Rep'!B:B,'Download of SFDC Activation Rep'!T:T)} -> 006VT00000o0IBR | K51: {=iferror(XLOOKUP(A51,'Download of SFDC Activation Rep'!B:B,'Download of SFDC Activation Rep'!C:C),"")} -> Cope Equities
F52: =B52/D52 -> 0.0083517431 | G52: {=iferror(XLOOKUP(A52,'Download of SFDC Activation Rep'!B:B,'Download of SFDC Activation Rep'!H:H),"")} -> Active | H52: {=iferror(xlookup(A52,'Download of SFDC Activation Rep'!B:B,'Download of SFDC Activation Rep'!L:L),"")} | I52: =IF(or(G52="Active",H52="Active"),"Active","Not Active") -> Active | J52: {=XLOOKUP(A52,'Download of SFDC Activation Rep'!B:B,'Download of SFDC Activation Rep'!T:T)} -> 006VT00000lZPWj | K52: {=iferror(XLOOKUP(A52,'Download of SFDC Activation Rep'!B:B,'Download of SFDC Activation Rep'!C:C),"")} -> Remotees LLC
F53: =B53/D53 -> 0.0046379678 | G53: {=iferror(XLOOKUP(A53,'Download of SFDC Activation Rep'!B:B,'Download of SFDC Activation Rep'!H:H),"")} -> Active | H53: {=iferror(xlookup(A53,'Download of SFDC Activation Rep'!B:B,'Download of SFDC Activation Rep'!L:L),"")} -> Churned | I53: =IF(or(G53="Active",H53="Active"),"Active","Not Active") -> Active | J53: {=XLOOKUP(A53,'Download of SFDC Activation Rep'!B:B,'Download of SFDC Activation Rep'!T:T)} -> 006VT00000m1AEc | K53: {=iferror(XLOOKUP(A53,'Download of SFDC Activation Rep'!B:B,'Download of SFDC Activation Rep'!C:C),"")} -> Barrel-Art LLC
F54: =B54/D54 -> 0.0056161506 | G54: {=iferror(XLOOKUP(A54,'Download of SFDC Activation Rep'!B:B,'Download of SFDC Activation Rep'!H:H),"")} -> Churned | H54: {=iferror(xlookup(A54,'Download of SFDC Activation Rep'!B:B,'Download of SFDC Activation Rep'!L:L),"")} -> Active | I54: =IF(or(G54="Active",H54="Active"),"Active","Not Active") -> Active | J54: {=XLOOKUP(A54,'Download of SFDC Activation Rep'!B:B,'Download of SFDC Activation Rep'!T:T)} -> 006VT00000mBSWo | K54: {=iferror(XLOOKUP(A54,'Download of SFDC Activation Rep'!B:B,'Download of SFDC Activation Rep'!C:C),"")} -> Avenue 8 Group Inc
G55: {=iferror(XLOOKUP(A55,'Download of SFDC Activation Rep'!B:B,'Download of SFDC Activation Rep'!H:H),"")} -> Active | H55: {=iferror(xlookup(A55,'Download of SFDC Activation Rep'!B:B,'Download of SFDC Activation Rep'!L:L),"")} | I55: =IF(or(G55="Active",H55="Active"),"Active","Not Active") -> Active | J55: {=XLOOKUP(A55,'Download of SFDC Activation Rep'!B:B,'Download of SFDC Activation Rep'!T:T)} -> 006UU00000Og7FN | K55: {=iferror(XLOOKUP(A55,'Download of SFDC Activation Rep'!B:B,'Download of SFDC Activation Rep'!C:C),"")} -> Solutions Group International, Inc.
F56: =B56/D56 -> 0.013410104 | G56: {=iferror(XLOOKUP(A56,'Download of SFDC Activation Rep'!B:B,'Download of SFDC Activation Rep'!H:H),"")} -> Active | H56: {=iferror(xlookup(A56,'Download of SFDC Activation Rep'!B:B,'Download of SFDC Activation Rep'!L:L),"")} | I56: =IF(or(G56="Active",H56="Active"),"Active","Not Active") -> Active | J56: {=XLOOKUP(A56,'Download of SFDC Activation Rep'!B:B,'Download of SFDC Activation Rep'!T:T)} -> 006VT00000m4O9l | K56: {=iferror(XLOOKUP(A56,'Download of SFDC Activation Rep'!B:B,'Download of SFDC Activation Rep'!C:C),"")} -> VetNecessity UC LLC
F57: =B57/D57 -> 0.013044091 | G57: {=iferror(XLOOKUP(A57,'Download of SFDC Activation Rep'!B:B,'Download of SFDC Activation Rep'!H:H),"")} -> Active | H57: {=iferror(xlookup(A57,'Download of SFDC Activation Rep'!B:B,'Download of SFDC Activation Rep'!L:L),"")} | I57: =IF(or(G57="Active",H57="Active"),"Active","Not Active") -> Active | J57: {=XLOOKUP(A57,'Download of SFDC Activation Rep'!B:B,'Download of SFDC Activation Rep'!T:T)} -> 006VT00000m4kgX | K57: {=iferror(XLOOKUP(A57,'Download of SFDC Activation Rep'!B:B,'Download of SFDC Activation Rep'!C:C),"")} -> GF Equine LLC
G58: {=iferror(XLOOKUP(A58,'Download of SFDC Activation Rep'!B:B,'Download of SFDC Activation Rep'!H:H),"")} -> Active | H58: {=iferror(xlookup(A58,'Download of SFDC Activation Rep'!B:B,'Download of SFDC Activation Rep'!L:L),"")} -> Active | I58: =IF(or(G58="Active",H58="Active"),"Active","Not Active") -> Active | J58: {=XLOOKUP(A58,'Download of SFDC Activation Rep'!B:B,'Download of SFDC Activation Rep'!T:T)} -> 006UU00000OgQGQ | K58: {=iferror(XLOOKUP(A58,'Download of SFDC Activation Rep'!B:B,'Download of SFDC Activation Rep'!C:C),"")} -> Scale Foundations Inc.
F59: =B59/D59 -> 0.085141045 | G59: {=iferror(XLOOKUP(A59,'Download of SFDC Activation Rep'!B:B,'Download of SFDC Activation Rep'!H:H),"")} | H59: {=iferror(xlookup(A59,'Download of SFDC Activation Rep'!B:B,'Download of SFDC Activation Rep'!L:L),"")} -> Active | I59: =IF(or(G59="Active",H59="Active"),"Active","Not Active") -> Active | J59: {=XLOOKUP(A59,'Download of SFDC Activation Rep'!B:B,'Download of SFDC Activation Rep'!T:T)} -> 006UU00000MmwzV | K59: {=iferror(XLOOKUP(A59,'Download of SFDC Activation Rep'!B:B,'Download of SFDC Activation Rep'!C:C),"")} -> Totally Chocolate Inc
F60: =B60/D60 -> 0.002575789 | G60: {=iferror(XLOOKUP(A60,'Download of SFDC Activation Rep'!B:B,'Download of SFDC Activation Rep'!H:H),"")} -> Churned | H60: {=iferror(xlookup(A60,'Download of SFDC Activation Rep'!B:B,'Download of SFDC Activation Rep'!L:L),"")} | I60: =IF(or(G60="Active",H60="Active"),"Active","Not Active") -> Not Active | J60: {=XLOOKUP(A60,'Download of SFDC Activation Rep'!B:B,'Download of SFDC Activation Rep'!T:T)} -> 006UU00000P2TFe | K60: {=iferror(XLOOKUP(A60,'Download of SFDC Activation Rep'!B:B,'Download of SFDC Activation Rep'!C:C),"")} -> RLM Solutions, LLC.
F61: =B61/D61 -> 0.0066693784 | G61: {=iferror(XLOOKUP(A61,'Download of SFDC Activation Rep'!B:B,'Download of SFDC Activation Rep'!H:H),"")} -> Churned | H61: {=iferror(xlookup(A61,'Download of SFDC Activation Rep'!B:B,'Download of SFDC Activation Rep'!L:L),"")} | I61: =IF(or(G61="Active",H61="Active"),"Active","Not Active") -> Not Active | J61: {=XLOOKUP(A61,'Download of SFDC Activation Rep'!B:B,'Download of SFDC Activation Rep'!T:T)} -> 006UU00000OzBdU | K61: {=iferror(XLOOKUP(A61,'Download of SFDC Activation Rep'!B:B,'Download of SFDC Activation Rep'!C:C),"")} -> Thistle and Amber LLC
G62: {=iferror(XLOOKUP(A62,'Download of SFDC Activation Rep'!B:B,'Download of SFDC Activation Rep'!H:H),"")} -> Active | H62: {=iferror(xlookup(A62,'Download of SFDC Activation Rep'!B:B,'Download of SFDC Activation Rep'!L:L),"")} | I62: =IF(or(G62="Active",H62="Active"),"Active","Not Active") -> Active | J62: {=XLOOKUP(A62,'Download of SFDC Activation Rep'!B:B,'Download of SFDC Activation Rep'!T:T)} -> 006UU00000P2jh1 | K62: {=iferror(XLOOKUP(A62,'Download of SFDC Activation Rep'!B:B,'Download of SFDC Activation Rep'!C:C),"")} -> Herbert Law Group, LLC
G63: {=iferror(XLOOKUP(A63,'Download of SFDC Activation Rep'!B:B,'Download of SFDC Activation Rep'!H:H),"")} -> Active | H63: {=iferror(xlookup(A63,'Download of SFDC Activation Rep'!B:B,'Download of SFDC Activation Rep'!L:L),"")} -> Active | I63: =IF(or(G63="Active",H63="Active"),"Active","Not Active") -> Active | J63: {=XLOOKUP(A63,'Download of SFDC Activation Rep'!B:B,'Download of SFDC Activation Rep'!T:T)} -> 006UU00000O7JjF | K63: {=iferror(XLOOKUP(A63,'Download of SFDC Activation Rep'!B:B,'Download of SFDC Activation Rep'!C:C),"")} -> Field Sports Publishing, Inc.
F64: =B64/D64 -> 0.0013267765 | G64: {=iferror(XLOOKUP(A64,'Download of SFDC Activation Rep'!B:B,'Download of SFDC Activation Rep'!H:H),"")} -> Active | H64: {=iferror(xlookup(A64,'Download of SFDC Activation Rep'!B:B,'Download of SFDC Activation Rep'!L:L),"")} | I64: =IF(or(G64="Active",H64="Active"),"Active","Not Active") -> Active | J64: {=XLOOKUP(A64,'Download of SFDC Activation Rep'!B:B,'Download of SFDC Activation Rep'!T:T)} -> 006VT00000sgdkH | K64: {=iferror(XLOOKUP(A64,'Download of SFDC Activation Rep'!B:B,'Download of SFDC Activation Rep'!C:C),"")} -> Marcus & Pollack LLP
G65: {=iferror(XLOOKUP(A65,'Download of SFDC Activation Rep'!B:B,'Download of SFDC Activation Rep'!H:H),"")} | H65: {=iferror(xlookup(A65,'Download of SFDC Activation Rep'!B:B,'Download of SFDC Activation Rep'!L:L),"")} -> Active | I65: =IF(or(G65="Active",H65="Active"),"Active","Not Active") -> Active | J65: {=XLOOKUP(A65,'Download of SFDC Activation Rep'!B:B,'Download of SFDC Activation Rep'!T:T)} -> 006UU00000OSfnC | K65: {=iferror(XLOOKUP(A65,'Download of SFDC Activation Rep'!B:B,'Download of SFDC Activation Rep'!C:C),"")} -> Wyoming Traders
F66: =B66/D66 -> 0.0086828148 | G66: {=iferror(XLOOKUP(A66,'Download of SFDC Activation Rep'!B:B,'Download of SFDC Activation Rep'!H:H),"")} -> Active | H66: {=iferror(xlookup(A66,'Download of SFDC Activation Rep'!B:B,'Download of SFDC Activation Rep'!L:L),"")} -> Churned | I66: =IF(or(G66="Active",H66="Active"),"Active","Not Active") -> Active | J66: {=XLOOKUP(A66,'Download of SFDC Activation Rep'!B:B,'Download of SFDC Activation Rep'!T:T)} -> 006UU00000OcYZ7 | K66: {=iferror(XLOOKUP(A66,'Download of SFDC Activation Rep'!B:B,'Download of SFDC Activation Rep'!C:C),"")} -> Big House Group LLC
G67: {=iferror(XLOOKUP(A67,'Download of SFDC Activation Rep'!B:B,'Download of SFDC Activation Rep'!H:H),"")} -> Active | H67: {=iferror(xlookup(A67,'Download of SFDC Activation Rep'!B:B,'Download of SFDC Activation Rep'!L:L),"")} | I67: =IF(or(G67="Active",H67="Active"),"Active","Not Active") -> Active | J67: {=XLOOKUP(A67,'Download of SFDC Activation Rep'!B:B,'Download of SFDC Activation Rep'!T:T)} -> 006UU00000OcWHB | K67: {=iferror(XLOOKUP(A67,'Download of SFDC Activation Rep'!B:B,'Download of SFDC Activation Rep'!C:C),"")} -> Kenneth Adam Designs
G68: {=iferror(XLOOKUP(A68,'Download of SFDC Activation Rep'!B:B,'Download of SFDC Activation Rep'!H:H),"")} -> Active | H68: {=iferror(xlookup(A68,'Download of SFDC Activation Rep'!B:B,'Download of SFDC Activation Rep'!L:L),"")} | I68: =IF(or(G68="Active",H68="Active"),"Active","Not Active") -> Active | J68: {=XLOOKUP(A68,'Download of SFDC Activation Rep'!B:B,'Download of SFDC Activation Rep'!T:T)} -> 006UU00000P2Ttx | K68: {=iferror(XLOOKUP(A68,'Download of SFDC Activation Rep'!B:B,'Download of SFDC Activation Rep'!C:C),"")} -> Skycrest Group llc
G69: {=iferror(XLOOKUP(A69,'Download of SFDC Activation Rep'!B:B,'Download of SFDC Activation Rep'!H:H),"")} | H69: {=iferror(xlookup(A69,'Download of SFDC Activation Rep'!B:B,'Download of SFDC Activation Rep'!L:L),"")} -> Churned | I69: =IF(or(G69="Active",H69="Active"),"Active","Not Active") -> Not Active | J69: {=XLOOKUP(A69,'Download of SFDC Activation Rep'!B:B,'Download of SFDC Activation Rep'!T:T)} -> 006VT00000m1Q85 | K69: {=iferror(XLOOKUP(A69,'Download of SFDC Activation Rep'!B:B,'Download of SFDC Activation Rep'!C:C),"")} -> Premier Computer Solutions, LLC
G70: {=iferror(XLOOKUP(A70,'Download of SFDC Activation Rep'!B:B,'Download of SFDC Activation Rep'!H:H),"")} -> Active | H70: {=iferror(xlookup(A70,'Download of SFDC Activation Rep'!B:B,'Download of SFDC Activation Rep'!L:L),"")} | I70: =IF(or(G70="Active",H70="Active"),"Active","Not Active") -> Active | J70: {=XLOOKUP(A70,'Download of SFDC Activation Rep'!B:B,'Download of SFDC Activation Rep'!T:T)} -> 006UU00000NnFru | K70: {=iferror(XLOOKUP(A70,'Download of SFDC Activation Rep'!B:B,'Download of SFDC Activation Rep'!C:C),"")} -> Mark S Dill DDS PLLC
F71: =B71/D71 -> 0.00053155835 | G71: {=iferror(XLOOKUP(A71,'Download of SFDC Activation Rep'!B:B,'Download of SFDC Activation Rep'!H:H),"")} | H71: {=iferror(xlookup(A71,'Download of SFDC Activation Rep'!B:B,'Download of SFDC Activation Rep'!L:L),"")} -> Active | I71: =IF(or(G71="Active",H71="Active"),"Active","Not Active") -> Active | J71: {=XLOOKUP(A71,'Download of SFDC Activation Rep'!B:B,'Download of SFDC Activation Rep'!T:T)} -> 006UU00000LzrZq | K71: {=iferror(XLOOKUP(A71,'Download of SFDC Activation Rep'!B:B,'Download of SFDC Activation Rep'!C:C),"")} -> Navimow Inc
G72: {=iferror(XLOOKUP(A72,'Download of SFDC Activation Rep'!B:B,'Download of SFDC Activation Rep'!H:H),"")} | H72: {=iferror(xlookup(A72,'Download of SFDC Activation Rep'!B:B,'Download of SFDC Activation Rep'!L:L),"")} -> Active | I72: =IF(or(G72="Active",H72="Active"),"Active","Not Active") -> Active | J72: {=XLOOKUP(A72,'Download of SFDC Activation Rep'!B:B,'Download of SFDC Activation Rep'!T:T)} -> 006UU00000OHzkP | K72: {=iferror(XLOOKUP(A72,'Download of SFDC Activation Rep'!B:B,'Download of SFDC Activation Rep'!C:C),"")} -> Smart Launch LLC
F73: =B73/D73 -> 0.0052641593 | G73: {=iferror(XLOOKUP(A73,'Download of SFDC Activation Rep'!B:B,'Download of SFDC Activation Rep'!H:H),"")} | H73: {=iferror(xlookup(A73,'Download of SFDC Activation Rep'!B:B,'Download of SFDC Activation Rep'!L:L),"")} -> Inactive | I73: =IF(or(G73="Active",H73="Active"),"Active","Not Active") -> Not Active | J73: {=XLOOKUP(A73,'Download of SFDC Activation Rep'!B:B,'Download of SFDC Activation Rep'!T:T)} -> 006VT00000o0WeE | K73: {=iferror(XLOOKUP(A73,'Download of SFDC Activation Rep'!B:B,'Download of SFDC Activation Rep'!C:C),"")} -> Rippa Sales Oklahoma, Llc
F74: =B74/D74 -> 0.020421229 | G74: {=iferror(XLOOKUP(A74,'Download of SFDC Activation Rep'!B:B,'Download of SFDC Activation Rep'!H:H),"")} | H74: {=iferror(xlookup(A74,'Download of SFDC Activation Rep'!B:B,'Download of SFDC Activation Rep'!L:L),"")} -> Inactive | I74: =IF(or(G74="Active",H74="Active"),"Active","Not Active") -> Not Active | J74: {=XLOOKUP(A74,'Download of SFDC Activation Rep'!B:B,'Download of SFDC Activation Rep'!T:T)} -> 006UU00000OEKtv | K74: {=iferror(XLOOKUP(A74,'Download of SFDC Activation Rep'!B:B,'Download of SFDC Activation Rep'!C:C),"")} -> D.R. Stephens Estate Wines, LLC
F75: =B75/D75 -> 0.0027934357 | G75: {=iferror(XLOOKUP(A75,'Download of SFDC Activation Rep'!B:B,'Download of SFDC Activation Rep'!H:H),"")} -> Active | H75: {=iferror(xlookup(A75,'Download of SFDC Activation Rep'!B:B,'Download of SFDC Activation Rep'!L:L),"")} | I75: =IF(or(G75="Active",H75="Active"),"Active","Not Active") -> Active | J75: {=XLOOKUP(A75,'Download of SFDC Activation Rep'!B:B,'Download of SFDC Activation Rep'!T:T)} -> 006VT00000sgdkF | K75: {=iferror(XLOOKUP(A75,'Download of SFDC Activation Rep'!B:B,'Download of SFDC Activation Rep'!C:C),"")} -> Naz Apparel
F76: =B76/D76 -> 0.0016977083 | G76: {=iferror(XLOOKUP(A76,'Download of SFDC Activation Rep'!B:B,'Download of SFDC Activation Rep'!H:H),"")} -> Churned | H76: {=iferror(xlookup(A76,'Download of SFDC Activation Rep'!B:B,'Download of SFDC Activation Rep'!L:L),"")} -> Inactive | I76: =IF(or(G76="Active",H76="Active"),"Active","Not Active") -> Not Active | J76: {=XLOOKUP(A76,'Download of SFDC Activation Rep'!B:B,'Download of SFDC Activation Rep'!T:T)} -> 006UU00000NTZhu | K76: {=iferror(XLOOKUP(A76,'Download of SFDC Activation Rep'!B:B,'Download of SFDC Activation Rep'!C:C),"")} -> JSC Distribution LLC
F77: =B77/D77 -> 0.0077282504 | G77: {=iferror(XLOOKUP(A77,'Download of SFDC Activation Rep'!B:B,'Download of SFDC Activation Rep'!H:H),"")} -> Churned | H77: {=iferror(xlookup(A77,'Download of SFDC Activation Rep'!B:B,'Download of SFDC Activation Rep'!L:L),"")} | I77: =IF(or(G77="Active",H77="Active"),"Active","Not Active") -> Not Active | J77: {=XLOOKUP(A77,'Download of SFDC Activation Rep'!B:B,'Download of SFDC Activation Rep'!T:T)} -> 006UU00000MzGw1 | K77: {=iferror(XLOOKUP(A77,'Download of SFDC Activation Rep'!B:B,'Download of SFDC Activation Rep'!C:C),"")} -> Official H2O, LLC
F78: =B78/D78 -> -1.0094953e-05 | G78: {=iferror(XLOOKUP(A78,'Download of SFDC Activation Rep'!B:B,'Download of SFDC Activation Rep'!H:H),"")} -> Churned | H78: {=iferror(xlookup(A78,'Download of SFDC Activation Rep'!B:B,'Download of SFDC Activation Rep'!L:L),"")} | I78: =IF(or(G78="Active",H78="Active"),"Active","Not Active") -> Not Active | J78: {=XLOOKUP(A78,'Download of SFDC Activation Rep'!B:B,'Download of SFDC Activation Rep'!T:T)} -> 006UU00000NzUFI | K78: {=iferror(XLOOKUP(A78,'Download of SFDC Activation Rep'!B:B,'Download of SFDC Activation Rep'!C:C),"")} -> Jet Powertrain
F79: =B79/D79 -> -2.6993865e-05 | G79: {=iferror(XLOOKUP(A79,'Download of SFDC Activation Rep'!B:B,'Download of SFDC Activation Rep'!H:H),"")} -> Churned | H79: {=iferror(xlookup(A79,'Download of SFDC Activation Rep'!B:B,'Download of SFDC Activation Rep'!L:L),"")} | I79: =IF(or(G79="Active",H79="Active"),"Active","Not Active") -> Not Active | J79: {=XLOOKUP(A79,'Download of SFDC Activation Rep'!B:B,'Download of SFDC Activation Rep'!T:T)} -> 006UU00000NzZy5 | K79: {=iferror(XLOOKUP(A79,'Download of SFDC Activation Rep'!B:B,'Download of SFDC Activation Rep'!C:C),"")} -> H&H Loveland Auto Parts, LLC
G80: {=iferror(XLOOKUP(A80,'Download of SFDC Activation Rep'!B:B,'Download of SFDC Activation Rep'!H:H),"")} -> Churned | H80: {=iferror(xlookup(A80,'Download of SFDC Activation Rep'!B:B,'Download of SFDC Activation Rep'!L:L),"")} | I80: =IF(or(G80="Active",H80="Active"),"Active","Not Active") -> Not Active | J80: {=XLOOKUP(A80,'Download of SFDC Activation Rep'!B:B,'Download of SFDC Activation Rep'!T:T)} -> 006UU00000NYF95 | K80: {=iferror(XLOOKUP(A80,'Download of SFDC Activation Rep'!B:B,'Download of SFDC Activation Rep'!C:C),"")} -> Ambassador Delivery Service
F81: =B81/D81 -> 0.00142131 | G81: {=iferror(XLOOKUP(A81,'Download of SFDC Activation Rep'!B:B,'Download of SFDC Activation Rep'!H:H),"")} -> Active | H81: {=iferror(xlookup(A81,'Download of SFDC Activation Rep'!B:B,'Download of SFDC Activation Rep'!L:L),"")} | I81: =IF(or(G81="Active",H81="Active"),"Active","Not Active") -> Active | J81: {=XLOOKUP(A81,'Download of SFDC Activation Rep'!B:B,'Download of SFDC Activation Rep'!T:T)} -> 006UU00000O1KbZ | K81: {=iferror(XLOOKUP(A81,'Download of SFDC Activation Rep'!B:B,'Download of SFDC Activation Rep'!C:C),"")} -> MJDII Architects, Inc. | L81: Median TPV per Org per Month | M81: =MEDIAN(E65:E240) -> 18870.71
G82: {=iferror(XLOOKUP(A82,'Download of SFDC Activation Rep'!B:B,'Download of SFDC Activation Rep'!H:H),"")} -> Active | H82: {=iferror(xlookup(A82,'Download of SFDC Activation Rep'!B:B,'Download of SFDC Activation Rep'!L:L),"")} | I82: =IF(or(G82="Active",H82="Active"),"Active","Not Active") -> Active | J82: {=XLOOKUP(A82,'Download of SFDC Activation Rep'!B:B,'Download of SFDC Activation Rep'!T:T)} -> 006UU00000MNO9q | K82: {=iferror(XLOOKUP(A82,'Download of SFDC Activation Rep'!B:B,'Download of SFDC Activation Rep'!C:C),"")} -> Johnston LLC
G83: {=iferror(XLOOKUP(A83,'Download of SFDC Activation Rep'!B:B,'Download of SFDC Activation Rep'!H:H),"")} -> Active | H83: {=iferror(xlookup(A83,'Download of SFDC Activation Rep'!B:B,'Download of SFDC Activation Rep'!L:L),"")} | I83: =IF(or(G83="Active",H83="Active"),"Active","Not Active") -> Active | J83: {=XLOOKUP(A83,'Download of SFDC Activation Rep'!B:B,'Download of SFDC Activation Rep'!T:T)} -> 006UU00000MIrPN | K83: {=iferror(XLOOKUP(A83,'Download of SFDC Activation Rep'!B:B,'Download of SFDC Activation Rep'!C:C),"")} -> National Rural Health Association
G84: {=iferror(XLOOKUP(A84,'Download of SFDC Activation Rep'!B:B,'Download of SFDC Activation Rep'!H:H),"")} | H84: {=iferror(xlookup(A84,'Download of SFDC Activation Rep'!B:B,'Download of SFDC Activation Rep'!L:L),"")} -> Active | I84: =IF(or(G84="Active",H84="Active"),"Active","Not Active") -> Active | J84: {=XLOOKUP(A84,'Download of SFDC Activation Rep'!B:B,'Download of SFDC Activation Rep'!T:T)} -> 006UU00000O1Il6 | K84: {=iferror(XLOOKUP(A84,'Download of SFDC Activation Rep'!B:B,'Download of SFDC Activation Rep'!C:C),"")} -> Jenny and Francois Selections
G85: {=iferror(XLOOKUP(A85,'Download of SFDC Activation Rep'!B:B,'Download of SFDC Activation Rep'!H:H),"")} | H85: {=iferror(xlookup(A85,'Download of SFDC Activation Rep'!B:B,'Download of SFDC Activation Rep'!L:L),"")} -> Active | I85: =IF(or(G85="Active",H85="Active"),"Active","Not Active") -> Active | J85: {=XLOOKUP(A85,'Download of SFDC Activation Rep'!B:B,'Download of SFDC Activation Rep'!T:T)} -> 006UU00000KfrEY | K85: {=iferror(XLOOKUP(A85,'Download of SFDC Activation Rep'!B:B,'Download of SFDC Activation Rep'!C:C),"")} -> Paydirt Earthworks Support Services LLC
G86: {=iferror(XLOOKUP(A86,'Download of SFDC Activation Rep'!B:B,'Download of SFDC Activation Rep'!H:H),"")} | H86: {=iferror(xlookup(A86,'Download of SFDC Activation Rep'!B:B,'Download of SFDC Activation Rep'!L:L),"")} -> Active | I86: =IF(or(G86="Active",H86="Active"),"Active","Not Active") -> Active | J86: {=XLOOKUP(A86,'Download of SFDC Activation Rep'!B:B,'Download of SFDC Activation Rep'!T:T)} -> 006UU00000NTAQC | K86: {=iferror(XLOOKUP(A86,'Download of SFDC Activation Rep'!B:B,'Download of SFDC Activation Rep'!C:C),"")} -> ETA Signs
F87: =B87/D87 -> 0.0085742109 | G87: {=iferror(XLOOKUP(A87,'Download of SFDC Activation Rep'!B:B,'Download of SFDC Activation Rep'!H:H),"")} | H87: {=iferror(xlookup(A87,'Download of SFDC Activation Rep'!B:B,'Download of SFDC Activation Rep'!L:L),"")} -> Active | I87: =IF(or(G87="Active",H87="Active"),"Active","Not Active") -> Active | J87: {=XLOOKUP(A87,'Download of SFDC Activation Rep'!B:B,'Download of SFDC Activation Rep'!T:T)} -> 006UU00000NKUMT | K87: {=iferror(XLOOKUP(A87,'Download of SFDC Activation Rep'!B:B,'Download of SFDC Activation Rep'!C:C),"")} -> 365 Archery LLC
G88: {=iferror(XLOOKUP(A88,'Download of SFDC Activation Rep'!B:B,'Download of SFDC Activation Rep'!H:H),"")} -> Churned | H88: {=iferror(xlookup(A88,'Download of SFDC Activation Rep'!B:B,'Download of SFDC Activation Rep'!L:L),"")} | I88: =IF(or(G88="Active",H88="Active"),"Active","Not Active") -> Not Active | J88: {=XLOOKUP(A88,'Download of SFDC Activation Rep'!B:B,'Download of SFDC Activation Rep'!T:T)} -> 006UU00000NV1PC | K88: {=iferror(XLOOKUP(A88,'Download of SFDC Activation Rep'!B:B,'Download of SFDC Activation Rep'!C:C),"")} -> Four Eleven LLC
F89: =B89/D89 -> 0.0058233227 | G89: {=iferror(XLOOKUP(A89,'Download of SFDC Activation Rep'!B:B,'Download of SFDC Activation Rep'!H:H),"")} -> Active | H89: {=iferror(xlookup(A89,'Download of SFDC Activation Rep'!B:B,'Download of SFDC Activation Rep'!L:L),"")} | I89: =IF(or(G89="Active",H89="Active"),"Active","Not Active") -> Active | J89: {=XLOOKUP(A89,'Download of SFDC Activation Rep'!B:B,'Download of SFDC Activation Rep'!T:T)} -> 006UU00000NVQyi | K89: {=iferror(XLOOKUP(A89,'Download of SFDC Activation Rep'!B:B,'Download of SFDC Activation Rep'!C:C),"")} -> The Makenzie House | L89: Total Active Orgs | M89: =COUNTIF(I:I,"Active") -> 146
G90: {=iferror(XLOOKUP(A90,'Download of SFDC Activation Rep'!B:B,'Download of SFDC Activation Rep'!H:H),"")} -> Active | H90: {=iferror(xlookup(A90,'Download of SFDC Activation Rep'!B:B,'Download of SFDC Activation Rep'!L:L),"")} | I90: =IF(or(G90="Active",H90="Active"),"Active","Not Active") -> Active | J90: {=XLOOKUP(A90,'Download of SFDC Activation Rep'!B:B,'Download of SFDC Activation Rep'!T:T)} -> 006UU00000MILsX | K90: {=iferror(XLOOKUP(A90,'Download of SFDC Activation Rep'!B:B,'Download of SFDC Activation Rep'!C:C),"")} -> H&H Auto Parts LLC
G91: {=iferror(XLOOKUP(A91,'Download of SFDC Activation Rep'!B:B,'Download of SFDC Activation Rep'!H:H),"")} -> Churned | H91: {=iferror(xlookup(A91,'Download of SFDC Activation Rep'!B:B,'Download of SFDC Activation Rep'!L:L),"")} | I91: =IF(or(G91="Active",H91="Active"),"Active","Not Active") -> Not Active | J91: {=XLOOKUP(A91,'Download of SFDC Activation Rep'!B:B,'Download of SFDC Activation Rep'!T:T)} -> 006UU00000MliAc | K91: {=iferror(XLOOKUP(A91,'Download of SFDC Activation Rep'!B:B,'Download of SFDC Activation Rep'!C:C),"")} -> BMP Team LLC
G92: {=iferror(XLOOKUP(A92,'Download of SFDC Activation Rep'!B:B,'Download of SFDC Activation Rep'!H:H),"")} -> Active | H92: {=iferror(xlookup(A92,'Download of SFDC Activation Rep'!B:B,'Download of SFDC Activation Rep'!L:L),"")} | I92: =IF(or(G92="Active",H92="Active"),"Active","Not Active") -> Active | J92: {=XLOOKUP(A92,'Download of SFDC Activation Rep'!B:B,'Download of SFDC Activation Rep'!T:T)} -> 006UU00000NTdIT | K92: {=iferror(XLOOKUP(A92,'Download of SFDC Activation Rep'!B:B,'Download of SFDC Activation Rep'!C:C),"")} -> Bespoke Creations LLC
G93: {=iferror(XLOOKUP(A93,'Download of SFDC Activation Rep'!B:B,'Download of SFDC Activation Rep'!H:H),"")} -> Churned | H93: {=iferror(xlookup(A93,'Download of SFDC Activation Rep'!B:B,'Download of SFDC Activation Rep'!L:L),"")} | I93: =IF(or(G93="Active",H93="Active"),"Active","Not Active") -> Not Active | J93: {=XLOOKUP(A93,'Download of SFDC Activation Rep'!B:B,'Download of SFDC Activation Rep'!T:T)} -> 006UU00000N0rFC | K93: {=iferror(XLOOKUP(A93,'Download of SFDC Activation Rep'!B:B,'Download of SFDC Activation Rep'!C:C),"")} -> Heritage Dialysis
F94: =B94/D94 -> 0.00031052518 | G94: {=iferror(XLOOKUP(A94,'Download of SFDC Activation Rep'!B:B,'Download of SFDC Activation Rep'!H:H),"")} -> Churned | H94: {=iferror(xlookup(A94,'Download of SFDC Activation Rep'!B:B,'Download of SFDC Activation Rep'!L:L),"")} | I94: =IF(or(G94="Active",H94="Active"),"Active","Not Active") -> Not Active | J94: {=XLOOKUP(A94,'Download of SFDC Activation Rep'!B:B,'Download of SFDC Activation Rep'!T:T)} -> 006UU00000MqVFx | K94: {=iferror(XLOOKUP(A94,'Download of SFDC Activation Rep'!B:B,'Download of SFDC Activation Rep'!C:C),"")} -> HOB Industries
F95: =B95/D95 -> -4.951322e-05 | G95: {=iferror(XLOOKUP(A95,'Download of SFDC Activation Rep'!B:B,'Download of SFDC Activation Rep'!H:H),"")} | H95: {=iferror(xlookup(A95,'Download of SFDC Activation Rep'!B:B,'Download of SFDC Activation Rep'!L:L),"")} -> Active | I95: =IF(or(G95="Active",H95="Active"),"Active","Not Active") -> Active | J95: {=XLOOKUP(A95,'Download of SFDC Activation Rep'!B:B,'Download of SFDC Activation Rep'!T:T)} -> 006UU00000MbeLB | K95: {=iferror(XLOOKUP(A95,'Download of SFDC Activation Rep'!B:B,'Download of SFDC Activation Rep'!C:C),"")} -> DQ of New Jersey, Inc.
F96: =B96/D96 -> 0.028968034 | G96: {=iferror(XLOOKUP(A96,'Download of SFDC Activation Rep'!B:B,'Download of SFDC Activation Rep'!H:H),"")} -> Churned | H96: {=iferror(xlookup(A96,'Download of SFDC Activation Rep'!B:B,'Download of SFDC Activation Rep'!L:L),"")} | I96: =IF(or(G96="Active",H96="Active"),"Active","Not Active") -> Not Active | J96: {=XLOOKUP(A96,'Download of SFDC Activation Rep'!B:B,'Download of SFDC Activation Rep'!T:T)} -> 006UU00000MhGCw | K96: {=iferror(XLOOKUP(A96,'Download of SFDC Activation Rep'!B:B,'Download of SFDC Activation Rep'!C:C),"")} -> Greenleaf Hotels LLC
G97: {=iferror(XLOOKUP(A97,'Download of SFDC Activation Rep'!B:B,'Download of SFDC Activation Rep'!H:H),"")} -> Active | H97: {=iferror(xlookup(A97,'Download of SFDC Activation Rep'!B:B,'Download of SFDC Activation Rep'!L:L),"")} | I97: =IF(or(G97="Active",H97="Active"),"Active","Not Active") -> Active | J97: {=XLOOKUP(A97,'Download of SFDC Activation Rep'!B:B,'Download of SFDC Activation Rep'!T:T)} -> 006UU00000N120w | K97: {=iferror(XLOOKUP(A97,'Download of SFDC Activation Rep'!B:B,'Download of SFDC Activation Rep'!C:C),"")} -> Amlife Global LLC
G98: {=iferror(XLOOKUP(A98,'Download of SFDC Activation Rep'!B:B,'Download of SFDC Activation Rep'!H:H),"")} -> Active | H98: {=iferror(xlookup(A98,'Download of SFDC Activation Rep'!B:B,'Download of SFDC Activation Rep'!L:L),"")} | I98: =IF(or(G98="Active",H98="Active"),"Active","Not Active") -> Active | J98: {=XLOOKUP(A98,'Download of SFDC Activation Rep'!B:B,'Download of SFDC Activation Rep'!T:T)} -> 006UU00000N14tx | K98: {=iferror(XLOOKUP(A98,'Download of SFDC Activation Rep'!B:B,'Download of SFDC Activation Rep'!C:C),"")} -> Hemm Ventures LLC
F99: =B99/D99 -> 0.0018664238 | G99: {=iferror(XLOOKUP(A99,'Download of SFDC Activation Rep'!B:B,'Download of SFDC Activation Rep'!H:H),"")} -> Active | H99: {=iferror(xlookup(A99,'Download of SFDC Activation Rep'!B:B,'Download of SFDC Activation Rep'!L:L),"")} | I99: =IF(or(G99="Active",H99="Active"),"Active","Not Active") -> Active | J99: {=XLOOKUP(A99,'Download of SFDC Activation Rep'!B:B,'Download of SFDC Activation Rep'!T:T)} -> 006UU00000N14E1 | K99: {=iferror(XLOOKUP(A99,'Download of SFDC Activation Rep'!B:B,'Download of SFDC Activation Rep'!C:C),"")} -> Trustwell Brands LLC | L99: Avg Monthly GP for Group | M99: =SUMIF(A:A,"<>"&"Grand Total",C:C) -> 34141.721
G100: {=iferror(XLOOKUP(A100,'Download of SFDC Activation Rep'!B:B,'Download of SFDC Activation Rep'!H:H),"")} -> Active | H100: {=iferror(xlookup(A100,'Download of SFDC Activation Rep'!B:B,'Download of SFDC Activation Rep'!L:L),"")} | I100: =IF(or(G100="Active",H100="Active"),"Active","Not Active") -> Active | J100: {=XLOOKUP(A100,'Download of SFDC Activation Rep'!B:B,'Download of SFDC Activation Rep'!T:T)} -> 006UU00000NTWs6 | K100: {=iferror(XLOOKUP(A100,'Download of SFDC Activation Rep'!B:B,'Download of SFDC Activation Rep'!C:C),"")} -> Meraki Ventures LLC
...

Sheet Ari
B1: Lifetime | C1: Quarterly | D1: Quarter Pacing | E1: Curret Month | I1: Revenue Pacing
A2: ='Lifetime Summary Stats'!O1 -> LAST DATA PULL: | B2: ='Lifetime Summary Stats'!P1 -> 46201 | C2: ='Current Calendar Quarter Stats'!S1 -> 46201 | D2: =C2 -> 46201 | E2: ='Current Calendar Month Stats'!Q1 -> 46201 | I2: Days Worked | J2: =NETWORKDAYS(L3,L2,J9:J19)-1 -> 63 | K2: Today | L2: =TODAY() -> 46202
A3: ='Lifetime Summary Stats'!L1 -> Total Orgs | B3: ='Lifetime Summary Stats'!M1 -> 210 | C3: ='Current Calendar Quarter Stats'!P1 -> 168 | E3: ='Current Calendar Month Stats'!N1 -> 121 | I3: Days Remaining | J3: =J4-J2 -> 2 | K3: Start | L3: 46113
A4: ='Lifetime Summary Stats'!L2 -> Total Active Orgs | B4: ='Lifetime Summary Stats'!M2 -> 146 | C4: ='Current Calendar Quarter Stats'!P2 -> 148 | E4: ='Current Calendar Month Stats'!N1 -> 121 | G4: ='Lifetime Summary Stats'!P2 | I4: Total Days | J4: =NETWORKDAYS(L3,L4,J9:J19) -> 65 | K4: End | L4: 46203
A5: ='Lifetime Summary Stats'!L3 | B5: ='Lifetime Summary Stats'!M3 | C5: ='Current Calendar Quarter Stats'!P3 | G5: ='Lifetime Summary Stats'!P3 | I5: % Elapsed | J5: =J2/J4 -> 0.96923077
A6: Avg Monthly TPV Per Org | B6: ='Lifetime Summary Stats'!M4 -> 99061.242 | C6: ='Current Calendar Quarter Stats'!P9 -> 109739.61 | E6: ='Current Calendar Month Stats'!N4 -> 130241.22 | G6: ='Lifetime Summary Stats'!P4
A7: Average Monthly GP Per Org | B7: ='Lifetime Summary Stats'!M5 -> 162.57962 | C7: ='Current Calendar Quarter Stats'!P7 -> 144.54922 | E7: ='Current Calendar Month Stats'!N6 -> 227.2066 | G7: ='Lifetime Summary Stats'!P5 | I7: BANK HOLIDAYS
A8: ='Lifetime Summary Stats'!L6 | B8: ='Lifetime Summary Stats'!M6 | C8: ='Current Calendar Quarter Stats'!P6 | G8: ='Lifetime Summary Stats'!P6
F9: ='Current Calendar Month Stats'!O7 | G9: ='Lifetime Summary Stats'!P7 | I9: NEW YEAR’S DAY | J9: 46023 | K9: 45658
I10: DR. MARTIN LUTHER KING, JR. DAY | J10: 46041
G11: ='Lifetime Summary Stats'!P9 | I11: WASHINGTON’S BIRTHDAY (Presidents’ Day) | J11: 46069
G12: ='Lifetime Summary Stats'!P10 | I12: MEMORIAL DAY | J12: 45803
G13: ='Lifetime Summary Stats'!P11 | I13: JUNETEEENTH | J13: 45827
G14: ='Lifetime Summary Stats'!P12 | I14: INDEPENDENCE DAY | J14: 45842
A15: ='Lifetime Summary Stats'!L9 -> Total GP Generated | B15: ='Lifetime Summary Stats'!M9 -> 138741.02 | C15: ='Current Calendar Quarter Stats'!P13 -> 72052.227 | D15: =SUM((C15/$J$2)*$J$4) -> 74339.599 | E15: ='Current Calendar Month Stats'!N13 -> 27491.998 | G15: ='Lifetime Summary Stats'!P13 | I15: LABOR DAY | J15: 45901
A16: ='Lifetime Summary Stats'!L10 | B16: ='Lifetime Summary Stats'!M10 | C16: ='Current Calendar Quarter Stats'!P14 | E16: ='Current Calendar Month Stats'!N8 | G16: ='Lifetime Summary Stats'!P14 | I16: COLUMBUS DAY/INDIGENOUS PEOPLE’S DAY | J16: 45943
A17: ='Lifetime Summary Stats'!L11 -> Total TPV Generated | B17: ='Lifetime Summary Stats'!M11 -> 1.0781201e+08 | C17: ='Current Calendar Quarter Stats'!P15 -> 54700977 | D17: =SUM((C17/$J$2)*$J$4) -> 56437516 | E17: ='Current Calendar Month Stats'!N15 -> 15759187 | G17: ='Lifetime Summary Stats'!P15 | I17: VETERANS’ DAY | J17: 45972
A18: ='Lifetime Summary Stats'!L12 | C18: ='Current Calendar Quarter Stats'!P16 | I18: THANKSGIVING DAY | J18: 45988
A19: ='Lifetime Summary Stats'!L13 | B19: Q1 Goal | C19: 115414 | I19: CHRISTMAS DAY | J19: 46016
B20: Current Attainment | C20: =SUM(C15/C19) -> 0.62429364 | D20: =C15 -> 72052.227
B21: Q4 Pacing Goal | C21: =SUM(D15/C19) -> 0.64411249 | D21: =D15 -> 74339.599
B23: UHV - GP here | C23: 89 | D23: <--Active QAU's
B24: Current Q Goal | C24: 2169500 | D24: 0.0031 | E24: <- Take Rate
B25: Current Attainment Q | C25: 215826 | D25: =SUM(C25/C24) -> 0.099481908 | E25: <- Current Atainment | F25: =SUM(C25/$J$2) -> 3425.8095 | G25: <-- GP Quarterly Biz Day
B26: Current Pacing | C26: =SUM((C25/$J$2)*$J$4) -> 222677.62
B27: Current Pacing % | C27: =SUM(C26/C24) -> 0.10264006
B28: UHV - Rev
B29: Current Q Goal | C29: =(0.027/D29)*C24 -> 18895645 | D29: 0.0031 | E29: <- Take Rate
B30: Current Attainment Q | C30: 2371000 | D30: =SUM(C30/C29) -> 0.12547865 | E30: <- Current Atainment | F30: =SUM(C30/$J$2) -> 37634.921 | G30: <-- Rev Quarterly Biz Day
B31: Current Pacing | C31: =SUM((C30/$J$2)*$J$4) -> 2446269.8
B32: Current Pacing % | C32: =SUM(C31/C29) -> 0.1294621
B33: UHV - TPV
B34: Current Q Goal | C34: =C24/D34 -> 6.9983871e+08 | D34: 0.0031 | E34: <- Take Rate
B35: Current Attainment Q | C35: 86740000 | D35: =SUM(C35/C34) -> 0.12394284 | E35: <- Current Atainment | F35: =SUM(C35/$J$2) -> 1376825.4 | G35: <-- TPV Quarterly Biz Day
B36: Current Pacing | C36: =SUM((C35/$J$2)*$J$4) -> 89493651
B37: Current Pacing % | C37: =SUM(C36/C34) -> 0.12787754
B39: SB - GP | C39: =C4 -> 148 | D39: <--Active QAU's | F39: =C7 -> 144.54922 | G39: <-- Avg GP per Org
B40: Current Q Goal | C40: 105000
B41: Current Attainment Q | C41: =C15 -> 72052.227 | D41: =SUM(C41/C40) -> 0.68621168 | E41: <- Current Atainment | F41: =SUM(C41/$J$2) -> 1143.6861 | G41: <-- GP Quarterly Biz Day
B42: Current Pacing | C42: =SUM((C41/$J$2)*$J$4) -> 74339.599
B43: Current Pacing % | C43: =SUM(C42/C40) -> 0.70799618
B44: SB - Rev | C44: =C39 -> 148 | D44: <--Active QAU's
B45: Current Q Goal | C45: =C40/D45 -> 420000 | D45: 0.25 | E45: <- Take Rate
B46: Current Attainment Q | C46: 43753.445 | D46: =SUM(C46/C45) -> 0.10417487 | E46: <- Current Atainment | F46: =SUM(C46/$J$2) -> 694.49913 | G46: <-- Rev Quarterly Biz Day | I46: this cant be lower than GP. doesnt make sense
B47: Current Pacing | C47: =SUM((C46/$J$2)*$J$4) -> 45142.444
B48: Current Pacing % | C48: =SUM(C47/C45) -> 0.10748201
B49: SB - TPV | C49: =C39 -> 148 | D49: <--Active QAU's
B50: Current Q Goal | C50: =C40/D50 -> 1.1666667e+08 | D50: 0.0009 | E50: <- Take Rate
B51: Current Attainment Q | C51: =C17 -> 54700977 | D51: =SUM(C51/C50) -> 0.46886552 | E51: <- Current Atainment | F51: =SUM(C51/$J$2) -> 868269.47 | G51: <-- TPV Quarterly Biz Day | I51: =F41/F51 -> 0.0013172018 | J51: very low
B52: Current Pacing | C52: =SUM((C51/$J$2)*$J$4) -> 56437516
B53: Current Pacing % | C53: =SUM(C52/C50) -> 0.48375013

Sheet Detail6-4440958
A1: current_tier | B1: month | C1: initiated_by_org_id | D1: activation_month | E1: total_payments | F1: ach_payments | G1: tpv | H1: visa_tpv | I1: total_revenue | J1: ach_fees | K1: core_gross_profit_wo_loss | L1: core_gp | M1: loss | N1: sub_gp | O1: Total GP | P1: Opp Create Date | Q1: Opp Create Month | R1: Count GP?
A2: Melio Unlimited Ach | B2: 46143 | C2: 4440958 | D2: 46054 | E2: 5 | F2: 0 | G2: 615065 | H2: 175763 | I2: 16376.89 | K2: 1107.2548 | L2: 550.06569 | M2: 557.18911 | N2: 64 | O2: 2313.7143 | P2: 46072 | Q2: 46054 | R2: Yes

Sheet Sheet7
A1: Opportunity ID | B1: Opportunity Name | C1: Account ID | D1: Account Name | E1: Estimated Monthly GP Potential | F1: Probability (%) | G1: Age | H1: Stage Duration | I1: Created Date | J1: Estimated Decision Date | K1: Estimated Account Sign-up Date | L1: Next Step | M1: Next Step Date | N1: Close Date | O1: Lead Source | P1: Opp Discovery Rep | Q1: Opportunity Source | R1: Forecast Category | S1: Source | T1: AP Status | U1: AR Status | V1: Organization Id | W1: Opportunity Owner | X1: Stage
A2: 006UU00000MQpnT | B2: Bicycle Bungalows, LLC - SMB | C2: 001UU00000LMKxh | D2: Bicycle Bungalows, LLC | E2: 0 | F2: 100 | G2: 13 | H2: 196 | I2: 45778 | N2: 45791 | P2: Kate Olivares | R2: Closed | S2: https://meliopayments.com/ | U2: Churned | V2: 3916711 | W2: Kate Olivares | X2: Closed Won | Y2: {=XLOOKUP(V2,'Lifetime Summary Stats'!A:A,'Lifetime Summary Stats'!A:A)} -> #N/A
A3: 006UU00000LzrZk | B3: Rumford Stone, Inc - SMB | C3: 001UU00000LeErN | D3: Rumford Stone, Inc | E3: 80 | F3: 100 | G3: 0 | H3: 177 | I3: 45797 | N3: 45797 | P3: Kate Olivares | R3: Closed | S3: direct | T3: Active | U3: Active | V3: 3935770 | W3: Kate Olivares | X3: Closed Won | Y3: {=XLOOKUP(V3,'Lifetime Summary Stats'!A:A,'Lifetime Summary Stats'!A:A)} -> 3935770
A4: 006UU00000Lzkqo | B4: INSAIT SOLUTIONS LLC - SMB | C4: 001UU00000LwhWp | D4: INSAIT SOLUTIONS LLC | E4: 80 | F4: 100 | G4: 0 | H4: 170 | I4: 45804 | N4: 45804 | P4: Kate Olivares | R4: Closed | S4: https://meliopayments.com/pricing/ | T4: Active | V4: 3945715 | W4: Kate Olivares | X4: Closed Won | Y4: {=XLOOKUP(V4,'Lifetime Summary Stats'!A:A,'Lifetime Summary Stats'!A:A)} -> 3945715
A5: 006UU00000Lzkqq | B5: Congdon & Coleman Real Estate - SMB | C5: 001UU00000LxMV3 | D5: Congdon & Coleman Real Estate | E5: 80 | F5: 100 | G5: 0 | H5: 169 | I5: 45805 | N5: 45805 | P5: Kate Olivares | R5: Closed | S5: adwords | T5: Active | V5: 3946131 | W5: Kate Olivares | X5: Closed Won | Y5: {=XLOOKUP(V5,'Lifetime Summary Stats'!A:A,'Lifetime Summary Stats'!A:A)} -> 3946131
A6: 006UU00000Lzkqp | B6: Weland Clinical Laboratories, P.C. - SMB | C6: 001UU00000LzUi6 | D6: Weland Clinical Laboratories, P.C. | E6: 55 | F6: 100 | G6: 0 | H6: 169 | I6: 45805 | L6: 6/9 Call Paul to see if CX assisted with QBO sync and CC addition since error message | N6: 45805 | P6: Kate Olivares | R6: Closed | S6: adwords | T6: Active | V6: 3947424 | W6: Kate Olivares | X6: Closed Won | Y6: {=XLOOKUP(V6,'Lifetime Summary Stats'!A:A,'Lifetime Summary Stats'!A:A)} -> 3947424
A7: 006UU00000Lzkqm | B7: ReSure Tax Tactics and Strategies LLC - SMB | C7: 001UU00000K4qSz | D7: ReSure Tax Tactics and Strategies LLC | E7: 25 | F7: 100 | G7: 0 | H7: 168 | I7: 45806 | L7: 6/9 monitor first AR payment | N7: 45806 | P7: Kate Olivares | R7: Closed | S7: direct | T7: Active | U7: Active | V7: 3785914 | W7: Kate Olivares | X7: Closed Won | Y7: {=XLOOKUP(V7,'Lifetime Summary Stats'!A:A,'Lifetime Summary Stats'!A:A)} -> 3785914
A8: 006UU00000Lzkql | B8: ReSure LLC - SMB | C8: 001UU00000K4q3k | D8: ReSure LLC | E8: 25 | F8: 100 | G8: 0 | H8: 168 | I8: 45806 | L8: 6/9 monitor first AR payment | N8: 45806 | P8: Kate Olivares | R8: Closed | S8: direct | T8: Inactive | U8: Churned | V8: 3738104 | W8: Kate Olivares | X8: Closed Won | Y8: {=XLOOKUP(V8,'Lifetime Summary Stats'!A:A,'Lifetime Summary Stats'!A:A)} -> 3738104
A9: 006UU00000MQpnS | B9: Not Provided - SMB | C9: 001UU00000MCdrD | D9: Meralex Farm, Inc. | E9: 0 | F9: 100 | G9: 3 | H9: 165 | I9: 45809 | N9: 45812 | P9: Kate Olivares | R9: Closed | S9: pardot | T9: Active | V9: 3942346 | W9: Kate Olivares | X9: Closed Won | Y9: {=XLOOKUP(V9,'Lifetime Summary Stats'!A:A,'Lifetime Summary Stats'!A:A)} -> 3942346
A10: 006UU00000Lzkqn | B10: Stupendous Events LLC - SMB | C10: 001UU00000LcZyT | D10: Stupendous Events LLC | E10: 25 | F10: 100 | G10: 0 | H10: 157 | I10: 45817 | L10: 6/9 sent a follow up email asking if theyve navigated through their account 5/21 signed up | N10: 45817 | P10: Kate Olivares | R10: Closed | S10: adwords | T10: Active | V10: 3934711 | W10: Kate Olivares | X10: Closed Won | Y10: {=XLOOKUP(V10,'Lifetime Summary Stats'!A:A,'Lifetime Summary Stats'!A:A)} -> 3934711
A11: 006UU00000Lzkqs | B11: scenic world LLC - SMB | C11: 001UU00000M7fhi | D11: scenic world LLC | E11: 25 | F11: 100 | G11: 19 | H11: 175 | I11: 45799 | J11: 45809 | K11: 45809 | L11: 6/9 Spoke to Joe, walked him through his account. Check in next month, next round of making payments is on 7/7 so check in on 7/9. Paypal charges 4.99 for intl payments so will continue to use that to pay abroad. 6/9 LVM, sent email | N11: 45818 | P11: Kate Olivares | R11: Closed | S11: adwords | T11: Active | V11: 3952865 | W11: Kate Olivares | X11: Closed Won | Y11: {=XLOOKUP(V11,'Lifetime Summary Stats'!A:A,'Lifetime Summary Stats'!A:A)} -> 3952865
A12: 006UU00000MQpnR | B12: K2X, Inc. - SMB | C12: 001UU00000MTQaj | D12: K2X, Inc. | E12: 0 | F12: 100 | G12: 10 | H12: 165 | I12: 45809 | N12: 45819 | P12: Kate Olivares | R12: Closed | S12: https://meliopayments.com/ | U12: Active | V12: 3942651 | W12: Kate Olivares | X12: Closed Won | Y12: {=XLOOKUP(V12,'Lifetime Summary Stats'!A:A,'Lifetime Summary Stats'!A:A)} -> 3942651
A13: 006UU00000MQpnN | B13: CLS Brands LLC - SMB | C13: 001UU00000MVqPC | D13: CLS Brands LLC | E13: 80 | F13: 100 | G13: 17 | H13: 165 | I13: 45809 | N13: 45826 | P13: Kate Olivares | R13: Closed | S13: adwords | T13: Active | V13: 3968250 | W13: Kate Olivares | X13: Closed Won | Y13: {=XLOOKUP(V13,'Lifetime Summary Stats'!A:A,'Lifetime Summary Stats'!A:A)} -> 3968250
A14: 006UU00000LzrZj | B14: Handled Commerce - SMB | C14: 001UU00000LcQ2O | D14: Handled Commerce | E14: 25 | F14: 100 | G14: 9 | H14: 154 | I14: 45820 | J14: 45821 | K14: 45821 | N14: 45829 | P14: Kate Olivares | R14: Closed | S14: adwords | U14: Inactive | V14: 3934664 | W14: Kate Olivares | X14: Closed Won | Y14: {=XLOOKUP(V14,'Lifetime Summary Stats'!A:A,'Lifetime Summary Stats'!A:A)} -> 3934664
A15: 006UU00000MQpn0 | B15: Florida Wholesale Printing - SMB | C15: 001UU00000MrOve | D15: Florida Wholesale Printing | E15: 0 | F15: 100 | G15: 12 | H15: 154 | I15: 45820 | N15: 45832 | P15: Kate Olivares | R15: Closed | S15: facebook | U15: Churned | V15: 492746 | W15: Kate Olivares | X15: Closed Won | Y15: {=XLOOKUP(V15,'Lifetime Summary Stats'!A:A,'Lifetime Summary Stats'!A:A)} -> 492746
A16: 006UU00000MQpnO | B16: Pelican Head Industries - SMB | C16: 001UU00000N4gI0 | D16: Pelican Head Industries | E16: 0 | F16: 100 | G16: 0 | H16: 98 | I16: 45876 | N16: 45833 | P16: Kate Olivares | R16: Closed | S16: microsoft ads | T16: Active | V16: 3962143 | W16: Kate Olivares | X16: Closed Won | Y16: {=XLOOKUP(V16,'Lifetime Summary Stats'!A:A,'Lifetime Summary Stats'!A:A)} -> 3962143
A17: 006UU00000MQpnM | B17: Pinelands Golf Club - SMB | C17: 001UU00000Mdzbn | D17: Pinelands Golf Club | E17: 0 | F17: 100 | G17: 13 | H17: 149 | I17: 45825 | N17: 45838 | P17: Kate Olivares | R17: Closed | S17: adwords | T17: Churned | V17: 3970546 | W17: Kate Olivares | X17: Closed Won | Y17: {=XLOOKUP(V17,'Lifetime Summary Stats'!A:A,'Lifetime Summary Stats'!A:A)} -> 3970546
A18: 006UU00000MQpnL | B18: Developros - SMB | C18: 001UU00000Mk42Q | D18: Developros | E18: 0 | F18: 100 | G18: 29 | H18: 165 | I18: 45809 | N18: 45838 | P18: Kate Olivares | R18: Closed | S18: https://meliopayments.com/ | U18: Active | V18: 3977410 | W18: Kate Olivares | X18: Closed Won | Y18: {=XLOOKUP(V18,'Lifetime Summary Stats'!A:A,'Lifetime Summary Stats'!A:A)} -> 3977410
A19: 006UU00000MQpnK | B19: Not Provided - SMB | C19: 001UU00000NKDTx | D19: Devents LLC | E19: 0 | F19: 100 | G19: 0 | H19: 135 | I19: 45839 | N19: 45839 | P19: Kate Olivares | R19: Closed | S19: https://meliopayments.com/ | U19: Inactive | V19: 3987123 | W19: Kate Olivares | X19: Closed Won | Y19: {=XLOOKUP(V19,'Lifetime Summary Stats'!A:A,'Lifetime Summary Stats'!A:A)} -> 3987123
A20: 006UU00000MQpnP | B20: United Home Care LLC - SMB | C20: 001UU00000MHUht | D20: United Home Care LLC | E20: 25 | F20: 100 | G20: 2 | H20: 135 | I20: 45839 | N20: 45841 | P20: Kate Olivares | R20: Closed | S20: https://meliopayments.com/ | T20: Active | V20: 3959338 | W20: Kate Olivares | X20: Closed Won | Y20: {=XLOOKUP(V20,'Lifetime Summary Stats'!A:A,'Lifetime Summary Stats'!A:A)} -> 3959338
A21: 006UU00000MQpnU | B21: The Hills Senior Living - SMB | C21: 001UU00000M54G7 | D21: The Hills Senior Living | E21: 80 | F21: 100 | G21: 32 | H21: 164 | I21: 45810 | N21: 45842 | P21: Kate Olivares | R21: Closed | S21: microsoft ads | U21: Active | V21: 3825826 | W21: Kate Olivares | X21: Closed Won | Y21: {=XLOOKUP(V21,'Lifetime Summary Stats'!A:A,'Lifetime Summary Stats'!A:A)} -> 3825826
A22: 006UU00000MQpnJ | B22: Northstar Distribution, LLC - SMB | C22: 001UU00000NPLvK | D22: Northstar Distribution, LLC | E22: 0 | F22: 100 | G22: 0 | H22: 126 | I22: 45848 | N22: 45847 | P22: Kate Olivares | R22: Closed | S22: adwords | T22: Churned | V22: 3991830 | W22: Kate Olivares | X22: Closed Won | Y22: {=XLOOKUP(V22,'Lifetime Summary Stats'!A:A,'Lifetime Summary Stats'!A:A)} -> #N/A
A23: 006UU00000MQpnX | B23: Leych Company - SMB | C23: 001UU00000Mk42O | D23: Leych Company | E23: 25 | F23: 100 | G23: 31 | H23: 157 | I23: 45817 | N23: 45848 | P23: Kate Olivares | R23: Closed | S23: https://meliopayments.com/ | U23: Active | V23: 3275131 | W23: Kate Olivares | X23: Closed Won | Y23: {=XLOOKUP(V23,'Lifetime Summary Stats'!A:A,'Lifetime Summary Stats'!A:A)} -> 3275131
A24: 006UU00000MQpnI | B24: METI Dallas, LLC - SMB | C24: 001UU00000NkUpf | D24: METI Dallas, LLC | E24: 0 | F24: 100 | G24: 0 | H24: 98 | I24: 45876 | N24: 45849 | P24: Kate Olivares | R24: Closed | S24: adwords | U24: Active | V24: 3997416 | W24: Kate Olivares | X24: Closed Won | Y24: {=XLOOKUP(V24,'Lifetime Summary Stats'!A:A,'Lifetime Summary Stats'!A:A)} -> 3997416
A25: 006UU00000MQpnE | B25: Wheatland Health Community Care, Inc. - SMB | C25: 001UU00000NkU88 | D25: Wheatland Health Community Care, Inc. | E25: 25 | F25: 100 | G25: 0 | H25: 125 | I25: 45849 | N25: 45849 | P25: Kate Olivares | R25: Closed | S25: adwords | T25: Active | V25: 4011819 | W25: Kate Olivares | X25: Closed Won | Y25: {=XLOOKUP(V25,'Lifetime Summary Stats'!A:A,'Lifetime Summary Stats'!A:A)} -> 4011819
A26: 006UU00000MQpnG | B26: Infinity Solar USA - SMB | C26: 001UU00000NrO8c | D26: Infinity Solar USA | E26: 80 | F26: 100 | G26: 14 | H26: 135 | I26: 45839 | N26: 45853 | P26: Kate Olivares | R26: Closed | S26: adwords | T26: Active | V26: 4010351 | W26: Kate Olivares | X26: Closed Won | Y26: {=XLOOKUP(V26,'Lifetime Summary Stats'!A:A,'Lifetime Summary Stats'!A:A)} -> 4010351
A27: 006UU00000MQpnF | B27: Roomrs - SMB | C27: 001UU00000NhKeB | D27: Roomrs | E27: 80 | F27: 100 | G27: 16 | H27: 136 | I27: 45838 | N27: 45854 | P27: Kate Olivares | R27: Closed | S27: google | T27: Churned | V27: 4011251 | W27: Kate Olivares | X27: Closed Won | Y27: {=XLOOKUP(V27,'Lifetime Summary Stats'!A:A,'Lifetime Summary Stats'!A:A)} -> 4011251
A28: 006UU00000MQpnV | B28: McCandless Group Strategies LLC - SMB | C28: 001UU00000MTjjg | D28: McCandless Group Strategies LLC | E28: 0 | F28: 100 | G28: 32 | H28: 150 | I28: 45824 | N28: 45856 | P28: Kate Olivares | R28: Closed | S28: adwords | T28: Churned | V28: 3782339 | W28: Kate Olivares | X28: Closed Won | Y28: {=XLOOKUP(V28,'Lifetime Summary Stats'!A:A,'Lifetime Summary Stats'!A:A)} -> 3782339
A29: 006UU00000MQpnD | B29: Expert Semiconductor Technology, inc - SMB | C29: 001UU00000NrswO | D29: Expert Semiconductor Technology, inc | E29: 80 | F29: 100 | G29: 41 | H29: 156 | I29: 45818 | N29: 45859 | P29: Kate Olivares | R29: Closed | S29: adwords | T29: Active | V29: 4018525 | W29: Kate Olivares | X29: Closed Won | Y29: {=XLOOKUP(V29,'Lifetime Summary Stats'!A:A,'Lifetime Summary Stats'!A:A)} -> 4018525
A30: 006UU00000MQpnQ | B30: Commercial Fire & Security - SMB | C30: 001UU00000OGV0A | D30: Commercial Fire & Security | E30: 0 | F30: 100 | G30: 23 | H30: 135 | I30: 45839 | N30: 45862 | P30: Kate Olivares | R30: Closed | S30: https://meliopayments.com/ | U30: Active | V30: 3958943 | W30: Kate Olivares | X30: Closed Won | Y30: {=XLOOKUP(V30,'Lifetime Summary Stats'!A:A,'Lifetime Summary Stats'!A:A)} -> 3958943
A31: 006UU00000MQpnC | B31: Lock Solid Storage - SMB | C31: 001UU00000OZvSv | D31: Lock Solid Storage | E31: 55 | F31: 100 | G31: 0 | H31: 105 | I31: 45869 | N31: 45869 | P31: Kate Olivares | R31: Closed | S31: adwords | T31: Churned | V31: 4027648 | W31: Kate Olivares | X31: Closed Won | Y31: {=XLOOKUP(V31,'Lifetime Summary Stats'!A:A,'Lifetime Summary Stats'!A:A)} -> 4027648
A32: 006UU00000MQpnB | B32: ANALYTICAL WATER SOLUTIONS INC. - SMB | C32: 001UU00000OZOzL | D32: ANALYTICAL WATER SOLUTIONS INC. | E32: 25 | F32: 100 | G32: 6 | H32: 104 | I32: 45870 | N32: 45876 | P32: Kate Olivares | R32: Closed | S32: google | T32: Active | U32: Active | V32: 4030970 | W32: Kate Olivares | X32: Closed Won | Y32: {=XLOOKUP(V32,'Lifetime Summary Stats'!A:A,'Lifetime Summary Stats'!A:A)} -> 4030970
A33: 006UU00000MQpnA | B33: CDT Construction - SMB | C33: 001UU00000OUuIN | D33: CDT Construction | E33: 80 | F33: 100 | G33: 38 | H33: 135 | I33: 45839 | N33: 45877 | P33: Kate Olivares | R33: Closed | S33: adwords | T33: Active | V33: 4038405 | W33: Kate Olivares | X33: Closed Won | Y33: {=XLOOKUP(V33,'Lifetime Summary Stats'!A:A,'Lifetime Summary Stats'!A:A)} -> 4038405
A34: 006UU00000MQpn9 | B34: Star Blue Interpreting Service, LLC - SMB | C34: 001UU00000ORzWJ | D34: Star Blue Interpreting Service, LLC | E34: 25 | F34: 100 | G34: 17 | H34: 111 | I34: 45863 | N34: 45880 | P34: Kate Olivares | R34: Closed | S34: direct | T34: Active | V34: 4039652 | W34: Kate Olivares | X34: Closed Won | Y34: {=XLOOKUP(V34,'Lifetime Summary Stats'!A:A,'Lifetime Summary Stats'!A:A)} -> 4039652
A35: 006UU00000MQpn8 | B35: Falkonry Inc - SMB | C35: 001UU00000OaMSP | D35: Falkonry Inc | E35: 80 | F35: 100 | G35: 54 | H35: 148 | I35: 45826 | N35: 45880 | P35: Kate Olivares | R35: Closed | S35: no source | T35: Churned | V35: 4044926 | W35: Kate Olivares | X35: Closed Won | Y35: {=XLOOKUP(V35,'Lifetime Summary Stats'!A:A,'Lifetime Summary Stats'!A:A)} -> 4044926
A36: 006UU00000MQpnH | B36: Coastal Speech Pathology, LLC. - SMB | C36: 001UU00000Nccry | D36: Coastal Speech Pathology, LLC. | E36: 25 | F36: 100 | G36: 14 | H36: 104 | I36: 45870 | N36: 45884 | P36: Kate Olivares | R36: Closed | S36: adwords | T36: Active | V36: 4008827 | W36: Kate Olivares | X36: Closed Won | Y36: {=XLOOKUP(V36,'Lifetime Summary Stats'!A:A,'Lifetime Summary Stats'!A:A)} -> 4008827
A37: 006UU00000MQpn7 | B37: Surgenex LLC. - SMB | C37: 001UU00000P5Aa0 | D37: Surgenex LLC. | E37: 0 | F37: 100 | G37: 14 | H37: 104 | I37: 45870 | N37: 45884 | P37: Kate Olivares | R37: Closed | S37: direct | U37: Churned | V37: 4064786 | W37: Kate Olivares | X37: Closed Won | Y37: {=XLOOKUP(V37,'Lifetime Summary Stats'!A:A,'Lifetime Summary Stats'!A:A)} -> #N/A
A38: 006UU00000MQpn6 | B38: L&M Mail & Courier - SMB | C38: 001UU00000PCStN | D38: L&M Mail & Courier | E38: 25 | F38: 100 | G38: 16 | H38: 94 | I38: 45880 | N38: 45896 | P38: Kate Olivares | R38: Closed | S38: google | T38: Active | U38: Active | V38: 4068848 | W38: Kate Olivares | X38: Closed Won | Y38: {=XLOOKUP(V38,'Lifetime Summary Stats'!A:A,'Lifetime Summary Stats'!A:A)} -> 4068848
A39: 006UU00000Lzkqr | B39: MAV Aqua LLC - SMB | C39: 001UU00000OCido | D39: MAV Aqua LLC | E39: 25 | F39: 100 | G39: 45 | H39: 118 | I39: 45856 | J39: 45870 | K39: 45899 | L39: 8/8 No need for addtl discount, since their budget is well above what we are offering. Core with 2 users will be $30 per month 7/28 Looking to see if they move forwrd w/melio or bill. follow up by EOW Demo set for 7/21 @ 4:15 PM | M39: 45915 | N39: 45901 | P39: Mass Niang | R39: Closed | S39: adwords | T39: Active | V39: 4031755 | W39: Kate Olivares | X39: Closed Won | Y39: {=XLOOKUP(V39,'Lifetime Summary Stats'!A:A,'Lifetime Summary Stats'!A:A)} -> 4031755
A40: 006UU00000MQpnW | B40: Piece of Cake - SMB | C40: 001UU00000Oei4Z | D40: Piece of Cake | E40: 55 | F40: 100 | G40: 87 | H40: 158 | I40: 45816 | N40: 45903 | P40: Kate Olivares | R40: Closed | S40: adwords | U40: Active | V40: 3328212 | W40: Kate Olivares | X40: Closed Won | Y40: {=XLOOKUP(V40,'Lifetime Summary Stats'!A:A,'Lifetime Summary Stats'!A:A)} -> 3328212
A41: 006UU00000Lzkqt | B41: Hope Harbor Partners OKC LP - SMB | C41: 001UU00000RE4nb | D41: Hope Harbor Partners OKC LP | E41: 25 | F41: 100 | G41: 1 | H41: 65 | I41: 45909 | J41: 45912 | K41: 45912 | M41: 45924 | N41: 45910 | O41: Upcision | P41: Mass Niang | R41: Closed | S41: direct | T41: Inactive | V41: 4136460 | W41: Mass Niang | X41: Closed Won | Y41: {=XLOOKUP(V41,'Lifetime Summary Stats'!A:A,'Lifetime Summary Stats'!A:A)} -> 4136460
A42: 006UU00000MQpn2 | B42: Brand Label Inc - SMB | C42: 001UU00000R1tZp | D42: Brand Label Inc | E42: 0 | F42: 100 | G42: 0 | H42: 50 | I42: 45924 | N42: 45918 | P42: Rudy Maestas | R42: Closed | S42: adwords | T42: Inactive | V42: 4111269 | W42: Mass Niang | X42: Closed Won | Y42: {=XLOOKUP(V42,'Lifetime Summary Stats'!A:A,'Lifetime Summary Stats'!A:A)} -> 4111269
A43: 006UU00000LKXgU | B43: MJM Construction - SMB | C43: 001UU00000RpsiC | D43: MJM Construction Enterprises, LLC | E43: 55 | F43: 100 | G43: 10 | H43: 27 | I43: 45937 | J43: 45951 | K43: 45951 | L43: Follow up with Steven to see how his payments went | M43: 45946 | N43: 45947 | O43: Calendly | P43: Dominic Bologna | R43: Closed | S43: google | T43: Active | V43: 4161223 | W43: Mass Niang | X43: Closed Won | Y43: {=XLOOKUP(V43,'Lifetime Summary Stats'!A:A,'Lifetime Summary Stats'!A:A)} -> 4161223
A44: 006UU00000LQDqM | B44: Grace Ventures LLC - SMB | C44: 001UU00000SCvqz | D44: Grace Ventures LLC | E44: 0 | F44: 100 | G44: 11 | H44: 24 | I44: 45939 | J44: 45944 | K44: 45944 | L44: Follow up scheduled with CX notes for account reactivation | M44: 45947 | N44: 45950 | O44: Calendly | P44: Dominic Bologna | R44: Closed | S44: adwords | V44: 4174641 | W44: Mass Niang | X44: Closed Won | Y44: {=XLOOKUP(V44,'Lifetime Summary Stats'!A:A,'Lifetime Summary Stats'!A:A)} -> #N/A
A45: 006UU00000Lzmje | B45: NextWave Co - SMB | C45: 001UU00000NoA8i | D45: NextWave Co | E45: 25 | F45: 100 | G45: 69 | H45: 21 | I45: 45884 | L45: Following up with Alan 8/22 | M45: 45919 | N45: 45953 | P45: Rudy Maestas | R45: Closed | S45: google | T45: Inactive | V45: 4016001 | W45: Mass Niang | X45: Closed Won | Y45: {=XLOOKUP(V45,'Lifetime Summary Stats'!A:A,'Lifetime Summary Stats'!A:A)} -> 4016001
A46: 006UU00000Lm7r7 | B46: White Mountain Construction - SMB | C46: 001UU000002cqGF | D46: White Mountain Construction | E46: 80 | F46: 100 | G46: 11 | H46: 16 | I46: 45947 | J46: 45960 | K46: 45960 | L46: Making an account and getting set up, following up on Monday 10/27 | M46: 45957 | N46: 45958 | O46: Platinum Form | P46: Dominic Bologna | R46: Closed | S46: adwords | T46: Active | U46: Active | V46: 3085000 | W46: Mass Niang | X46: Closed Won | Y46: {=XLOOKUP(V46,'Lifetime Summary Stats'!A:A,'Lifetime Summary Stats'!A:A)} -> 3085000
A47: 006UU00000LTAki | B47: TecTeam - SMB | C47: 001UU00000S1Dfr | D47: TecTeam LLC | E47: 0 | F47: 100 | G47: 18 | H47: 16 | I47: 45940 | J47: 45960 | K47: 45960 | L47: Held demo, created an account and will have office manager make payments | M47: 45957 | N47: 45958 | O47: Calendly | P47: Dominic Bologna | R47: Closed | S47: direct | T47: Active | V47: 4169152 | W47: Mass Niang | X47: Closed Won | Y47: {=XLOOKUP(V47,'Lifetime Summary Stats'!A:A,'Lifetime Summary Stats'!A:A)} -> 4169152
A48: 006UU00000LesGy | B48: Stillwater Communications - SMB | C48: 001UU00000S8tId | D48: Stillwater Communications | E48: 0 | F48: 100 | G48: 13 | H48: 16 | I48: 45945 | J48: 45960 | K48: 45960 | L48: Checking in to see if AR process has worked for him in absorbing CC fees on AR side | M48: 45957 | N48: 45958 | O48: Calendly | P48: Hunter Newcomb | R48: Closed | S48: adwords | U48: Active | V48: 4172812 | W48: Mass Niang | X48: Closed Won | Y48: {=XLOOKUP(V48,'Lifetime Summary Stats'!A:A,'Lifetime Summary Stats'!A:A)} -> #N/A
A49: 006UU00000L8MCA | B49: ROC Steel, LLC - SMB | C49: 001UU00000Rptny | D49: ROC Steel, LLC | E49: 75 | F49: 100 | G49: 27 | H49: 16 | I49: 45931 | J49: 45937 | K49: 45937 | L49: QBDT sync call scheduled for tuesday | M49: 45954 | N49: 45958 | O49: Calendly | P49: Hunter Newcomb | R49: Closed | S49: no source | T49: Active | V49: 4161378 | W49: Mass Niang | X49: Closed Won | Y49: {=XLOOKUP(V49,'Lifetime Summary Stats'!A:A,'Lifetime Summary Stats'!A:A)} -> 4161378
A50: 006UU00000MDrEj | B50: COR Equipment, LLC - SMB | C50: 001UU00000Rpto1 | D50: COR Equipment, LLC | E50: 0 | F50: 100 | G50: 0 | H50: 15 | I50: 45959 | N50: 45959 | P50: Mass Niang | R50: Closed | S50: no source | T50: Active | V50: 4161412 | W50: Mass Niang | X50: Closed Won | Y50: {=XLOOKUP(V50,'Lifetime Summary Stats'!A:A,'Lifetime Summary Stats'!A:A)} -> 4161412
A51: 006UU00000MGrux | B51: Harbor House Foundation - SMB | C51: 001UU00000RfuYG | D51: Harbor House Foundation | E51: 0 | F51: 100 | G51: 0 | H51: 14 | I51: 45960 | N51: 45960 | P51: Mass Niang | R51: Closed | S51: adwords | V51: 4140778 | W51: Mass Niang | X51: Closed Won | Y51: {=XLOOKUP(V51,'Lifetime Summary Stats'!A:A,'Lifetime Summary Stats'!A:A)} -> #N/A
